Workbook
Name Delivery_Cost: 'Master Data'!$B$142:$B$196
Name Labour_Cost: 'Master Data'!$B$111
Name Labour_Cost_Working: 'Master Data'!$X$109
Name Maruthi_Plastics_Packing_Material_Cost: 'Master Data'!$D$201
Name Masala_and_Blends_Costings: 'Master Data'!$A$551
Name No._Of_Units_Of_PM_Required_for_Selected_Retail_Packs: 'Master Data'!$C$322
Name Packaging_Cost: 'Master Data'!$B$115:$B$139
Name Raw_Material_Cost: 'Master Data'!$B$22:$B$110
Name Raw_Material_source_costs: 'Master Data'!$453:$541
Name Size_in_grams: 'Master Data'!$U$1171:$U$1180
Name Swiss_Pac_Packing_Material_Cost: 'Master Data'!$D$260
Name Vendor_Transport_Costs: 'Master Data'!$433:$447

Sheet Cost Sheet
A1: 1 | B1: =+A1+1 -> 2 | C1: =+B1+1 -> 3 | D1: =+C1+1 -> 4 | E1: =+D1+1 -> 5 | F1: =+E1+1 -> 6 | G1: =+F1+1 -> 7 | H1: =+G1+1 -> 8 | I1: =+H1+1 -> 9 | ... V1: =+U1+1 -> 22
A2: Sr. No. | B2: Item | C2: Name in Hindi | D2: Sources | E2: Landed Cost of Goods With GST Per Gm | F2: Landed Cost of Goods With GST Per Kg | G2: No. Of Retail Packs Per Kg | H2: No. Of Units Of PM Required for Selected Retail Packs | I2: Packing Material | J2: Packing Material for Shipping | K2: Shipping/Postage | L2: Miscellaneous Costs Percentage | M2: Qty per Pack | N2: Packaging Cost Per Retail Pack | O2: Packaging Cost With GST | P2: Cost of sticker with GST | Q2: Total Labour Cost | R2: Storage Cost | S2: Packaging Material for Shipping With GST | T2: Shipping/Postage With GST | U2: Miscellaneous Costs | V2: Total Cost Per Kg
A3: 1 | B3: Black Cardamom | C3: काली इलाइची | D3: =+VLOOKUP($B3,'Master Data'!$B$20:$W$197,2,FALSE) -> Ali Kikabai | E3: =+VLOOKUP($B3,'Master Data'!$B:$V,21,FALSE) -> 1.9586 | F3: =+E3*1000 -> 1958.6 | G3: 0.5 | H3: =+IF($G3=0.5,1,IF($G3=1,2,$G3)) -> 1 | I3: One side Transparent Stand Up with Zipper (25Gm-100Gm) | J3: Five Ply Box | K3: Surface Xpressbees 0.5Kg-Within City | L3: 15 | M3: =1000/G3 -> 2000 | N3: =+VLOOKUP($I3,'Master Data'!$B:$V,21,FALSE) -> 2.23 | O3: =+N3*H3 -> 2.23 | P3: =+'Master Data'!$W$127*$H3 -> 2.2 | Q3: =+'Master Data'!$W$111*$H3 -> 3.0769231 | R3: 0 | S3: =+VLOOKUP($J3,'Master Data'!$B:$V,21,FALSE)*$H3 -> 55.02 | T3: =+VLOOKUP($K3,'Master Data'!$B:$V,21,FALSE) -> 30 | U3: =+($F3+$O3+$P3+$S3)*($L3/100) -> 302.7075 | V3: =+$F3+$O3+$P3+$Q3+$R3+$S3+$T3+$U3 -> 2353.8344
A4: =+A3+1 -> 2 | B4: Green Cardamom | C4: इलायची | D4: Chandan Enterprise | E4: =+VLOOKUP($B4,'Master Data'!$B:$V,21,FALSE) -> 3.141 | F4: =+E4*1000 -> 3141 | G4: 1 | H4: =+IF($G4=0.5,1,IF($G4=1,2,$G4)) -> 2 | I4: One side Transparent Flat Bottom with Zipper (1000Gm) | J4: Recycle Box | K4: NA | L4: 25 | M4: =1000/G4 -> 1000 | N4: =+VLOOKUP($I4,'Master Data'!$B:$V,21,FALSE)*H4 -> 23.88 | O4: =+N4*G4 -> 23.88 | P4: =+'Master Data'!$W$127*$H4 -> 4.4 | Q4: =+'Master Data'!$W$111*$H4 -> 6.1538462 | R4: 0 | S4: =+VLOOKUP($J4,'Master Data'!$B:$V,21,FALSE)*$H4 -> 0 | T4: =+VLOOKUP($K4,'Master Data'!$B:$V,21,FALSE) -> #N/A | U4: =+($F4+$O4+$P4+$S4)*0.25 -> 792.32 | V4: =+$F4+$O4+$P4+$Q4+$R4+$S4+$T4+$U4 -> #N/A
A5: =+A4+1 -> 3 | B5: Cassia Cinnamon Flakes | C5: कासिया दालचीनी | D5: =+VLOOKUP($B5,'Master Data'!$B$20:$W$197,2,FALSE) -> #N/A | E5: =+VLOOKUP($B5,'Master Data'!$B:$V,21,FALSE) -> #N/A | F5: =+E5*1000 -> #N/A | G5: 1 | H5: =+IF($G5=0.5,2,IF($G5=1,4,$G5)) -> 4 | I5: Brown Kraft Paper with Window & Zipper (25Gm-100Gm) | J5: Bubble Pouch Small | K5: Surface Xpressbees 0.5Kg-Within City | L5: 15 | M5: =1000/G5 -> 1000 | N5: =+VLOOKUP($I5,'Master Data'!$B:$V,21,FALSE) -> 3.16 | O5: =+N5*G5 -> 3.16 | P5: =+'Master Data'!$W$127*$G5 -> 2.2 | Q5: =+'Master Data'!$W$111*$G5 -> 3.0769231 | R5: 0 | S5: =+VLOOKUP($J5,'Master Data'!$B:$V,21,FALSE)*$H5 -> 35.08 | T5: =+VLOOKUP($K5,'Master Data'!$B:$V,21,FALSE) -> 30 | U5: =+($F5+$O5+$P5+$S5)*0.15 -> #N/A | V5: =+$F5+$O5+$P5+$Q5+$R5+$S5+$T5+$U5 -> #N/A
A6: =+A5+1 -> 4 | B6: Cloves | C6: लौंग | D6: =+VLOOKUP($B6,'Master Data'!$B$20:$W$197,2,FALSE) -> Nadha Spices | E6: =+VLOOKUP($B6,'Master Data'!$B:$V,21,FALSE) -> 1.191 | F6: =+E6*1000 -> 1191 | G6: 40 | H6: =+IF($G6=0.5,1,IF($G6=1,1,$G6)) -> 40 | I6: Brown Kraft Paper with Window & Zipper (25Gm-100Gm) | J6: Bubble Pouch Medium | K6: Surface Xpressbees 1Kg-NE,J&K,KL,AN | L6: 40 | M6: =1000/G6 -> 25 | N6: =+VLOOKUP($I6,'Master Data'!$B:$V,21,FALSE) -> 3.16 | O6: =+N6*G6 -> 126.4 | P6: =+'Master Data'!$W$127*$G6 -> 88 | Q6: =+'Master Data'!$W$111*$G6 -> 123.07692 | R6: 0 | S6: =+VLOOKUP($J6,'Master Data'!$B:$V,21,FALSE)*$H6 -> 472 | T6: =+VLOOKUP($K6,'Master Data'!$B:$V,21,FALSE) -> 98 | U6: =+($F6+$O6+$P6+$S6)*0.15 -> 281.61 | V6: =+$F6+$O6+$P6+$Q6+$R6+$S6+$T6+$U6 -> 2380.0869
A7: =+A6+1 -> 5 | B7: Original Indian Bay Leaf | C7: तेज पत्ता | D7: =+VLOOKUP($B7,'Master Data'!$B$20:$W$197,2,FALSE) -> Ali Kikabai | E7: =+VLOOKUP($B7,'Master Data'!$B:$V,21,FALSE) -> 0.1736 | F7: =+E7*1000 -> 173.6 | G7: 1 | H7: =+IF($G7=0.5,2,IF($G7=1,4,$G7)) -> 4 | I7: Brown Kraft Paper with Window & Zipper (25Gm-100Gm) | J7: Bubble Pouch Small | K7: Surface Xpressbees 0.5Kg-Within City | L7: 15 | M7: =1000/G7 -> 1000 | N7: =+VLOOKUP($I7,'Master Data'!$B:$V,21,FALSE) -> 3.16 | O7: =+N7*G7 -> 3.16 | P7: =+'Master Data'!$W$127*$G7 -> 2.2 | Q7: =+'Master Data'!$W$111*$G7 -> 3.0769231 | R7: 0 | S7: =+VLOOKUP($J7,'Master Data'!$B:$V,21,FALSE)*$H7 -> 35.08 | T7: =+VLOOKUP($K7,'Master Data'!$B:$V,21,FALSE) -> 30 | U7: =+($F7+$O7+$P7+$S7)*0.15 -> 32.106 | V7: =+$F7+$O7+$P7+$Q7+$R7+$S7+$T7+$U7 -> 279.22292
A8: =+A7+1 -> 6 | B8: Original Kerala Cinnamon Flakes | C8: केरला दालचीनी | D8: =+VLOOKUP($B8,'Master Data'!$B$20:$W$197,2,FALSE) -> Eternal Blooms | E8: =+VLOOKUP($B8,'Master Data'!$B:$V,21,FALSE) -> 1.006 | F8: =+E8*1000 -> 1006 | G8: 1 | H8: =+IF($G8=0.5,2,IF($G8=1,4,$G8)) -> 4 | I8: Brown Kraft Paper with Window & Zipper (25Gm-100Gm) | J8: Bubble Pouch Small | K8: Surface Xpressbees 0.5Kg-Within City | L8: 15 | M8: =1000/G8 -> 1000 | N8: =+VLOOKUP($I8,'Master Data'!$B:$V,21,FALSE) -> 3.16 | O8: =+N8*G8 -> 3.16 | P8: =+'Master Data'!$W$127*$G8 -> 2.2 | Q8: =+'Master Data'!$W$111*$G8 -> 3.0769231 | R8: 0 | S8: =+VLOOKUP($J8,'Master Data'!$B:$V,21,FALSE)*$H8 -> 35.08 | T8: =+VLOOKUP($K8,'Master Data'!$B:$V,21,FALSE) -> 30 | U8: =+($F8+$O8+$P8+$S8)*0.15 -> 156.966 | V8: =+$F8+$O8+$P8+$Q8+$R8+$S8+$T8+$U8 -> 1236.4829
A9: =+A8+1 -> 7 | B9: Red Chilli Whole - Byadagi | C9: लाल मिर्च - ब्याडगी | D9: =+VLOOKUP($B9,'Master Data'!$B$20:$W$197,2,FALSE) -> MS Malagi | E9: =+VLOOKUP($B9,'Master Data'!$B:$V,21,FALSE) -> 0.611 | F9: =+E9*1000 -> 611 | G9: 1 | H9: =+IF($G9=0.5,2,IF($G9=1,4,$G9)) -> 4 | I9: Brown Kraft Paper with Window & Zipper (25Gm-100Gm) | J9: Bubble Pouch Small | K9: Surface Xpressbees 0.5Kg-Within City | L9: 15 | M9: =1000/G9 -> 1000 | N9: =+VLOOKUP($I9,'Master Data'!$B:$V,21,FALSE) -> 3.16 | O9: =+N9*G9 -> 3.16 | P9: =+'Master Data'!$W$127*$G9 -> 2.2 | Q9: =+'Master Data'!$W$111*$G9 -> 3.0769231 | R9: 0 | S9: =+VLOOKUP($J9,'Master Data'!$B:$V,21,FALSE)*$H9 -> 35.08 | T9: =+VLOOKUP($K9,'Master Data'!$B:$V,21,FALSE) -> 30 | U9: =+($F9+$O9+$P9+$S9)*0.15 -> 97.716 | V9: =+$F9+$O9+$P9+$Q9+$R9+$S9+$T9+$U9 -> 782.23292
A10: =+A9+1 -> 8 | B10: Red Chilli Whole - Kashmiri | C10: लाल मिर्च - कश्मीरी | D10: =+VLOOKUP($B10,'Master Data'!$B$20:$W$197,2,FALSE) -> MS Malagi | E10: =+VLOOKUP($B10,'Master Data'!$B:$V,21,FALSE) -> 0.641 | F10: =+E10*1000 -> 641 | G10: 1 | H10: =+IF($G10=0.5,2,IF($G10=1,4,$G10)) -> 4 | I10: Brown Kraft Paper with Window & Zipper (25Gm-100Gm) | J10: Bubble Pouch Small | K10: Surface Xpressbees 0.5Kg-Within City | L10: 15 | M10: =1000/G10 -> 1000 | N10: =+VLOOKUP($I10,'Master Data'!$B:$V,21,FALSE) -> 3.16 | O10: =+N10*G10 -> 3.16 | P10: =+'Master Data'!$W$127*$G10 -> 2.2 | Q10: =+'Master Data'!$W$111*$G10 -> 3.0769231 | R10: 0 | S10: =+VLOOKUP($J10,'Master Data'!$B:$V,21,FALSE)*$H10 -> 35.08 | T10: =+VLOOKUP($K10,'Master Data'!$B:$V,21,FALSE) -> 30 | U10: =+($F10+$O10+$P10+$S10)*0.15 -> 102.216 | V10: =+$F10+$O10+$P10+$Q10+$R10+$S10+$T10+$U10 -> 816.73292
A11: =+A10+1 -> 9 | B11: Black Pepper Whole | C11: काली मिर्च | D11: =+VLOOKUP($B11,'Master Data'!$B$20:$W$197,2,FALSE) -> Nadha Spices | E11: =+VLOOKUP($B11,'Master Data'!$B:$V,21,FALSE) -> 0.881 | F11: =+E11*1000 -> 881 | G11: 1 | H11: =+IF($G11=0.5,1,IF($G11=1,1,$G11)) -> 1 | I11: Brown Kraft Paper with Window & Zipper (25Gm-100Gm) | J11: Bubble Pouch Small | K11: Surface Xpressbees 0.5Kg-Within City | L11: 15 | M11: =1000/G11 -> 1000 | N11: =+VLOOKUP($I11,'Master Data'!$B:$V,21,FALSE) -> 3.16 | O11: =+N11*G11 -> 3.16 | P11: =+'Master Data'!$W$127*$G11 -> 2.2 | Q11: =+'Master Data'!$W$111*$G11 -> 3.0769231 | R11: 0 | S11: =+VLOOKUP($J11,'Master Data'!$B:$V,21,FALSE)*$H11 -> 8.77 | T11: =+VLOOKUP($K11,'Master Data'!$B:$V,21,FALSE) -> 30 | U11: =+($F11+$O11+$P11+$S11)*0.15 -> 134.2695 | V11: =+$F11+$O11+$P11+$Q11+$R11+$S11+$T11+$U11 -> 1062.4764
A12: =+A11+1 -> 10 | B12: Coriander Seeds | C12: धनिया | D12: =+VLOOKUP($B12,'Master Data'!$B$20:$W$197,2,FALSE) -> Chandan Enterprise | E12: =+VLOOKUP($B12,'Master Data'!$B:$V,21,FALSE) -> 0.192 | F12: =+E12*1000 -> 192 | G12: 1 | H12: =+IF($G12=0.5,1,IF($G12=1,2,$G12)) -> 2 | I12: Brown Kraft Paper with Window & Zipper (25Gm-100Gm) | J12: Bubble Pouch Small | K12: Surface Xpressbees 0.5Kg-Within City | L12: 15 | M12: =1000/G12 -> 1000 | N12: =+VLOOKUP($I12,'Master Data'!$B:$V,21,FALSE) -> 3.16 | O12: =+N12*G12 -> 3.16 | P12: =+'Master Data'!$W$127*$G12 -> 2.2 | Q12: =+'Master Data'!$W$111*$G12 -> 3.0769231 | R12: 0 | S12: =+VLOOKUP($J12,'Master Data'!$B:$V,21,FALSE)*$H12 -> 17.54 | T12: =+VLOOKUP($K12,'Master Data'!$B:$V,21,FALSE) -> 30 | U12: =+($F12+$O12+$P12+$S12)*0.15 -> 32.235 | V12: =+$F12+$O12+$P12+$Q12+$R12+$S12+$T12+$U12 -> 280.21192
A13: =+A12+1 -> 11 | B13: Cumin Seeds | C13: जीरा | D13: =+VLOOKUP($B13,'Master Data'!$B$20:$W$197,2,FALSE) -> Chandan Enterprise | E13: =+VLOOKUP($B13,'Master Data'!$B:$V,21,FALSE) -> 0.304 | F13: =+E13*1000 -> 304 | G13: 1 | H13: =+IF($G13=0.5,1,IF($G13=1,1,$G13)) -> 1 | I13: Brown Kraft Paper with Window & Zipper (25Gm-100Gm) | J13: Bubble Pouch Small | K13: Surface Xpressbees 0.5Kg-Within City | L13: 15 | M13: =1000/G13 -> 1000 | N13: =+VLOOKUP($I13,'Master Data'!$B:$V,21,FALSE) -> 3.16 | O13: =+N13*G13 -> 3.16 | P13: =+'Master Data'!$W$127*$G13 -> 2.2 | Q13: =+'Master Data'!$W$111*$G13 -> 3.0769231 | R13: 0 | S13: =+VLOOKUP($J13,'Master Data'!$B:$V,21,FALSE)*$H13 -> 8.77 | T13: =+VLOOKUP($K13,'Master Data'!$B:$V,21,FALSE) -> 30 | U13: =+($F13+$O13+$P13+$S13)*0.15 -> 47.7195 | V13: =+$F13+$O13+$P13+$Q13+$R13+$S13+$T13+$U13 -> 398.92642
A14: =+A13+1 -> 12 | B14: Mustard Seeds | C14: राइ | D14: =+VLOOKUP($B14,'Master Data'!$B$20:$W$197,2,FALSE) -> Chandan Enterprise | E14: =+VLOOKUP($B14,'Master Data'!$B:$V,21,FALSE) -> 0.132 | F14: =+E14*1000 -> 132 | G14: 1 | H14: =+IF($G14=0.5,1,IF($G14=1,1,$G14)) -> 1 | I14: Brown Kraft Paper with Window & Zipper (25Gm-100Gm) | J14: Bubble Pouch Small | K14: Surface Xpressbees 0.5Kg-Within City | L14: 15 | M14: =1000/G14 -> 1000 | N14: =+VLOOKUP($I14,'Master Data'!$B:$V,21,FALSE) -> 3.16 | O14: =+N14*G14 -> 3.16 | P14: =+'Master Data'!$W$127*$G14 -> 2.2 | Q14: =+'Master Data'!$W$111*$G14 -> 3.0769231 | R14: 0 | S14: =+VLOOKUP($J14,'Master Data'!$B:$V,21,FALSE)*$H14 -> 8.77 | T14: =+VLOOKUP($K14,'Master Data'!$B:$V,21,FALSE) -> 30 | U14: =+($F14+$O14+$P14+$S14)*0.15 -> 21.9195 | V14: =+$F14+$O14+$P14+$Q14+$R14+$S14+$T14+$U14 -> 201.12642
A15: =+A14+1 -> 13 | B15: Mace | C15: जावित्री | D15: =+VLOOKUP($B15,'Master Data'!$B$20:$W$197,2,FALSE) -> Eternal Blooms | E15: =+VLOOKUP($B15,'Master Data'!$B:$V,21,FALSE) -> 2.741 | F15: =+E15*1000 -> 2741 | G15: 1 | H15: =+IF($G15=0.5,2,IF($G15=1,4,$G15)) -> 4 | I15: Brown Kraft Paper with Window & Zipper (25Gm-100Gm) | J15: Bubble Pouch Small | K15: Surface Xpressbees 0.5Kg-Within City | L15: 15 | M15: =1000/G15 -> 1000 | N15: =+VLOOKUP($I15,'Master Data'!$B:$V,21,FALSE) -> 3.16 | O15: =+N15*G15 -> 3.16 | P15: =+'Master Data'!$W$127*$G15 -> 2.2 | Q15: =+'Master Data'!$W$111*$G15 -> 3.0769231 | R15: 0 | S15: =+VLOOKUP($J15,'Master Data'!$B:$V,21,FALSE)*$H15 -> 35.08 | T15: =+VLOOKUP($K15,'Master Data'!$B:$V,21,FALSE) -> 30 | U15: =+($F15+$O15+$P15+$S15)*0.15 -> 417.216 | V15: =+$F15+$O15+$P15+$Q15+$R15+$S15+$T15+$U15 -> 3231.7329
A16: =+A15+1 -> 14 | B16: Nutmeg | C16: जायफल | D16: =+VLOOKUP($B16,'Master Data'!$B$20:$W$197,2,FALSE) -> Nadha Spices | E16: =+VLOOKUP($B16,'Master Data'!$B:$V,21,FALSE) -> 0.941 | F16: =+E16*1000 -> 941 | G16: 1 | H16: =+IF($G16=0.5,1,IF($G16=1,2,$G16)) -> 2 | I16: Brown Kraft Paper with Window & Zipper (25Gm-100Gm) | J16: Bubble Pouch Small | K16: Surface Xpressbees 0.5Kg-Within City | L16: 15 | M16: =1000/G16 -> 1000 | N16: =+VLOOKUP($I16,'Master Data'!$B:$V,21,FALSE) -> 3.16 | O16: =+N16*G16 -> 3.16 | P16: =+'Master Data'!$W$127*$G16 -> 2.2 | Q16: =+'Master Data'!$W$111*$G16 -> 3.0769231 | R16: 0 | S16: =+VLOOKUP($J16,'Master Data'!$B:$V,21,FALSE)*$H16 -> 17.54 | T16: =+VLOOKUP($K16,'Master Data'!$B:$V,21,FALSE) -> 30 | U16: =+($F16+$O16+$P16+$S16)*0.15 -> 144.585 | V16: =+$F16+$O16+$P16+$Q16+$R16+$S16+$T16+$U16 -> 1141.5619
A17: =+A16+1 -> 15 | B17: Star Anise | C17: चक्र फूल | D17: =+VLOOKUP($B17,'Master Data'!$B$20:$W$197,2,FALSE) -> Ali Kikabai | E17: =+VLOOKUP($B17,'Master Data'!$B:$V,21,FALSE) -> 0.5196 | F17: =+E17*1000 -> 519.6 | G17: 1 | H17: =+IF($G17=0.5,1,IF($G17=1,2,$G17)) -> 2 | I17: Brown Kraft Paper with Window & Zipper (25Gm-100Gm) | J17: Bubble Pouch Small | K17: Surface Xpressbees 0.5Kg-Within City | L17: 15 | M17: =1000/G17 -> 1000 | N17: =+VLOOKUP($I17,'Master Data'!$B:$V,21,FALSE) -> 3.16 | O17: =+N17*G17 -> 3.16 | P17: =+'Master Data'!$W$127*$G17 -> 2.2 | Q17: =+'Master Data'!$W$111*$G17 -> 3.0769231 | R17: 0 | S17: =+VLOOKUP($J17,'Master Data'!$B:$V,21,FALSE)*$H17 -> 17.54 | T17: =+VLOOKUP($K17,'Master Data'!$B:$V,21,FALSE) -> 30 | U17: =+($F17+$O17+$P17+$S17)*0.15 -> 81.375 | V17: =+$F17+$O17+$P17+$Q17+$R17+$S17+$T17+$U17 -> 656.95192
A18: =+A17+1 -> 16 | B18: Black Pepper Powder | C18: काली मिर्च पाउडर | D18: In House Production | E18: =+VLOOKUP($B18,#REF!,2,FALSE)/100 -> #REF! | F18: =+E18*1000 -> #REF! | G18: 1 | H18: =+IF($G18=0.5,1,IF($G18=1,1,$G18)) -> 1 | I18: Brown Kraft Paper with Window & Zipper (25Gm-100Gm) | J18: Bubble Pouch Small | K18: Surface Xpressbees 0.5Kg-Within City | L18: 15 | M18: =1000/G18 -> 1000 | N18: =+VLOOKUP($I18,'Master Data'!$B:$V,21,FALSE) -> 3.16 | O18: =+N18*G18 -> 3.16 | P18: =+'Master Data'!$W$127*$G18 -> 2.2 | Q18: =+'Master Data'!$W$111*$G18 -> 3.0769231 | R18: 0 | S18: =+VLOOKUP($J18,'Master Data'!$B:$V,21,FALSE)*$H18 -> 8.77 | T18: =+VLOOKUP($K18,'Master Data'!$B:$V,21,FALSE) -> 30 | U18: =+($F18+$O18+$P18+$S18)*0.15 -> #REF! | V18: =+$F18+$O18+$P18+$Q18+$R18+$S18+$T18+$U18 -> #REF!
A19: =+A18+1 -> 17 | B19: Coriander Seeds Powder | C19: धनिया पाउडर | D19: In House Production | E19: =+VLOOKUP($B19,#REF!,2,FALSE)/100 -> #REF! | F19: =+E19*1000 -> #REF! | G19: 1 | H19: =+IF($G19=0.5,1,IF($G19=1,1,$G19)) -> 1 | I19: One side Transparent Stand Up with Zipper (25Gm-100Gm) | J19: Bubble Pouch Small | K19: Surface Xpressbees 0.5Kg-Within City | L19: 15 | M19: =1000/G19 -> 1000 | N19: =+VLOOKUP($I19,'Master Data'!$B:$V,21,FALSE) -> 2.23 | O19: =+N19*G19 -> 2.23 | P19: =+'Master Data'!$W$127*$G19 -> 2.2 | Q19: =+'Master Data'!$W$111*$G19 -> 3.0769231 | R19: 0 | S19: =+VLOOKUP($J19,'Master Data'!$B:$V,21,FALSE)*$H19 -> 8.77 | T19: =+VLOOKUP($K19,'Master Data'!$B:$V,21,FALSE) -> 30 | U19: =+($F19+$O19+$P19+$S19)*0.15 -> #REF! | V19: =+$F19+$O19+$P19+$Q19+$R19+$S19+$T19+$U19 -> #REF!
A20: =+A19+1 -> 18 | B20: Cumin Seeds Powder | C20: जीरा पाउडर | D20: In House Production | E20: =+VLOOKUP($B20,#REF!,2,FALSE)/100 -> #REF! | F20: =+E20*1000 -> #REF! | G20: 1 | H20: =+IF($G20=0.5,1,IF($G20=1,1,$G20)) -> 1 | I20: One side Transparent Stand Up with Zipper (25Gm-100Gm) | J20: Bubble Pouch Small | K20: Surface Xpressbees 0.5Kg-Within City | L20: 15 | M20: =1000/G20 -> 1000 | N20: =+VLOOKUP($I20,'Master Data'!$B:$V,21,FALSE) -> 2.23 | O20: =+N20*G20 -> 2.23 | P20: =+'Master Data'!$W$127*$G20 -> 2.2 | Q20: =+'Master Data'!$W$111*$G20 -> 3.0769231 | R20: 0 | S20: =+VLOOKUP($J20,'Master Data'!$B:$V,21,FALSE)*$H20 -> 8.77 | T20: =+VLOOKUP($K20,'Master Data'!$B:$V,21,FALSE) -> 30 | U20: =+($F20+$O20+$P20+$S20)*0.15 -> #REF! | V20: =+$F20+$O20+$P20+$Q20+$R20+$S20+$T20+$U20 -> #REF!
A21: =+A20+1 -> 19 | B21: Coriander Cumin Seeds Powder | C21: धनिया - जीरा पाउडर | D21: In House Production | E21: =+VLOOKUP($B21,#REF!,2,FALSE)/100 -> #REF! | F21: =+E21*1000 -> #REF! | G21: 1 | H21: =+IF($G21=0.5,1,IF($G21=1,1,$G21)) -> 1 | I21: One side Transparent Stand Up with Zipper (25Gm-100Gm) | J21: Bubble Pouch Small | K21: Surface Xpressbees 0.5Kg-Within City | L21: 15 | M21: =1000/G21 -> 1000 | N21: =+VLOOKUP($I21,'Master Data'!$B:$V,21,FALSE) -> 2.23 | O21: =+N21*G21 -> 2.23 | P21: =+'Master Data'!$W$127*$G21 -> 2.2 | Q21: =+'Master Data'!$W$111*$G21 -> 3.0769231 | R21: 0 | S21: =+VLOOKUP($J21,'Master Data'!$B:$V,21,FALSE)*$H21 -> 8.77 | T21: =+VLOOKUP($K21,'Master Data'!$B:$V,21,FALSE) -> 30 | U21: =+($F21+$O21+$P21+$S21)*0.15 -> #REF! | V21: =+$F21+$O21+$P21+$Q21+$R21+$S21+$T21+$U21 -> #REF!
A22: =+A21+1 -> 20 | B22: Red Chilli Powder - Mildly Spicy | C22: लाल मिर्च पाउडर – सौम्य मसालेदार | D22: =+VLOOKUP($B22,'Master Data'!$B$20:$W$197,2,FALSE) -> MS Malagi | E22: =+VLOOKUP($B22,'Master Data'!$B:$V,21,FALSE) -> 0.281 | F22: =+E22*1000 -> 281 | G22: 1 | H22: =+IF($G22=0.5,1,IF($G22=1,1,$G22)) -> 1 | I22: One side Transparent Stand Up with Zipper (25Gm-100Gm) | J22: Bubble Pouch Small | K22: Surface Xpressbees 0.5Kg-Within City | L22: 15 | M22: =1000/G22 -> 1000 | N22: =+VLOOKUP($I22,'Master Data'!$B:$V,21,FALSE) -> 2.23 | O22: =+N22*G22 -> 2.23 | P22: =+'Master Data'!$W$127*$G22 -> 2.2 | Q22: =+'Master Data'!$W$111*$G22 -> 3.0769231 | R22: 0 | S22: =+VLOOKUP($J22,'Master Data'!$B:$V,21,FALSE)*$H22 -> 8.77 | T22: =+VLOOKUP($K22,'Master Data'!$B:$V,21,FALSE) -> 30 | U22: =+($F22+$O22+$P22+$S22)*0.15 -> 44.13 | V22: =+$F22+$O22+$P22+$Q22+$R22+$S22+$T22+$U22 -> 371.40692
A23: =+A22+1 -> 21 | B23: Red Chilli Powder - Medium Spicy | C23: लाल मिर्च पाउडर मध्यम मसालेदार | D23: =+VLOOKUP($B23,'Master Data'!$B$20:$W$197,2,FALSE) -> MS Malagi | E23: =+VLOOKUP($B23,'Master Data'!$B:$V,21,FALSE) -> 0.286 | F23: =+E23*1000 -> 286 | G23: 1 | H23: =+IF($G23=0.5,1,IF($G23=1,1,$G23)) -> 1 | I23: One side Transparent Flat Bottom with Zipper (1000Gm) | J23: Recycle Box | K23: NA | L23: 15 | M23: =1000/G23 -> 1000 | N23: =+VLOOKUP($I23,'Master Data'!$B:$V,21,FALSE) -> 11.94 | O23: =+N23*G23 -> 11.94 | P23: =+'Master Data'!$W$127*$G23 -> 2.2 | Q23: =+'Master Data'!$W$111*$G23 -> 3.0769231 | R23: 0 | S23: =+VLOOKUP($J23,'Master Data'!$B:$V,21,FALSE)*$H23 -> 0 | T23: =+VLOOKUP($K23,'Master Data'!$B:$V,21,FALSE) -> #N/A | U23: =+($F23+$O23+$P23+$S23)*0.15 -> 45.021 | V23: =+$F23+$O23+$P23+$Q23+$R23+$S23+$T23+$U23 -> #N/A
A24: =+A23+1 -> 22 | B24: Red Chilli Powder - Very Spicy | C24: लाल मिर्च पाउडर – तीव्र मसालेदार | D24: =+VLOOKUP($B24,'Master Data'!$B$20:$W$197,2,FALSE) -> MS Malagi | E24: =+VLOOKUP($B24,'Master Data'!$B:$V,21,FALSE) -> 0.281 | F24: =+E24*1000 -> 281 | G24: 1 | H24: =+IF($G24=0.5,1,IF($G24=1,1,$G24)) -> 1 | I24: One side Transparent Stand Up with Zipper (25Gm-100Gm) | J24: Bubble Pouch Small | K24: Surface Xpressbees 0.5Kg-Within City | L24: 15 | M24: =1000/G24 -> 1000 | N24: =+VLOOKUP($I24,'Master Data'!$B:$V,21,FALSE) -> 2.23 | O24: =+N24*G24 -> 2.23 | P24: =+'Master Data'!$W$127*$G24 -> 2.2 | Q24: =+'Master Data'!$W$111*$G24 -> 3.0769231 | R24: 0 | S24: =+VLOOKUP($J24,'Master Data'!$B:$V,21,FALSE)*$H24 -> 8.77 | T24: =+VLOOKUP($K24,'Master Data'!$B:$V,21,FALSE) -> 30 | U24: =+($F24+$O24+$P24+$S24)*0.15 -> 44.13 | V24: =+$F24+$O24+$P24+$Q24+$R24+$S24+$T24+$U24 -> 371.40692
A25: =+A24+1 -> 23 | B25: Red Chilli Powder - Premium Kashmiri | C25: लाल मिर्च पाउडर – प्रीमियम कश्मीरी | D25: =+VLOOKUP($B25,'Master Data'!$B$20:$W$197,2,FALSE) -> MS Malagi | E25: =+VLOOKUP($B25,'Master Data'!$B:$V,21,FALSE) -> 0.601 | F25: =+E25*1000 -> 601 | G25: 1 | H25: =+IF($G25=0.5,1,IF($G25=1,1,$G25)) -> 1 | I25: One side Transparent Stand Up with Zipper (25Gm-100Gm) | J25: Bubble Pouch Small | K25: Surface Xpressbees 0.5Kg-Within City | L25: 15 | M25: =1000/G25 -> 1000 | N25: =+VLOOKUP($I25,'Master Data'!$B:$V,21,FALSE) -> 2.23 | O25: =+N25*G25 -> 2.23 | P25: =+'Master Data'!$W$127*$G25 -> 2.2 | Q25: =+'Master Data'!$W$111*$G25 -> 3.0769231 | R25: 0 | S25: =+VLOOKUP($J25,'Master Data'!$B:$V,21,FALSE)*$H25 -> 8.77 | T25: =+VLOOKUP($K25,'Master Data'!$B:$V,21,FALSE) -> 30 | U25: =+($F25+$O25+$P25+$S25)*0.15 -> 92.13 | V25: =+$F25+$O25+$P25+$Q25+$R25+$S25+$T25+$U25 -> 739.40692
A26: =+A25+1 -> 24 | B26: Turmeric Powder - Erode | C26: हल्दी पाउडर - इरोड | D26: =+VLOOKUP($B26,'Master Data'!$B$20:$W$197,2,FALSE) -> SMR | E26: =+VLOOKUP($B26,'Master Data'!$B:$V,21,FALSE) -> 0.217 | F26: =+E26*1000 -> 217 | G26: 1 | H26: =+IF($G26=0.5,1,IF($G26=1,1,$G26)) -> 1 | I26: One side Transparent Stand Up with Zipper (25Gm-100Gm) | J26: Bubble Pouch Small | K26: Surface Xpressbees 0.5Kg-Within City | L26: 15 | M26: =1000/G26 -> 1000 | N26: =+VLOOKUP($I26,'Master Data'!$B:$V,21,FALSE) -> 2.23 | O26: =+N26*G26 -> 2.23 | P26: =+'Master Data'!$W$127*$G26 -> 2.2 | Q26: =+'Master Data'!$W$111*$G26 -> 3.0769231 | R26: 0 | S26: =+VLOOKUP($J26,'Master Data'!$B:$V,21,FALSE)*$H26 -> 8.77 | T26: =+VLOOKUP($K26,'Master Data'!$B:$V,21,FALSE) -> 30 | U26: =+($F26+$O26+$P26+$S26)*0.15 -> 34.53 | V26: =+$F26+$O26+$P26+$Q26+$R26+$S26+$T26+$U26 -> 297.80692
A27: =+A26+1 -> 25 | B27: Turmeric Powder - Lakadong | C27: हल्दी पाउडर - लकडोंग | D27: =+VLOOKUP($B27,'Master Data'!$B$20:$W$197,2,FALSE) -> Na Risa | E27: =+VLOOKUP($B27,'Master Data'!$B:$V,21,FALSE) -> 0.447 | F27: =+E27*1000 -> 447 | G27: 1 | H27: =+IF($G27=0.5,1,IF($G27=1,1,$G27)) -> 1 | I27: One side Transparent Stand Up with Zipper (25Gm-100Gm) | J27: Bubble Pouch Small | K27: Surface Xpressbees 0.5Kg-Within City | L27: 15 | M27: =1000/G27 -> 1000 | N27: =+VLOOKUP($I27,'Master Data'!$B:$V,21,FALSE) -> 2.23 | O27: =+N27*G27 -> 2.23 | P27: =+'Master Data'!$W$127*$G27 -> 2.2 | Q27: =+'Master Data'!$W$111*$G27 -> 3.0769231 | R27: 0 | S27: =+VLOOKUP($J27,'Master Data'!$B:$V,21,FALSE)*$H27 -> 8.77 | T27: =+VLOOKUP($K27,'Master Data'!$B:$V,21,FALSE) -> 30 | U27: =+($F27+$O27+$P27+$S27)*0.15 -> 69.03 | V27: =+$F27+$O27+$P27+$Q27+$R27+$S27+$T27+$U27 -> 562.30692
A28: =+A27+1 -> 26 | B28: Asafoetida | C28: हींग | D28: =+VLOOKUP($B28,'Master Data'!$B$20:$W$197,2,FALSE) -> Chandan Enterprise | E28: =+VLOOKUP($B28,'Master Data'!$B:$V,21,FALSE) -> 0.538 | F28: =+E28*1000 -> 538 | G28: 1 | H28: =+IF($G28=0.5,1,IF($G28=1,1,$G28)) -> 1 | I28: One side Transparent Stand Up with Zipper (25Gm-100Gm) | J28: Bubble Pouch Small | K28: Surface Xpressbees 0.5Kg-Within City | L28: 15 | M28: =1000/G28 -> 1000 | N28: =+VLOOKUP($I28,'Master Data'!$B:$V,21,FALSE) -> 2.23 | O28: =+N28*G28 -> 2.23 | P28: =+'Master Data'!$W$127*$G28 -> 2.2 | Q28: =+'Master Data'!$W$111*$G28 -> 3.0769231 | R28: 0 | S28: =+VLOOKUP($J28,'Master Data'!$B:$V,21,FALSE)*$H28 -> 8.77 | T28: =+VLOOKUP($K28,'Master Data'!$B:$V,21,FALSE) -> 30 | U28: =+($F28+$O28+$P28+$S28)*0.15 -> 82.68 | V28: =+$F28+$O28+$P28+$Q28+$R28+$S28+$T28+$U28 -> 666.95692
A29: =+A28+1 -> 27 | B29: Chaat Masala | C29: चाट मसाला | D29: In House Production | E29: =+VLOOKUP($B29,#REF!,2,FALSE)/100 -> #REF! | F29: =+E29*1000 -> #REF! | G29: 1 | H29: =+IF($G29=0.5,1,IF($G29=1,1,$G29)) -> 1 | I29: One side Transparent Stand Up with Zipper (25Gm-100Gm) | J29: Bubble Pouch Small | K29: Surface Xpressbees 0.5Kg-Within City | L29: 15 | M29: =1000/G29 -> 1000 | N29: =+VLOOKUP($I29,'Master Data'!$B:$V,21,FALSE) -> 2.23 | O29: =+N29*G29 -> 2.23 | P29: =+'Master Data'!$W$127*$G29 -> 2.2 | Q29: =+'Master Data'!$W$111*$G29 -> 3.0769231 | R29: 0 | S29: =+VLOOKUP($J29,'Master Data'!$B:$V,21,FALSE)*$H29 -> 8.77 | T29: =+VLOOKUP($K29,'Master Data'!$B:$V,21,FALSE) -> 30 | U29: =+($F29+$O29+$P29+$S29)*0.15 -> #REF! | V29: =+$F29+$O29+$P29+$Q29+$R29+$S29+$T29+$U29 -> #REF!
A30: =+A29+1 -> 28 | B30: Punjabi Chole Masala | C30: पंजाबी चना मसाला | D30: In House Production | E30: =+VLOOKUP($B30,#REF!,2,FALSE)/100 -> #REF! | F30: =+E30*1000 -> #REF! | G30: 40 | H30: =+IF($G30=0.5,1,IF($G30=1,1,$G30)) -> 40 | I30: Brown Kraft Paper with Window & Zipper (25Gm-100Gm) | J30: Recycle Box | K30: NA | L30: 15 | M30: =1000/G30 -> 25 | N30: =+VLOOKUP($I30,'Master Data'!$B:$V,21,FALSE) -> 3.16 | O30: =+N30*G30 -> 126.4 | P30: =+'Master Data'!$W$127*$G30 -> 88 | Q30: =+'Master Data'!$W$111*$G30 -> 123.07692 | R30: 0 | S30: =+VLOOKUP($J30,'Master Data'!$B:$V,21,FALSE)*$H30 -> 0 | T30: =+VLOOKUP($K30,'Master Data'!$B:$V,21,FALSE) -> #N/A | U30: =+($F30+$O30+$P30+$S30)*0.15 -> #REF! | V30: =+$F30+$O30+$P30+$Q30+$R30+$S30+$T30+$U30 -> #REF!
A31: =+A30+1 -> 29 | B31: Garam Masala | C31: गरम मसाला | D31: In House Production | E31: =+VLOOKUP($B31,#REF!,2,FALSE)/100 -> #REF! | F31: =+E31*1000 -> #REF! | G31: 1 | H31: =+IF($G31=0.5,1,IF($G31=1,1,$G31)) -> 1 | I31: One side Transparent Stand Up with Zipper (25Gm-100Gm) | J31: Bubble Pouch Small | K31: Surface Xpressbees 0.5Kg-Within City | L31: 15 | M31: =1000/G31 -> 1000 | N31: =+VLOOKUP($I31,'Master Data'!$B:$V,21,FALSE) -> 2.23 | O31: =+N31*G31 -> 2.23 | P31: =+'Master Data'!$W$127*$G31 -> 2.2 | Q31: =+'Master Data'!$W$111*$G31 -> 3.0769231 | R31: 0 | S31: =+VLOOKUP($J31,'Master Data'!$B:$V,21,FALSE)*$H31 -> 8.77 | T31: =+VLOOKUP($K31,'Master Data'!$B:$V,21,FALSE) -> 30 | U31: =+($F31+$O31+$P31+$S31)*0.15 -> #REF! | V31: =+$F31+$O31+$P31+$Q31+$R31+$S31+$T31+$U31 -> #REF!
A32: =+A31+1 -> 30 | B32: Rasam Masala Powder | C32: रसम मसाला | D32: In House Production | E32: =+VLOOKUP($B32,#REF!,2,FALSE)/100 -> #REF! | F32: =+E32*1000 -> #REF! | G32: 1 | H32: =+IF($G32=0.5,1,IF($G32=1,1,$G32)) -> 1 | I32: One side Transparent Stand Up with Zipper (25Gm-100Gm) | J32: Bubble Pouch Small | K32: Surface Xpressbees 0.5Kg-Within City | L32: 15 | M32: =1000/G32 -> 1000 | N32: =+VLOOKUP($I32,'Master Data'!$B:$V,21,FALSE) -> 2.23 | O32: =+N32*G32 -> 2.23 | P32: =+'Master Data'!$W$127*$G32 -> 2.2 | Q32: =+'Master Data'!$W$111*$G32 -> 3.0769231 | R32: 0 | S32: =+VLOOKUP($J32,'Master Data'!$B:$V,21,FALSE)*$H32 -> 8.77 | T32: =+VLOOKUP($K32,'Master Data'!$B:$V,21,FALSE) -> 30 | U32: =+($F32+$O32+$P32+$S32)*0.15 -> #REF! | V32: =+$F32+$O32+$P32+$Q32+$R32+$S32+$T32+$U32 -> #REF!
A33: =+A32+1 -> 31 | B33: Sambar Masala Powder | C33: सांभर मसाला | D33: In House Production | E33: =+VLOOKUP($B33,#REF!,2,FALSE)/100 -> #REF! | F33: =+E33*1000 -> #REF! | G33: 1 | H33: =+IF($G33=0.5,1,IF($G33=1,1,$G33)) -> 1 | I33: One side Transparent Stand Up with Zipper (25Gm-100Gm) | J33: Bubble Pouch Small | K33: Surface Xpressbees 0.5Kg-Within City | L33: 15 | M33: =1000/G33 -> 1000 | N33: =+VLOOKUP($I33,'Master Data'!$B:$V,21,FALSE) -> 2.23 | O33: =+N33*G33 -> 2.23 | P33: =+'Master Data'!$W$127*$G33 -> 2.2 | Q33: =+'Master Data'!$W$111*$G33 -> 3.0769231 | R33: 0 | S33: =+VLOOKUP($J33,'Master Data'!$B:$V,21,FALSE)*$H33 -> 8.77 | T33: =+VLOOKUP($K33,'Master Data'!$B:$V,21,FALSE) -> 30 | U33: =+($F33+$O33+$P33+$S33)*0.15 -> #REF! | V33: =+$F33+$O33+$P33+$Q33+$R33+$S33+$T33+$U33 -> #REF!
A34: =+A33+1 -> 32 | B34: Sabji Masala Powder | C34: सब्जी मसाला | D34: In House Production | E34: =+VLOOKUP($B34,#REF!,2,FALSE)/100 -> #REF! | F34: =+E34*1000 -> #REF! | G34: 1 | H34: =+IF($G34=0.5,1,IF($G34=1,1,$G34)) -> 1 | I34: One side Transparent Stand Up with Zipper (25Gm-100Gm) | J34: Bubble Pouch Small | K34: Surface Xpressbees 0.5Kg-Within City | L34: 15 | M34: =1000/G34 -> 1000 | N34: =+VLOOKUP($I34,'Master Data'!$B:$V,21,FALSE) -> 2.23 | O34: =+N34*G34 -> 2.23 | P34: =+'Master Data'!$W$127*$G34 -> 2.2 | Q34: =+'Master Data'!$W$111*$G34 -> 3.0769231 | R34: 0 | S34: =+VLOOKUP($J34,'Master Data'!$B:$V,21,FALSE)*$H34 -> 8.77 | T34: =+VLOOKUP($K34,'Master Data'!$B:$V,21,FALSE) -> 30 | U34: =+($F34+$O34+$P34+$S34)*0.15 -> #REF! | V34: =+$F34+$O34+$P34+$Q34+$R34+$S34+$T34+$U34 -> #REF!
A35: =+A34+1 -> 33 | B35: Pav Bhaji Masala | C35: पाव भाजी मसाला | D35: In House Production | E35: =+VLOOKUP($B35,#REF!,2,FALSE)/100 -> #REF! | F35: =+E35*1000 -> #REF! | G35: 1 | H35: =+IF($G35=0.5,1,IF($G35=1,1,$G35)) -> 1 | I35: One side Transparent Stand Up with Zipper (25Gm-100Gm) | J35: Bubble Pouch Small | K35: Surface Xpressbees 0.5Kg-Within City | L35: 15 | M35: =1000/G35 -> 1000 | N35: =+VLOOKUP($I35,'Master Data'!$B:$V,21,FALSE) -> 2.23 | O35: =+N35*G35 -> 2.23 | P35: =+'Master Data'!$W$127*$G35 -> 2.2 | Q35: =+'Master Data'!$W$111*$G35 -> 3.0769231 | R35: 0 | S35: =+VLOOKUP($J35,'Master Data'!$B:$V,21,FALSE)*$H35 -> 8.77 | T35: =+VLOOKUP($K35,'Master Data'!$B:$V,21,FALSE) -> 30 | U35: =+($F35+$O35+$P35+$S35)*0.15 -> #REF! | V35: =+$F35+$O35+$P35+$Q35+$R35+$S35+$T35+$U35 -> #REF!
A36: =+A35+1 -> 34 | B36: Bisibele Bhat Masala | C36: बिसिबेले भात मसाला | D36: In House Production | E36: =+VLOOKUP($B36,#REF!,2,FALSE)/100 -> #REF! | F36: =+E36*1000 -> #REF! | G36: 1 | H36: =+IF($G36=0.5,1,IF($G36=1,1,$G36)) -> 1 | I36: One side Transparent Stand Up with Zipper (25Gm-100Gm) | J36: Bubble Pouch Small | K36: Surface Xpressbees 0.5Kg-Within City | L36: 15 | M36: =1000/G36 -> 1000 | N36: =+VLOOKUP($I36,'Master Data'!$B:$V,21,FALSE) -> 2.23 | O36: =+N36*G36 -> 2.23 | P36: =+'Master Data'!$W$127*$G36 -> 2.2 | Q36: =+'Master Data'!$W$111*$G36 -> 3.0769231 | R36: 0 | S36: =+VLOOKUP($J36,'Master Data'!$B:$V,21,FALSE)*$H36 -> 8.77 | T36: =+VLOOKUP($K36,'Master Data'!$B:$V,21,FALSE) -> 30 | U36: =+($F36+$O36+$P36+$S36)*0.15 -> #REF! | V36: =+$F36+$O36+$P36+$Q36+$R36+$S36+$T36+$U36 -> #REF!
A37: =+A36+1 -> 35 | B37: Premium Chai Masala | C37: प्रीमियम चाय मसाला | D37: In House Production | E37: =+VLOOKUP($B37,#REF!,2,FALSE)/100 -> #REF! | F37: =+E37*1000 -> #REF! | G37: 1 | H37: =+IF($G37=0.5,1,IF($G37=1,1,$G37)) -> 1 | I37: Both Sides Metallic Stand Up Without Zipper (25Gm-100Gm) | J37: Bubble Pouch Small | K37: Surface Xpressbees 0.5Kg-Within City | L37: 15 | M37: =1000/G37 -> 1000 | N37: =+VLOOKUP($I37,'Master Data'!$B:$V,21,FALSE) -> 1.85 | O37: =+N37*G37 -> 1.85 | P37: =+'Master Data'!$W$127*$G37 -> 2.2 | Q37: =+'Master Data'!$W$111*$G37 -> 3.0769231 | R37: 0 | S37: =+VLOOKUP($J37,'Master Data'!$B:$V,21,FALSE)*$H37 -> 8.77 | T37: =+VLOOKUP($K37,'Master Data'!$B:$V,21,FALSE) -> 30 | U37: =+($F37+$O37+$P37+$S37)*0.15 -> #REF! | V37: =+$F37+$O37+$P37+$Q37+$R37+$S37+$T37+$U37 -> #REF!
A38: =+A37+1 -> 36 | B38: Premium Kashmiri Saffron | C38: प्रीमियम कश्मीरी केसर | D38: =+VLOOKUP($B38,'Master Data'!$B$20:$W$197,2,FALSE) -> True Ventures | E38: =+VLOOKUP($B38,'Master Data'!$B:$V,21,FALSE) -> 183.5 | F38: =+E38*1000 -> 183500 | G38: 1 | H38: =+IF($G38=0.5,1,IF($G38=1,1,$G38)) -> 1 | I38: Both Sides Metallic Stand Up Without Zipper (25Gm-100Gm) | J38: Bubble Pouch Small | K38: Surface Xpressbees 1Kg-Within City | L38: 15 | M38: =1000/G38 -> 1000 | N38: =+VLOOKUP($I38,'Master Data'!$B:$V,21,FALSE) -> 1.85 | O38: =+N38*G38 -> 1.85 | P38: =+'Master Data'!$W$127*$G38 -> 2.2 | Q38: =+'Master Data'!$W$111*$G38 -> 3.0769231 | R38: 0 | S38: =+VLOOKUP($J38,'Master Data'!$B:$V,21,FALSE)*$H38 -> 8.77 | T38: =+VLOOKUP($K38,'Master Data'!$B:$V,21,FALSE) -> 54 | U38: =+($F38+$O38+$P38+$S38)*0.15 -> 27526.923 | V38: =+$F38+$O38+$P38+$Q38+$R38+$S38+$T38+$U38 -> 211096.82
A39: =+A38+1 -> 37 | B39: Gun Powder - Without Garlic | C39: गन पाउडर चटनी | D39: In House Production | E39: =+VLOOKUP($B39,#REF!,2,FALSE)/100 -> #REF! | F39: =+E39*1000 -> #REF! | G39: 1 | H39: =+IF($G39=0.5,1,IF($G39=1,1,$G39)) -> 1 | I39: Both Sides Metallic Stand Up Without Zipper (25Gm-100Gm) | J39: Bubble Pouch Small | K39: Surface Xpressbees 0.5Kg-Within City | L39: 15 | M39: =1000/G39 -> 1000 | N39: =+VLOOKUP($I39,'Master Data'!$B:$V,21,FALSE) -> 1.85 | O39: =+N39*G39 -> 1.85 | P39: =+'Master Data'!$W$127*$G39 -> 2.2 | Q39: =+'Master Data'!$W$111*$G39 -> 3.0769231 | R39: 0 | S39: =+VLOOKUP($J39,'Master Data'!$B:$V,21,FALSE)*$H39 -> 8.77 | T39: =+VLOOKUP($K39,'Master Data'!$B:$V,21,FALSE) -> 30 | U39: =+($F39+$O39+$P39+$S39)*0.15 -> #REF! | V39: =+$F39+$O39+$P39+$Q39+$R39+$S39+$T39+$U39 -> #REF!
A40: =+A39+1 -> 38 | B40: Multi-grain Special Chutney Powder | C40: मल्टी ग्रेन स्पेशल चटनी पाउडर | D40: In House Production | E40: =+VLOOKUP($B40,#REF!,2,FALSE)/100 -> #REF! | F40: =+E40*1000 -> #REF! | G40: 1 | H40: =+IF($G40=0.5,1,IF($G40=1,1,$G40)) -> 1 | I40: Both Sides Metallic Stand Up Without Zipper (25Gm-100Gm) | J40: Bubble Pouch Small | K40: Surface Xpressbees 0.5Kg-Within City | L40: 15 | M40: =1000/G40 -> 1000 | N40: =+VLOOKUP($I40,'Master Data'!$B:$V,21,FALSE) -> 1.85 | O40: =+N40*G40 -> 1.85 | P40: =+'Master Data'!$W$127*$G40 -> 2.2 | Q40: =+'Master Data'!$W$111*$G40 -> 3.0769231 | R40: 0 | S40: =+VLOOKUP($J40,'Master Data'!$B:$V,21,FALSE)*$H40 -> 8.77 | T40: =+VLOOKUP($K40,'Master Data'!$B:$V,21,FALSE) -> 30 | U40: =+($F40+$O40+$P40+$S40)*0.15 -> #REF! | V40: =+$F40+$O40+$P40+$Q40+$R40+$S40+$T40+$U40 -> #REF!
A41: =+A40+1 -> 39 | B41: Peanut Chutney Powder - Without Garlic | C41: मूंगफली चटनी पाउडर | D41: In House Production | E41: =+VLOOKUP($B41,#REF!,2,FALSE)/100 -> #REF! | F41: =+E41*1000 -> #REF! | G41: 1 | H41: =+IF($G41=0.5,1,IF($G41=1,1,$G41)) -> 1 | I41: Both Sides Metallic Stand Up Without Zipper (25Gm-100Gm) | J41: Bubble Pouch Small | K41: Surface Xpressbees 0.5Kg-Within City | L41: 15 | M41: =1000/G41 -> 1000 | N41: =+VLOOKUP($I41,'Master Data'!$B:$V,21,FALSE) -> 1.85 | O41: =+N41*G41 -> 1.85 | P41: =+'Master Data'!$W$127*$G41 -> 2.2 | Q41: =+'Master Data'!$W$111*$G41 -> 3.0769231 | R41: 0 | S41: =+VLOOKUP($J41,'Master Data'!$B:$V,21,FALSE)*$H41 -> 8.77 | T41: =+VLOOKUP($K41,'Master Data'!$B:$V,21,FALSE) -> 30 | U41: =+($F41+$O41+$P41+$S41)*0.15 -> #REF! | V41: =+$F41+$O41+$P41+$Q41+$R41+$S41+$T41+$U41 -> #REF!
A42: =+A41+1 -> 40 | B42: Pulihora Masala Powder | C42: पुलिहोरा | D42: In House Production | E42: =+VLOOKUP($B42,#REF!,2,FALSE)/100 -> #REF! | F42: =+E42*1000 -> #REF! | G42: 1 | H42: =+IF($G42=0.5,1,IF($G42=1,1,$G42)) -> 1 | I42: Both Sides Metallic Stand Up Without Zipper (25Gm-100Gm) | J42: Bubble Pouch Small | K42: Surface Xpressbees 0.5Kg-Within City | L42: 15 | M42: =1000/G42 -> 1000 | N42: =+VLOOKUP($I42,'Master Data'!$B:$V,21,FALSE) -> 1.85 | O42: =+N42*G42 -> 1.85 | P42: =+'Master Data'!$W$127*$G42 -> 2.2 | Q42: =+'Master Data'!$W$111*$G42 -> 3.0769231 | R42: 0 | S42: =+VLOOKUP($J42,'Master Data'!$B:$V,21,FALSE)*$H42 -> 8.77 | T42: =+VLOOKUP($K42,'Master Data'!$B:$V,21,FALSE) -> 30 | U42: =+($F42+$O42+$P42+$S42)*0.15 -> #REF! | V42: =+$F42+$O42+$P42+$Q42+$R42+$S42+$T42+$U42 -> #REF!
A43: =+A42+1 -> 41 | B43: Multi-grain Metkut Powder | C43: मल्टीग्रैन मेतकूट पाउडर | D43: In House Production | E43: =+VLOOKUP($B43,#REF!,2,FALSE)/100 -> #REF! | F43: =+E43*1000 -> #REF! | G43: 1 | H43: =+IF($G43=0.5,1,IF($G43=1,1,$G43)) -> 1 | I43: One side Transparent Stand Up with Zipper (25Gm-100Gm) | J43: Bubble Pouch Small | K43: Surface Xpressbees 0.5Kg-Within City | L43: 15 | M43: =1000/G43 -> 1000 | N43: =+VLOOKUP($I43,'Master Data'!$B:$V,21,FALSE) -> 2.23 | O43: =+N43*G43 -> 2.23 | P43: =+'Master Data'!$W$127*$G43 -> 2.2 | Q43: =+'Master Data'!$W$111*$G43 -> 3.0769231 | R43: 0 | S43: =+VLOOKUP($J43,'Master Data'!$B:$V,21,FALSE)*$H43 -> 8.77 | T43: =+VLOOKUP($K43,'Master Data'!$B:$V,21,FALSE) -> 30 | U43: =+($F43+$O43+$P43+$S43)*0.15 -> #REF! | V43: =+$F43+$O43+$P43+$Q43+$R43+$S43+$T43+$U43 -> #REF!
A44: =+A43+1 -> 42 | B44: Immunity Booster | C44: इम्युनिटी बूस्टर | D44: In House Production | E44: =+VLOOKUP($B44,#REF!,2,FALSE)/100 -> #REF! | F44: =+E44*1000 -> #REF! | G44: 1 | H44: =+IF($G44=0.5,1,IF($G44=1,1,$G44)) -> 1 | I44: One side Transparent Stand Up with Zipper (25Gm-100Gm) | J44: Bubble Pouch Small | K44: Surface Xpressbees 0.5Kg-Within City | L44: 15 | M44: =1000/G44 -> 1000 | N44: =+VLOOKUP($I44,'Master Data'!$B:$V,21,FALSE) -> 2.23 | O44: =+N44*G44 -> 2.23 | P44: =+'Master Data'!$W$127*$G44 -> 2.2 | Q44: =+'Master Data'!$W$111*$G44 -> 3.0769231 | R44: 0 | S44: =+VLOOKUP($J44,'Master Data'!$B:$V,21,FALSE)*$H44 -> 8.77 | T44: =+VLOOKUP($K44,'Master Data'!$B:$V,21,FALSE) -> 30 | U44: =+($F44+$O44+$P44+$S44)*0.15 -> #REF! | V44: =+$F44+$O44+$P44+$Q44+$R44+$S44+$T44+$U44 -> #REF!
A45: =+A44+1 -> 43 | B45: Very Spicy Mango Pickle | C45: आम का अचार – तीव्र मसालेदार | E45: =+VLOOKUP($B45,'Master Data'!$B:$V,21,FALSE) -> 0.322 | F45: =+E45*1000 -> 322 | G45: 1 | H45: =+IF($G45=0.5,1,IF($G45=1,1,$G45)) -> 1 | I45: One side Transparent Flat Bottom with Zipper (1000Gm) | J45: Bubble Pouch Small | K45: Surface Xpressbees 0.5Kg-Within City | L45: 15 | M45: =1000/G45 -> 1000 | N45: =+VLOOKUP($I45,'Master Data'!$B:$V,21,FALSE) -> 11.94 | O45: =+N45*G45 -> 11.94 | P45: =+'Master Data'!$W$127*$G45 -> 2.2 | Q45: =+'Master Data'!$W$111*$G45 -> 3.0769231 | R45: 0 | S45: =+VLOOKUP($J45,'Master Data'!$B:$V,21,FALSE)*$H45 -> 8.77 | T45: =+VLOOKUP($K45,'Master Data'!$B:$V,21,FALSE) -> 30 | U45: =+($F45+$O45+$P45+$S45)*0.15 -> 51.7365 | V45: =+$F45+$O45+$P45+$Q45+$R45+$S45+$T45+$U45 -> 429.72342
A46: =+A45+1 -> 44 | B46: Kapok Buds | C46: मराठी मोग्गू | D46: =+VLOOKUP($B46,'Master Data'!$B$20:$W$197,2,FALSE) -> Amazon | E46: =+VLOOKUP($B46,'Master Data'!$B:$V,21,FALSE) -> 1.07 | F46: =+E46*1000 -> 1070 | G46: 1 | H46: =+IF($G46=0.5,1,IF($G46=1,2,$G46)) -> 2 | I46: One side Transparent Flat Bottom with Zipper (1000Gm) | J46: Bubble Pouch Small | K46: Surface Xpressbees 0.5Kg-Within City | L46: 15 | M46: =1000/G46 -> 1000 | N46: =+VLOOKUP($I46,'Master Data'!$B:$V,21,FALSE) -> 11.94 | O46: =+N46*G46 -> 11.94 | P46: =+'Master Data'!$W$127*$G46 -> 2.2 | Q46: =+'Master Data'!$W$111*$G46 -> 3.0769231 | R46: 0 | S46: =+VLOOKUP($J46,'Master Data'!$B:$V,21,FALSE)*$H46 -> 17.54 | T46: =+VLOOKUP($K46,'Master Data'!$B:$V,21,FALSE) -> 30 | U46: =+($F46+$O46+$P46+$S46)*0.15 -> 165.252 | V46: =+$F46+$O46+$P46+$Q46+$R46+$S46+$T46+$U46 -> 1300.0089
A47: =+A46+1 -> 45 | B47: Kabab Chini | C47: कबाब चीनी | D47: =+VLOOKUP($B47,'Master Data'!$B$20:$W$197,2,FALSE) -> Chandan Enterprise | E47: =+VLOOKUP($B47,'Master Data'!$B:$V,21,FALSE) -> 1.4135238 | F47: =+E47*1000 -> 1413.5238 | G47: 1 | H47: =+IF($G47=0.5,1,IF($G47=1,1,$G47)) -> 1 | I47: One side Transparent Flat Bottom with Zipper (1000Gm) | J47: Bubble Pouch Small | K47: Surface Xpressbees 0.5Kg-Within City | L47: 15 | M47: =1000/G47 -> 1000 | N47: =+VLOOKUP($I47,'Master Data'!$B:$V,21,FALSE) -> 11.94 | O47: =+N47*G47 -> 11.94 | P47: =+'Master Data'!$W$127*$G47 -> 2.2 | Q47: =+'Master Data'!$W$111*$G47 -> 3.0769231 | R47: 0 | S47: =+VLOOKUP($J47,'Master Data'!$B:$V,21,FALSE)*$H47 -> 8.77 | T47: =+VLOOKUP($K47,'Master Data'!$B:$V,21,FALSE) -> 30 | U47: =+($F47+$O47+$P47+$S47)*0.15 -> 215.46507 | V47: =+$F47+$O47+$P47+$Q47+$R47+$S47+$T47+$U47 -> 1684.9758
A48: =+A47+1 -> 46 | B48: Black Cumin | C48: काला जीरा | D48: =+VLOOKUP($B48,'Master Data'!$B$20:$W$197,2,FALSE) -> Chandan Enterprise | E48: =+VLOOKUP($B48,'Master Data'!$B:$V,21,FALSE) -> 1.1087619 | F48: =+E48*1000 -> 1108.7619 | G48: 1 | H48: =+IF($G48=0.5,1,IF($G48=1,1,$G48)) -> 1 | I48: One side Transparent Flat Bottom with Zipper (1000Gm) | J48: Bubble Pouch Small | K48: Surface Xpressbees 0.5Kg-Within City | L48: 15 | M48: =1000/G48 -> 1000 | N48: =+VLOOKUP($I48,'Master Data'!$B:$V,21,FALSE) -> 11.94 | O48: =+N48*G48 -> 11.94 | P48: =+'Master Data'!$W$127*$G48 -> 2.2 | Q48: =+'Master Data'!$W$111*$G48 -> 3.0769231 | R48: 0 | S48: =+VLOOKUP($J48,'Master Data'!$B:$V,21,FALSE)*$H48 -> 8.77 | T48: =+VLOOKUP($K48,'Master Data'!$B:$V,21,FALSE) -> 30 | U48: =+($F48+$O48+$P48+$S48)*0.15 -> 169.75079 | V48: =+$F48+$O48+$P48+$Q48+$R48+$S48+$T48+$U48 -> 1334.4996
A49: =+A48+1 -> 47 | B49: Stone Flower | C49: दगड़ फूल | D49: =+VLOOKUP($B49,'Master Data'!$B$20:$W$197,2,FALSE) -> Ali Kikabai | E49: =+VLOOKUP($B49,'Master Data'!$B:$V,21,FALSE) -> 0.4836 | F49: =+E49*1000 -> 483.6 | G49: 1 | H49: =+IF($G49=0.5,2,IF($G49=1,4,$G49)) -> 4 | I49: One side Transparent Flat Bottom with Zipper (1000Gm) | J49: Bubble Pouch Small | K49: Surface Xpressbees 0.5Kg-Within City | L49: 15 | M49: =1000/G49 -> 1000 | N49: =+VLOOKUP($I49,'Master Data'!$B:$V,21,FALSE) -> 11.94 | O49: =+N49*G49 -> 11.94 | P49: =+'Master Data'!$W$127*$G49 -> 2.2 | Q49: =+'Master Data'!$W$111*$G49 -> 3.0769231 | R49: 0 | S49: =+VLOOKUP($J49,'Master Data'!$B:$V,21,FALSE)*$H49 -> 35.08 | T49: =+VLOOKUP($K49,'Master Data'!$B:$V,21,FALSE) -> 30 | U49: =+($F49+$O49+$P49+$S49)*0.15 -> 79.923 | V49: =+$F49+$O49+$P49+$Q49+$R49+$S49+$T49+$U49 -> 645.81992
A50: =+A49+1 -> 48 | B50: Fenugreek Seeds | D50: =+VLOOKUP($B50,'Master Data'!$B$20:$W$197,2,FALSE) -> Chandan Enterprise | E50: =+VLOOKUP($B50,'Master Data'!$B:$V,21,FALSE) -> 0.1 | F50: =+E50*1000 -> 100 | G50: 1 | H50: =+IF($G50=0.5,1,IF($G50=1,1,$G50)) -> 1 | I50: One side Transparent Flat Bottom with Zipper (1000Gm) | J50: Bubble Pouch Small | K50: Surface Xpressbees 0.5Kg-Within City | L50: 15 | M50: =1000/G50 -> 1000 | N50: =+VLOOKUP($I50,'Master Data'!$B:$V,21,FALSE) -> 11.94 | O50: =+N50*G50 -> 11.94 | P50: =+'Master Data'!$W$127*$G50 -> 2.2 | Q50: =+'Master Data'!$W$111*$G50 -> 3.0769231 | R50: 0 | S50: =+VLOOKUP($J50,'Master Data'!$B:$V,21,FALSE)*$H50 -> 8.77 | T50: =+VLOOKUP($K50,'Master Data'!$B:$V,21,FALSE) -> 30 | U50: =+($F50+$O50+$P50+$S50)*0.15 -> 18.4365 | V50: =+$F50+$O50+$P50+$Q50+$R50+$S50+$T50+$U50 -> 174.42342
A51: =+A50+1 -> 49 | B51: Dried Fenugreek Leaves [Kasuri Methi] | D51: =+VLOOKUP($B51,'Master Data'!$B$20:$W$197,2,FALSE) -> Chandan Enterprise | E51: =+VLOOKUP($B51,'Master Data'!$B:$V,21,FALSE) -> 0.27 | F51: =+E51*1000 -> 270 | G51: 1 | H51: =+IF($G51=0.5,2,IF($G51=1,4,$G51)) -> 4 | I51: One side Transparent Flat Bottom with Zipper (1000Gm) | J51: Bubble Pouch Small | K51: Surface Xpressbees 0.5Kg-Within City | L51: 15 | M51: =1000/G51 -> 1000 | N51: =+VLOOKUP($I51,'Master Data'!$B:$V,21,FALSE) -> 11.94 | O51: =+N51*G51 -> 11.94 | P51: =+'Master Data'!$W$127*$G51 -> 2.2 | Q51: =+'Master Data'!$W$111*$G51 -> 3.0769231 | R51: 0 | S51: =+VLOOKUP($J51,'Master Data'!$B:$V,21,FALSE)*$H51 -> 35.08 | T51: =+VLOOKUP($K51,'Master Data'!$B:$V,21,FALSE) -> 30 | U51: =+($F51+$O51+$P51+$S51)*0.15 -> 47.883 | V51: =+$F51+$O51+$P51+$Q51+$R51+$S51+$T51+$U51 -> 400.17992
A52: =+A51+1 -> 50 | B52: Black Sesame Seeds [Til] | D52: =+VLOOKUP($B52,'Master Data'!$B$20:$W$197,2,FALSE) -> Chandan Enterprise | E52: =+VLOOKUP($B52,'Master Data'!$B:$V,21,FALSE) -> 0.365 | F52: =+E52*1000 -> 365 | G52: 1 | H52: =+IF($G52=0.5,1,IF($G52=1,1,$G52)) -> 1 | I52: One side Transparent Flat Bottom with Zipper (1000Gm) | J52: Bubble Pouch Small | K52: Surface Xpressbees 0.5Kg-Within City | L52: 15 | M52: =1000/G52 -> 1000 | N52: =+VLOOKUP($I52,'Master Data'!$B:$V,21,FALSE) -> 11.94 | O52: =+N52*G52 -> 11.94 | P52: =+'Master Data'!$W$127*$G52 -> 2.2 | Q52: =+'Master Data'!$W$111*$G52 -> 3.0769231 | R52: 0 | S52: =+VLOOKUP($J52,'Master Data'!$B:$V,21,FALSE)*$H52 -> 8.77 | T52: =+VLOOKUP($K52,'Master Data'!$B:$V,21,FALSE) -> 30 | U52: =+($F52+$O52+$P52+$S52)*0.15 -> 58.1865 | V52: =+$F52+$O52+$P52+$Q52+$R52+$S52+$T52+$U52 -> 479.17342
A53: =+A52+1 -> 51 | B53: White Sesame Seeds | D53: =+VLOOKUP($B53,'Master Data'!$B$20:$W$197,2,FALSE) -> Chandan Enterprise | E53: =+VLOOKUP($B53,'Master Data'!$B:$V,21,FALSE) -> 0.212 | F53: =+E53*1000 -> 212 | G53: 1 | H53: =+IF($G53=0.5,1,IF($G53=1,1,$G53)) -> 1 | I53: One side Transparent Flat Bottom with Zipper (1000Gm) | J53: Bubble Pouch Small | K53: Surface Xpressbees 0.5Kg-Within City | L53: 15 | M53: =1000/G53 -> 1000 | N53: =+VLOOKUP($I53,'Master Data'!$B:$V,21,FALSE) -> 11.94 | O53: =+N53*G53 -> 11.94 | P53: =+'Master Data'!$W$127*$G53 -> 2.2 | Q53: =+'Master Data'!$W$111*$G53 -> 3.0769231 | R53: 0 | S53: =+VLOOKUP($J53,'Master Data'!$B:$V,21,FALSE)*$H53 -> 8.77 | T53: =+VLOOKUP($K53,'Master Data'!$B:$V,21,FALSE) -> 30 | U53: =+($F53+$O53+$P53+$S53)*0.15 -> 35.2365 | V53: =+$F53+$O53+$P53+$Q53+$R53+$S53+$T53+$U53 -> 303.22342
A54: =+A53+1 -> 52 | B54: Dessicated Coconut Powder | D54: =+VLOOKUP($B54,'Master Data'!$B$20:$W$197,2,FALSE) -> Chandan Enterprise | E54: =+VLOOKUP($B54,'Master Data'!$B:$V,21,FALSE) -> 0.346 | F54: =+E54*1000 -> 346 | G54: 1 | H54: =+IF($G54=0.5,1,IF($G54=1,1,$G54)) -> 1 | I54: One side Transparent Flat Bottom with Zipper (1000Gm) | J54: Bubble Pouch Small | K54: Surface Xpressbees 0.5Kg-Within City | L54: 15 | M54: =1000/G54 -> 1000 | N54: =+VLOOKUP($I54,'Master Data'!$B:$V,21,FALSE) -> 11.94 | O54: =+N54*G54 -> 11.94 | P54: =+'Master Data'!$W$127*$G54 -> 2.2 | Q54: =+'Master Data'!$W$111*$G54 -> 3.0769231 | R54: 0 | S54: =+VLOOKUP($J54,'Master Data'!$B:$V,21,FALSE)*$H54 -> 8.77 | T54: =+VLOOKUP($K54,'Master Data'!$B:$V,21,FALSE) -> 30 | U54: =+($F54+$O54+$P54+$S54)*0.15 -> 55.3365 | V54: =+$F54+$O54+$P54+$Q54+$R54+$S54+$T54+$U54 -> 457.32342

Sheet Output Sheet
B5: Item | C5: Black Cardamom
B6: Sources | C6: =VLOOKUP($C5,'Production Cost'!$B$2:$D$79,3,FALSE) -> Ali Kikabai
B7: Packing Material for Shipping | C7: Five Ply Box
B8: Size in grams | C8: 1000
B9: Type | C9: Wholesale
B10: Vendor | C10: Maruthi Plastics
B11: Amount | C11: =(VALUE($C$8)*IF($C$6="In House Production",INDEX('Master Data'!$H$552:$J$576,MATCH($C$5,'Master Data'!$H$552:$H$576,0),3),VLOOKUP($C$5,'Master Data'!$B:$W,IF($C$9="Wholesale",21,22),FALSE)))+(VLOOKUP(IF($C$10="Maruthi Plastics",INDEX('Master Data'!$B$202:$L$255,MATCH($C$5,'Master Data'!$B$202:$B$255,0),MATCH(VALUE($C$8),'Master Data'!$B$202:$L$202,0)),INDEX('Master Data'!$B$261:$L$314,MATCH($C$5,'Master Data'!$B$261:$B$314,0),MATCH(VALUE($C$8),'Master Data'!$B$261:$L$261,0))),'Master Data'!$B:$W,IF($C$9="Wholesale",21,22),FALSE)*INDEX('Master Data'!$B$323:$K$376,MATCH($C$5,'Master Data'!$B$323:$B$376,0),MATCH(VALUE($C$8),'Master Data'!$B$323:$K$323,0)))+(IF($C$9="Wholesale",'Master Data'!$V$127*INDEX('Master Data'!$B$323:$K$376,MATCH($C$5,'Master Data'!$B$323:$B$376,0),MATCH(VALUE($C$8),'Master Data'!$B$323:$K$323,0)),'Master Data'!$W$127*INDEX('Master Data'!$B$323:$K$376,MATCH($C$5,'Master Data'!$B$323:$B$376,0),MATCH(VALUE($C$8),'Master Data'!$B$323:$K$323,0))))+(IF($C$9="Wholesale",'Master Data'!$V$111*INDEX('Master Data'!$B$323:$K$376,MATCH($C$5,'Master Data'!$B$323:$B$376,0),MATCH(VALUE($C$8),'Master Data'!$B$323:$K$323,0)),'Master Data'!$W$111*INDEX('Master Data'!$B$323:$K$376,MATCH($C$5,'Master Data'!$B$323:$B$376,0),MATCH(VALUE($C$8),'Master Data'!$B$323:$K$323,0))))+(IF(VALUE($C$8)=1000,'Master Data'!$AF$40,IF(VALUE($C$8)=500,'Master Data'!$AF$39,IF(VALUE($C$8)=250,'Master Data'!$AF$39,'Master Data'!$AF$38))))+(IF(VALUE($C$8)=1000,VLOOKUP($C$7,'Master Data'!$B:$W,IF($C$9="Wholesale",21,22),FALSE),IF(VALUE($C$8)=500,VLOOKUP($C$7,'Master Data'!$B:$W,IF($C$9="Wholesale",21,22),FALSE)/2,IF(VALUE($C$8)=250,VLOOKUP($C$7,'Master Data'!$B:$W,IF($C$9="Wholesale",21,22),FALSE)/3,IF(VALUE($C$8)=100,VLOOKUP($C$7,'Master Data'!$B:$W,IF($C$9="Wholesale",21,22),FALSE)/4,IF(VALUE($C$8)=50,VLOOKUP($C$7,'Master Data'!$B:$W,IF($C$9="Wholesale",21,22),FALSE)/6,IF(VALUE($C$8)=25,VLOOKUP($C$7,'Master Data'!$B:$W,IF($C$9="Wholesale",21,22),FALSE)/8,VLOOKUP($C$7,'Master Data'!$B:$W,IF($C$9="Wholesale",21,22),FALSE)/8)))))))+(IF(VALUE($C$8)=1000,'Master Data'!$AB$32,IF(VALUE($C$8)=500,'Master Data'!$AB$33,IF(VALUE($C$8)=250,'Master Data'!$AB$34,IF(VALUE($C$8)=100,'Master Data'!$AB$35,IF(VALUE($C$8)=50,'Master Data'!$AB$36,IF(VALUE($C$8)=25,'Master Data'!$AB$37,'Master Data'!$AB$38)))))))+(((VALUE($C$8)*IF($C$6="In House Production",INDEX('Master Data'!$H$552:$J$576,MATCH($C$5,'Master Data'!$H$552:$H$576,0),3),VLOOKUP($C$5,'Master Data'!$B:$W,IF($C$9="Wholesale",21,22),FALSE)))+(VLOOKUP(IF($C$10="Maruthi Plastics",INDEX('Master Data'!$B$202:$L$255,MATCH($C$5,'Master Data'!$B$202:$B$255,0),MATCH(VALUE($C$8),'Master Data'!$B$202:$L$202,0)),INDEX('Master Data'!$B$261:$L$314,MATCH($C$5,'Master Data'!$B$261:$B$314,0),MATCH(VALUE($C$8),'Master Data'!$B$261:$L$261,0))),'Master Data'!$B:$W,IF($C$9="Wholesale",21,22),FALSE)*INDEX('Master Data'!$B$323:$K$376,MATCH($C$5,'Master Data'!$B$323:$B$376,0),MATCH(VALUE($C$8),'Master Data'!$B$323:$K$323,0)))+(IF($C$9="Wholesale",'Master Data'!$V$127*INDEX('Master Data'!$B$323:$K$376,MATCH($C$5,'Master Data'!$B$323:$B$376,0),MATCH(VALUE($C$8),'Master Data'!$B$323:$K$323,0)),'Master Data'!$W$127*INDEX('Master Data'!$B$323:$K$376,MATCH($C$5,'Master Data'!$B$323:$B$376,0),MATCH(VALUE($C$8),'Master Data'!$B$323:$K$323,0))))+(IF(VALUE($C$8)=1000,VLOOKUP($C$7,'Master Data'!$B:$W,IF($C$9="Wholesale",21,22),FALSE),IF(VALUE($C$8)=500,VLOOKUP($C$7,'Master Data'!$B:$W,IF($C$9="Wholesale",21,22),FALSE)/2,IF(VALUE($C$8)=250,VLOOKUP($C$7,'Master Data'!$B:$W,IF($C$9="Wholesale",21,22),FALSE)/3,IF(VALUE($C$8)=100,VLOOKUP($C$7,'Master Data'!$B:$W,IF($C$9="Wholesale",21,22),FALSE)/4,IF(VALUE($C$8)=50,VLOOKUP($C$7,'Master Data'!$B:$W,IF($C$9="Wholesale",21,22),FALSE)/6,IF(VALUE($C$8)=25,VLOOKUP($C$7,'Master Data'!$B:$W,IF($C$9="Wholesale",21,22),FALSE)/8,VLOOKUP($C$7,'Master Data'!$B:$W,IF($C$9="Wholesale",21,22),FALSE)/8)))))))+(IF($C$9="Wholesale",'Master Data'!$V$111*INDEX('Master Data'!$B$323:$K$376,MATCH($C$5,'Master Data'!$B$323:$B$376,0),MATCH(VALUE($C$8),'Master Data'!$B$323:$K$323,0)),'Master Data'!$W$111*INDEX('Master Data'!$B$323:$K$376,MATCH($C$5,'Master Data'!$B$323:$B$376,0),MATCH(VALUE($C$8),'Master Data'!$B$323:$K$323,0)))))*(10/100)) -> 2320.5259

Sheet Production Cost
A1: Essence Retail Ventures Private Limited | L1: USA Packaging Cost-MRP Analysis
A2: Sr. No. | B2: Item | C2: Name in Hindi | D2: Sources | E2: Packing Material for Shipping | F2: Size in grams | G2: Type | H2: Vendor | I2: Shipping/Postage | J2: Miscellaneous Costs Percentage | K2: Landed Cost of Goods Per Gm | L2: No. Of Retail Packs Per Kg | M2: No. Of Units Of PM Required for Selected Retail Packs | N2: Packing Material | O2: Qty per Pack | P2: Packaging Cost Per Retail Pack | Q2: Total Packaging Cost | R2: Cost of sticker | S2: Total Labour Cost | T2: Storage Cost | U2: Packaging Material for Shipping | V2: Shipping/Postage | W2: New Shipping/Postage | X2: Miscellaneous Costs | Y2: Total Cost | Z2: Total Cost Per Pack | AA2: Total Cost with New Shipping
A3: 1 | B3: Black Cardamom | C3: काली इलाइची | D3: =+VLOOKUP($B3,'Master Data'!$B$20:$W$197,2,FALSE) -> Ali Kikabai | E3: Recycle Box | F3: 1000 | G3: Wholesale | H3: Maruthi Plastics | I3: Shree Maruthi Couriers-Local | J3: 20 | K3: =IF(D3="In House Production",INDEX('Master Data'!$H$552:$J$580,MATCH('Production Cost'!B3,'Master Data'!$H$552:$H$580,0),3),VLOOKUP($B3,'Master Data'!$B:$W,IF(G3="Wholesale",21,22),FALSE)) -> 1.9586 | L3: 1 | M3: =INDEX('Master Data'!$B$323:$K$376,MATCH('Production Cost'!$B3,'Master Data'!$B$323:$B$376,0),MATCH('Production Cost'!F$3,'Master Data'!$B$323:$K$323,0)) -> 2 | N3: =IF(H3="Maruthi Plastics",INDEX('Master Data'!$B$202:$L$255,MATCH('Production Cost'!B3,'Master Data'!$B$202:$B$255,0),MATCH('Production Cost'!F3,'Master Data'!$B$202:$L$202,0)),INDEX('Master Data'!$B$261:$L$314,MATCH('Production Cost'!B3,'Master Data'!$B$261:$B$314,0),MATCH('Production Cost'!F3,'Master Data'!$B$261:$L$261,0))) -> One side Transparent Flat Bottom with Zipper (1000Gm) | O3: =1000/L3 -> 1000 | P3: =+VLOOKUP($N3,'Master Data'!$B:$W,IF(G3="Wholesale",21,22),FALSE) -> 11.94 | Q3: =+P3*M3 -> 23.88 | R3: =IF(G3="Wholesale",'Master Data'!$V$127*$M3,'Master Data'!$W$127*$M3) -> 4.4 | S3: =IF(G3="Wholesale",'Master Data'!$V$111*$M3,'Master Data'!$W$111*$M3) -> 6.1538462 | T3: =IF(F3=1000,'Master Data'!$AF$40,IF(F3=500,'Master Data'!$AF$39,IF(F3=250,'Master Data'!$AF$39,'Master Data'!$AF$38))) -> 11.116667 | U3: =IF(F3=1000,VLOOKUP($E3,'Master Data'!$B:$W,IF(G3="Wholesale",21,22),FALSE),IF(F3=500,VLOOKUP($E3,'Master Data'!$B:$W,IF(G3="Wholesale",21,22),FALSE)/2,IF(F3=250,VLOOKUP($E3,'Master Data'!$B:$W,IF(G3="Wholesale",21,22),FALSE)/3,IF(F3=100,VLOOKUP($E3,'Master Data'!$B:$W,IF(G3="Wholesale",21,22),FALSE)/4,IF(F3=50,VLOOKUP($E3,'Master Data'!$B:$W,IF(G3="Wholesale",21,22),FALSE)/6,IF(F3=25,VLOOKUP($E3,'Master Data'!$B:$W,IF(G3="Wholesale",21,22),FALSE)/8,VLOOKUP($E3,'Master Data'!$B:$W,IF(G3="Wholesale",21,22),FALSE)/8)))))) -> 0 | V3: =+VLOOKUP($I3,'Master Data'!$B:$V,IF(G3="Wholesale",20,21),FALSE) -> 40 | W3: =IF(F3=1000,'Master Data'!$AB$32,IF(F3=500,'Master Data'!$AB$33,IF(F3=250,'Master Data'!$AB$34,IF(F3=100,'Master Data'!$AB$35,IF(F3=50,'Master Data'!$AB$36,IF(F3=25,'Master Data'!$AB$37,'Master Data'!$AB$38)))))) -> 56.55 | X3: =+((K3*F3)+$Q3+$R3+$U3+$S3+$T3+$W3)*($J3/100) -> 412.1401 | Y3: =+(F3*K3)+Q3+R3+S3+U3+(IF(F3=1000,V3,IF(F3=500,V3/2,IF(F3=250,V3/4,IF(F3=100,V3/10,IF(F3=50,V3/20,V3/40)))))+X3) -> 2445.1739 | Z3: =+Y3/L3 -> 2445.1739 | AA3: =(F3*K3)+Q3+R3+S3+T3+U3+W3+X3 -> 2472.8406 | AB3: =+((K3*F3)+$Q3+$R3+$U3+$S3+$T3)*($J3/100) -> 400.8301 | AC3: =(F3*K3)+Q3+R3+S3+T3+U3+AB3 -> 2404.9806 | AD3: =AC3*1.5 -> 3607.4709
A4: =+A3+1 -> 2 | B4: Green Cardamom | C4: इलायची | D4: =+VLOOKUP($B4,'Master Data'!$B$20:$W$197,2,FALSE) -> Nadha Spices | E4: Recycle Box | F4: 1000 | G4: Wholesale | H4: Maruthi Plastics | I4: Shree Maruthi Couriers-Local | J4: 20 | K4: =IF(D4="In House Production",INDEX('Master Data'!$H$552:$J$580,MATCH('Production Cost'!B4,'Master Data'!$H$552:$H$580,0),3),VLOOKUP($B4,'Master Data'!$B:$W,IF(G4="Wholesale",21,22),FALSE)) -> 3.141 | L4: 1 | M4: =INDEX('Master Data'!$B$323:$K$376,MATCH('Production Cost'!$B4,'Master Data'!$B$323:$B$376,0),MATCH('Production Cost'!F$3,'Master Data'!$B$323:$K$323,0)) -> 2 | N4: =IF(H4="Maruthi Plastics",INDEX('Master Data'!$B$202:$L$255,MATCH('Production Cost'!B4,'Master Data'!$B$202:$B$255,0),MATCH('Production Cost'!F4,'Master Data'!$B$202:$L$202,0)),INDEX('Master Data'!$B$261:$L$314,MATCH('Production Cost'!B4,'Master Data'!$B$261:$B$314,0),MATCH('Production Cost'!F4,'Master Data'!$B$261:$L$261,0))) -> One side Transparent Flat Bottom with Zipper (1000Gm) | O4: =1000/L4 -> 1000 | P4: =+VLOOKUP($N4,'Master Data'!$B:$W,IF(G4="Wholesale",21,22),FALSE) -> 11.94 | Q4: =+P4*M4 -> 23.88 | R4: =IF(G4="Wholesale",'Master Data'!$V$127*$M4,'Master Data'!$W$127*$M4) -> 4.4 | S4: =IF(G4="Wholesale",'Master Data'!$V$111*$M4,'Master Data'!$W$111*$M4) -> 6.1538462 | T4: =IF(F4=1000,'Master Data'!$AF$40,IF(F4=500,'Master Data'!$AF$39,IF(F4=250,'Master Data'!$AF$39,'Master Data'!$AF$38))) -> 11.116667 | U4: =IF(F4=1000,VLOOKUP($E4,'Master Data'!$B:$W,IF(G4="Wholesale",21,22),FALSE),IF(F4=500,VLOOKUP($E4,'Master Data'!$B:$W,IF(G4="Wholesale",21,22),FALSE)/2,IF(F4=250,VLOOKUP($E4,'Master Data'!$B:$W,IF(G4="Wholesale",21,22),FALSE)/3,IF(F4=100,VLOOKUP($E4,'Master Data'!$B:$W,IF(G4="Wholesale",21,22),FALSE)/4,IF(F4=50,VLOOKUP($E4,'Master Data'!$B:$W,IF(G4="Wholesale",21,22),FALSE)/6,IF(F4=25,VLOOKUP($E4,'Master Data'!$B:$W,IF(G4="Wholesale",21,22),FALSE)/8,VLOOKUP($E4,'Master Data'!$B:$W,IF(G4="Wholesale",21,22),FALSE)/8)))))) -> 0 | V4: =+VLOOKUP($I4,'Master Data'!$B:$V,IF(G4="Wholesale",20,21),FALSE) -> 40 | W4: =IF(F4=1000,'Master Data'!$AB$32,IF(F4=500,'Master Data'!$AB$33,IF(F4=250,'Master Data'!$AB$34,IF(F4=100,'Master Data'!$AB$35,IF(F4=50,'Master Data'!$AB$36,IF(F4=25,'Master Data'!$AB$37,'Master Data'!$AB$38)))))) -> 56.55 | X4: =+((K4*F4)+$Q4+$R4+$U4+S4)*($J4/100) -> 635.08677 | Y4: =+(F4*K4)+Q4+R4+S4+U4+(IF(F4=1000,V4,IF(F4=500,V4/2,IF(F4=250,V4/4,IF(F4=100,V4/10,IF(F4=50,V4/20,V4/40)))))+X4) -> 3850.5206 | Z4: =+Y4/L4 -> 3850.5206 | AA4: =(F4*K4)+Q4+R4+S4+T4+U4+W4+X4 -> 3878.1873 | AB4: =+((K4*F4)+$Q4+$R4+$U4+$S4+$T4)*($J4/100) -> 637.3101 | AC4: =(F4*K4)+Q4+R4+S4+T4+U4+AB4 -> 3823.8606 | AD4: =AC4*1.5 -> 5735.7909
A5: =+A4+1 -> 3 | B5: Cassia Cinnamon Rolls For Powdering | C5: कासिया दालचीनी | D5: =+VLOOKUP($B5,'Master Data'!$B$20:$W$197,2,FALSE) -> Ali Kikabai | E5: Recycle Box | F5: 1000 | G5: Wholesale | H5: Maruthi Plastics | I5: Shree Maruthi Couriers-Local | J5: 20 | K5: =IF(D5="In House Production",INDEX('Master Data'!$H$552:$J$580,MATCH('Production Cost'!B5,'Master Data'!$H$552:$H$580,0),3),VLOOKUP($B5,'Master Data'!$B:$W,IF(G5="Wholesale",21,22),FALSE)) -> 0.2886 | L5: 1 | M5: =INDEX('Master Data'!$B$323:$K$376,MATCH('Production Cost'!$B5,'Master Data'!$B$323:$B$376,0),MATCH('Production Cost'!F$3,'Master Data'!$B$323:$K$323,0)) -> 4 | N5: =IF(H5="Maruthi Plastics",INDEX('Master Data'!$B$202:$L$255,MATCH('Production Cost'!B5,'Master Data'!$B$202:$B$255,0),MATCH('Production Cost'!F5,'Master Data'!$B$202:$L$202,0)),INDEX('Master Data'!$B$261:$L$314,MATCH('Production Cost'!B5,'Master Data'!$B$261:$B$314,0),MATCH('Production Cost'!F5,'Master Data'!$B$261:$L$261,0))) -> One side Transparent Flat Bottom with Zipper (1000Gm) | O5: =1000/L5 -> 1000 | P5: =+VLOOKUP($N5,'Master Data'!$B:$W,IF(G5="Wholesale",21,22),FALSE) -> 11.94 | Q5: =+P5*M5 -> 47.76 | R5: =IF(G5="Wholesale",'Master Data'!$V$127*$M5,'Master Data'!$W$127*$M5) -> 8.8 | S5: =IF(G5="Wholesale",'Master Data'!$V$111*$M5,'Master Data'!$W$111*$M5) -> 12.307692 | T5: =IF(F5=1000,'Master Data'!$AF$40,IF(F5=500,'Master Data'!$AF$39,IF(F5=250,'Master Data'!$AF$39,'Master Data'!$AF$38))) -> 11.116667 | U5: =IF(F5=1000,VLOOKUP($E5,'Master Data'!$B:$W,IF(G5="Wholesale",21,22),FALSE),IF(F5=500,VLOOKUP($E5,'Master Data'!$B:$W,IF(G5="Wholesale",21,22),FALSE)/2,IF(F5=250,VLOOKUP($E5,'Master Data'!$B:$W,IF(G5="Wholesale",21,22),FALSE)/3,IF(F5=100,VLOOKUP($E5,'Master Data'!$B:$W,IF(G5="Wholesale",21,22),FALSE)/4,IF(F5=50,VLOOKUP($E5,'Master Data'!$B:$W,IF(G5="Wholesale",21,22),FALSE)/6,IF(F5=25,VLOOKUP($E5,'Master Data'!$B:$W,IF(G5="Wholesale",21,22),FALSE)/8,VLOOKUP($E5,'Master Data'!$B:$W,IF(G5="Wholesale",21,22),FALSE)/8)))))) -> 0 | V5: =+VLOOKUP($I5,'Master Data'!$B:$V,IF(G5="Wholesale",20,21),FALSE) -> 40 | W5: =IF(F5=1000,'Master Data'!$AB$32,IF(F5=500,'Master Data'!$AB$33,IF(F5=250,'Master Data'!$AB$34,IF(F5=100,'Master Data'!$AB$35,IF(F5=50,'Master Data'!$AB$36,IF(F5=25,'Master Data'!$AB$37,'Master Data'!$AB$38)))))) -> 56.55 | X5: =+((K5*F5)+$Q5+$R5+$U5+S5)*($J5/100) -> 71.493538 | Y5: =+(F5*K5)+Q5+R5+S5+U5+(IF(F5=1000,V5,IF(F5=500,V5/2,IF(F5=250,V5/4,IF(F5=100,V5/10,IF(F5=50,V5/20,V5/40)))))+X5) -> 468.96123 | Z5: =+Y5/L5 -> 468.96123 | AA5: =(F5*K5)+Q5+R5+S5+T5+U5+W5+X5 -> 496.6279 | AB5: =+((K5*F5)+$Q5+$R5+$U5+$S5+$T5)*($J5/100) -> 73.716872 | AC5: =(F5*K5)+Q5+R5+S5+T5+U5+AB5 -> 442.30123 | AD5: =AC5*1.5 -> 663.45185
A6: =+A5+1 -> 4 | B6: Cloves | C6: लौंग | D6: =+VLOOKUP($B6,'Master Data'!$B$20:$W$197,2,FALSE) -> Nadha Spices | E6: Recycle Box | F6: 1000 | G6: Wholesale | H6: Maruthi Plastics | I6: Shree Maruthi Couriers-Local | J6: 20 | K6: =IF(D6="In House Production",INDEX('Master Data'!$H$552:$J$580,MATCH('Production Cost'!B6,'Master Data'!$H$552:$H$580,0),3),VLOOKUP($B6,'Master Data'!$B:$W,IF(G6="Wholesale",21,22),FALSE)) -> 1.191 | L6: 1 | M6: =INDEX('Master Data'!$B$323:$K$376,MATCH('Production Cost'!$B6,'Master Data'!$B$323:$B$376,0),MATCH('Production Cost'!F$3,'Master Data'!$B$323:$K$323,0)) -> 2 | N6: =IF(H6="Maruthi Plastics",INDEX('Master Data'!$B$202:$L$255,MATCH('Production Cost'!B6,'Master Data'!$B$202:$B$255,0),MATCH('Production Cost'!F6,'Master Data'!$B$202:$L$202,0)),INDEX('Master Data'!$B$261:$L$314,MATCH('Production Cost'!B6,'Master Data'!$B$261:$B$314,0),MATCH('Production Cost'!F6,'Master Data'!$B$261:$L$261,0))) -> One side Transparent Flat Bottom with Zipper (1000Gm) | O6: =1000/L6 -> 1000 | P6: =+VLOOKUP($N6,'Master Data'!$B:$W,IF(G6="Wholesale",21,22),FALSE) -> 11.94 | Q6: =+P6*M6 -> 23.88 | R6: =IF(G6="Wholesale",'Master Data'!$V$127*$M6,'Master Data'!$W$127*$M6) -> 4.4 | S6: =IF(G6="Wholesale",'Master Data'!$V$111*$M6,'Master Data'!$W$111*$M6) -> 6.1538462 | T6: =IF(F6=1000,'Master Data'!$AF$40,IF(F6=500,'Master Data'!$AF$39,IF(F6=250,'Master Data'!$AF$39,'Master Data'!$AF$38))) -> 11.116667 | U6: =IF(F6=1000,VLOOKUP($E6,'Master Data'!$B:$W,IF(G6="Wholesale",21,22),FALSE),IF(F6=500,VLOOKUP($E6,'Master Data'!$B:$W,IF(G6="Wholesale",21,22),FALSE)/2,IF(F6=250,VLOOKUP($E6,'Master Data'!$B:$W,IF(G6="Wholesale",21,22),FALSE)/3,IF(F6=100,VLOOKUP($E6,'Master Data'!$B:$W,IF(G6="Wholesale",21,22),FALSE)/4,IF(F6=50,VLOOKUP($E6,'Master Data'!$B:$W,IF(G6="Wholesale",21,22),FALSE)/6,IF(F6=25,VLOOKUP($E6,'Master Data'!$B:$W,IF(G6="Wholesale",21,22),FALSE)/8,VLOOKUP($E6,'Master Data'!$B:$W,IF(G6="Wholesale",21,22),FALSE)/8)))))) -> 0 | V6: =+VLOOKUP($I6,'Master Data'!$B:$V,IF(G6="Wholesale",20,21),FALSE) -> 40 | W6: =IF(F6=1000,'Master Data'!$AB$32,IF(F6=500,'Master Data'!$AB$33,IF(F6=250,'Master Data'!$AB$34,IF(F6=100,'Master Data'!$AB$35,IF(F6=50,'Master Data'!$AB$36,IF(F6=25,'Master Data'!$AB$37,'Master Data'!$AB$38)))))) -> 56.55 | X6: =+((K6*F6)+$Q6+$R6+$U6+S6)*($J6/100) -> 245.08677 | Y6: =+(F6*K6)+Q6+R6+S6+U6+(IF(F6=1000,V6,IF(F6=500,V6/2,IF(F6=250,V6/4,IF(F6=100,V6/10,IF(F6=50,V6/20,V6/40)))))+X6) -> 1510.5206 | Z6: =+Y6/L6 -> 1510.5206 | AA6: =(F6*K6)+Q6+R6+S6+T6+U6+W6+X6 -> 1538.1873 | AB6: =+((K6*F6)+$Q6+$R6+$U6+$S6+$T6)*($J6/100) -> 247.3101 | AC6: =(F6*K6)+Q6+R6+S6+T6+U6+AB6 -> 1483.8606 | AD6: =AC6*1.5 -> 2225.7909
A7: =+A6+1 -> 5 | B7: Original Indian Bay Leaf | C7: तेज पत्ता | D7: =+VLOOKUP($B7,'Master Data'!$B$20:$W$197,2,FALSE) -> Ali Kikabai | E7: Recycle Box | F7: 1000 | G7: Wholesale | H7: Maruthi Plastics | I7: Shree Maruthi Couriers-Local | J7: 20 | K7: =IF(D7="In House Production",INDEX('Master Data'!$H$552:$J$580,MATCH('Production Cost'!B7,'Master Data'!$H$552:$H$580,0),3),VLOOKUP($B7,'Master Data'!$B:$W,IF(G7="Wholesale",21,22),FALSE)) -> 0.1736 | L7: 1 | M7: =INDEX('Master Data'!$B$323:$K$376,MATCH('Production Cost'!$B7,'Master Data'!$B$323:$B$376,0),MATCH('Production Cost'!F$3,'Master Data'!$B$323:$K$323,0)) -> 4 | N7: =IF(H7="Maruthi Plastics",INDEX('Master Data'!$B$202:$L$255,MATCH('Production Cost'!B7,'Master Data'!$B$202:$B$255,0),MATCH('Production Cost'!F7,'Master Data'!$B$202:$L$202,0)),INDEX('Master Data'!$B$261:$L$314,MATCH('Production Cost'!B7,'Master Data'!$B$261:$B$314,0),MATCH('Production Cost'!F7,'Master Data'!$B$261:$L$261,0))) -> One side Transparent Flat Bottom with Zipper (1000Gm) | O7: =1000/L7 -> 1000 | P7: =+VLOOKUP($N7,'Master Data'!$B:$W,IF(G7="Wholesale",21,22),FALSE) -> 11.94 | Q7: =+P7*M7 -> 47.76 | R7: =IF(G7="Wholesale",'Master Data'!$V$127*$M7,'Master Data'!$W$127*$M7) -> 8.8 | S7: =IF(G7="Wholesale",'Master Data'!$V$111*$M7,'Master Data'!$W$111*$M7) -> 12.307692 | T7: =IF(F7=1000,'Master Data'!$AF$40,IF(F7=500,'Master Data'!$AF$39,IF(F7=250,'Master Data'!$AF$39,'Master Data'!$AF$38))) -> 11.116667 | U7: =IF(F7=1000,VLOOKUP($E7,'Master Data'!$B:$W,IF(G7="Wholesale",21,22),FALSE),IF(F7=500,VLOOKUP($E7,'Master Data'!$B:$W,IF(G7="Wholesale",21,22),FALSE)/2,IF(F7=250,VLOOKUP($E7,'Master Data'!$B:$W,IF(G7="Wholesale",21,22),FALSE)/3,IF(F7=100,VLOOKUP($E7,'Master Data'!$B:$W,IF(G7="Wholesale",21,22),FALSE)/4,IF(F7=50,VLOOKUP($E7,'Master Data'!$B:$W,IF(G7="Wholesale",21,22),FALSE)/6,IF(F7=25,VLOOKUP($E7,'Master Data'!$B:$W,IF(G7="Wholesale",21,22),FALSE)/8,VLOOKUP($E7,'Master Data'!$B:$W,IF(G7="Wholesale",21,22),FALSE)/8)))))) -> 0 | V7: =+VLOOKUP($I7,'Master Data'!$B:$V,IF(G7="Wholesale",20,21),FALSE) -> 40 | W7: =IF(F7=1000,'Master Data'!$AB$32,IF(F7=500,'Master Data'!$AB$33,IF(F7=250,'Master Data'!$AB$34,IF(F7=100,'Master Data'!$AB$35,IF(F7=50,'Master Data'!$AB$36,IF(F7=25,'Master Data'!$AB$37,'Master Data'!$AB$38)))))) -> 56.55 | X7: =+((K7*F7)+$Q7+$R7+$U7+S7)*($J7/100) -> 48.493538 | Y7: =+(F7*K7)+Q7+R7+S7+U7+(IF(F7=1000,V7,IF(F7=500,V7/2,IF(F7=250,V7/4,IF(F7=100,V7/10,IF(F7=50,V7/20,V7/40)))))+X7) -> 330.96123 | Z7: =+Y7/L7 -> 330.96123 | AA7: =(F7*K7)+Q7+R7+S7+T7+U7+W7+X7 -> 358.6279 | AB7: =+((K7*F7)+$Q7+$R7+$U7+$S7+$T7)*($J7/100) -> 50.716872 | AC7: =(F7*K7)+Q7+R7+S7+T7+U7+AB7 -> 304.30123 | AD7: =AC7*1.5 -> 456.45185
A8: =+A7+1 -> 6 | B8: Original Kerala Cinnamon Flakes | C8: केरला दालचीनी | D8: =+VLOOKUP($B8,'Master Data'!$B$20:$W$197,2,FALSE) -> Eternal Blooms | E8: Recycle Box | F8: 1000 | G8: Wholesale | H8: Maruthi Plastics | I8: Shree Maruthi Couriers-Local | J8: 20 | K8: =IF(D8="In House Production",INDEX('Master Data'!$H$552:$J$580,MATCH('Production Cost'!B8,'Master Data'!$H$552:$H$580,0),3),VLOOKUP($B8,'Master Data'!$B:$W,IF(G8="Wholesale",21,22),FALSE)) -> 1.006 | L8: 1 | M8: =INDEX('Master Data'!$B$323:$K$376,MATCH('Production Cost'!$B8,'Master Data'!$B$323:$B$376,0),MATCH('Production Cost'!F$3,'Master Data'!$B$323:$K$323,0)) -> 4 | N8: =IF(H8="Maruthi Plastics",INDEX('Master Data'!$B$202:$L$255,MATCH('Production Cost'!B8,'Master Data'!$B$202:$B$255,0),MATCH('Production Cost'!F8,'Master Data'!$B$202:$L$202,0)),INDEX('Master Data'!$B$261:$L$314,MATCH('Production Cost'!B8,'Master Data'!$B$261:$B$314,0),MATCH('Production Cost'!F8,'Master Data'!$B$261:$L$261,0))) -> One side Transparent Flat Bottom with Zipper (1000Gm) | O8: =1000/L8 -> 1000 | P8: =+VLOOKUP($N8,'Master Data'!$B:$W,IF(G8="Wholesale",21,22),FALSE) -> 11.94 | Q8: =+P8*M8 -> 47.76 | R8: =IF(G8="Wholesale",'Master Data'!$V$127*$M8,'Master Data'!$W$127*$M8) -> 8.8 | S8: =IF(G8="Wholesale",'Master Data'!$V$111*$M8,'Master Data'!$W$111*$M8) -> 12.307692 | T8: =IF(F8=1000,'Master Data'!$AF$40,IF(F8=500,'Master Data'!$AF$39,IF(F8=250,'Master Data'!$AF$39,'Master Data'!$AF$38))) -> 11.116667 | U8: =IF(F8=1000,VLOOKUP($E8,'Master Data'!$B:$W,IF(G8="Wholesale",21,22),FALSE),IF(F8=500,VLOOKUP($E8,'Master Data'!$B:$W,IF(G8="Wholesale",21,22),FALSE)/2,IF(F8=250,VLOOKUP($E8,'Master Data'!$B:$W,IF(G8="Wholesale",21,22),FALSE)/3,IF(F8=100,VLOOKUP($E8,'Master Data'!$B:$W,IF(G8="Wholesale",21,22),FALSE)/4,IF(F8=50,VLOOKUP($E8,'Master Data'!$B:$W,IF(G8="Wholesale",21,22),FALSE)/6,IF(F8=25,VLOOKUP($E8,'Master Data'!$B:$W,IF(G8="Wholesale",21,22),FALSE)/8,VLOOKUP($E8,'Master Data'!$B:$W,IF(G8="Wholesale",21,22),FALSE)/8)))))) -> 0 | V8: =+VLOOKUP($I8,'Master Data'!$B:$V,IF(G8="Wholesale",20,21),FALSE) -> 40 | W8: =IF(F8=1000,'Master Data'!$AB$32,IF(F8=500,'Master Data'!$AB$33,IF(F8=250,'Master Data'!$AB$34,IF(F8=100,'Master Data'!$AB$35,IF(F8=50,'Master Data'!$AB$36,IF(F8=25,'Master Data'!$AB$37,'Master Data'!$AB$38)))))) -> 56.55 | X8: =+((K8*F8)+$Q8+$R8+$U8+S8)*($J8/100) -> 214.97354 | Y8: =+(F8*K8)+Q8+R8+S8+U8+(IF(F8=1000,V8,IF(F8=500,V8/2,IF(F8=250,V8/4,IF(F8=100,V8/10,IF(F8=50,V8/20,V8/40)))))+X8) -> 1329.8412 | Z8: =+Y8/L8 -> 1329.8412 | AA8: =(F8*K8)+Q8+R8+S8+T8+U8+W8+X8 -> 1357.5079 | AB8: =+((K8*F8)+$Q8+$R8+$U8+$S8+$T8)*($J8/100) -> 217.19687 | AC8: =(F8*K8)+Q8+R8+S8+T8+U8+AB8 -> 1303.1812 | AD8: =AC8*1.5 -> 1954.7718
A9: =+A8+1 -> 7 | B9: Red Chilli Whole - Byadagi | C9: लाल मिर्च - ब्याडगी | D9: =+VLOOKUP($B9,'Master Data'!$B$20:$W$197,2,FALSE) -> MS Malagi | E9: Recycle Box | F9: 1000 | G9: Wholesale | H9: Maruthi Plastics | I9: Shree Maruthi Couriers-Local | J9: 20 | K9: =IF(D9="In House Production",INDEX('Master Data'!$H$552:$J$580,MATCH('Production Cost'!B9,'Master Data'!$H$552:$H$580,0),3),VLOOKUP($B9,'Master Data'!$B:$W,IF(G9="Wholesale",21,22),FALSE)) -> 0.611 | L9: 1 | M9: =INDEX('Master Data'!$B$323:$K$376,MATCH('Production Cost'!$B9,'Master Data'!$B$323:$B$376,0),MATCH('Production Cost'!F$3,'Master Data'!$B$323:$K$323,0)) -> 4 | N9: =IF(H9="Maruthi Plastics",INDEX('Master Data'!$B$202:$L$255,MATCH('Production Cost'!B9,'Master Data'!$B$202:$B$255,0),MATCH('Production Cost'!F9,'Master Data'!$B$202:$L$202,0)),INDEX('Master Data'!$B$261:$L$314,MATCH('Production Cost'!B9,'Master Data'!$B$261:$B$314,0),MATCH('Production Cost'!F9,'Master Data'!$B$261:$L$261,0))) -> One side Transparent Flat Bottom with Zipper (1000Gm) | O9: =1000/L9 -> 1000 | P9: =+VLOOKUP($N9,'Master Data'!$B:$W,IF(G9="Wholesale",21,22),FALSE) -> 11.94 | Q9: =+P9*M9 -> 47.76 | R9: =IF(G9="Wholesale",'Master Data'!$V$127*$M9,'Master Data'!$W$127*$M9) -> 8.8 | S9: =IF(G9="Wholesale",'Master Data'!$V$111*$M9,'Master Data'!$W$111*$M9) -> 12.307692 | T9: =IF(F9=1000,'Master Data'!$AF$40,IF(F9=500,'Master Data'!$AF$39,IF(F9=250,'Master Data'!$AF$39,'Master Data'!$AF$38))) -> 11.116667 | U9: =IF(F9=1000,VLOOKUP($E9,'Master Data'!$B:$W,IF(G9="Wholesale",21,22),FALSE),IF(F9=500,VLOOKUP($E9,'Master Data'!$B:$W,IF(G9="Wholesale",21,22),FALSE)/2,IF(F9=250,VLOOKUP($E9,'Master Data'!$B:$W,IF(G9="Wholesale",21,22),FALSE)/3,IF(F9=100,VLOOKUP($E9,'Master Data'!$B:$W,IF(G9="Wholesale",21,22),FALSE)/4,IF(F9=50,VLOOKUP($E9,'Master Data'!$B:$W,IF(G9="Wholesale",21,22),FALSE)/6,IF(F9=25,VLOOKUP($E9,'Master Data'!$B:$W,IF(G9="Wholesale",21,22),FALSE)/8,VLOOKUP($E9,'Master Data'!$B:$W,IF(G9="Wholesale",21,22),FALSE)/8)))))) -> 0 | V9: =+VLOOKUP($I9,'Master Data'!$B:$V,IF(G9="Wholesale",20,21),FALSE) -> 40 | W9: =IF(F9=1000,'Master Data'!$AB$32,IF(F9=500,'Master Data'!$AB$33,IF(F9=250,'Master Data'!$AB$34,IF(F9=100,'Master Data'!$AB$35,IF(F9=50,'Master Data'!$AB$36,IF(F9=25,'Master Data'!$AB$37,'Master Data'!$AB$38)))))) -> 56.55 | X9: =+((K9*F9)+$Q9+$R9+$U9+S9)*($J9/100) -> 135.97354 | Y9: =+(F9*K9)+Q9+R9+S9+U9+(IF(F9=1000,V9,IF(F9=500,V9/2,IF(F9=250,V9/4,IF(F9=100,V9/10,IF(F9=50,V9/20,V9/40)))))+X9) -> 855.84123 | Z9: =+Y9/L9 -> 855.84123 | AA9: =(F9*K9)+Q9+R9+S9+T9+U9+W9+X9 -> 883.5079 | AB9: =+((K9*F9)+$Q9+$R9+$U9+$S9+$T9)*($J9/100) -> 138.19687 | AC9: =(F9*K9)+Q9+R9+S9+T9+U9+AB9 -> 829.18123 | AD9: =AC9*1.5 -> 1243.7718
A10: =+A9+1 -> 8 | B10: Red Chilli Whole - Kashmiri | C10: लाल मिर्च - कश्मीरी | D10: =+VLOOKUP($B10,'Master Data'!$B$20:$W$197,2,FALSE) -> MS Malagi | E10: Recycle Box | F10: 1000 | G10: Wholesale | H10: Maruthi Plastics | I10: Shree Maruthi Couriers-Local | J10: 20 | K10: =IF(D10="In House Production",INDEX('Master Data'!$H$552:$J$580,MATCH('Production Cost'!B10,'Master Data'!$H$552:$H$580,0),3),VLOOKUP($B10,'Master Data'!$B:$W,IF(G10="Wholesale",21,22),FALSE)) -> 0.641 | L10: 1 | M10: =INDEX('Master Data'!$B$323:$K$376,MATCH('Production Cost'!$B10,'Master Data'!$B$323:$B$376,0),MATCH('Production Cost'!F$3,'Master Data'!$B$323:$K$323,0)) -> 4 | N10: =IF(H10="Maruthi Plastics",INDEX('Master Data'!$B$202:$L$255,MATCH('Production Cost'!B10,'Master Data'!$B$202:$B$255,0),MATCH('Production Cost'!F10,'Master Data'!$B$202:$L$202,0)),INDEX('Master Data'!$B$261:$L$314,MATCH('Production Cost'!B10,'Master Data'!$B$261:$B$314,0),MATCH('Production Cost'!F10,'Master Data'!$B$261:$L$261,0))) -> One side Transparent Flat Bottom with Zipper (1000Gm) | O10: =1000/L10 -> 1000 | P10: =+VLOOKUP($N10,'Master Data'!$B:$W,IF(G10="Wholesale",21,22),FALSE) -> 11.94 | Q10: =+P10*M10 -> 47.76 | R10: =IF(G10="Wholesale",'Master Data'!$V$127*$M10,'Master Data'!$W$127*$M10) -> 8.8 | S10: =IF(G10="Wholesale",'Master Data'!$V$111*$M10,'Master Data'!$W$111*$M10) -> 12.307692 | T10: =IF(F10=1000,'Master Data'!$AF$40,IF(F10=500,'Master Data'!$AF$39,IF(F10=250,'Master Data'!$AF$39,'Master Data'!$AF$38))) -> 11.116667 | U10: =IF(F10=1000,VLOOKUP($E10,'Master Data'!$B:$W,IF(G10="Wholesale",21,22),FALSE),IF(F10=500,VLOOKUP($E10,'Master Data'!$B:$W,IF(G10="Wholesale",21,22),FALSE)/2,IF(F10=250,VLOOKUP($E10,'Master Data'!$B:$W,IF(G10="Wholesale",21,22),FALSE)/3,IF(F10=100,VLOOKUP($E10,'Master Data'!$B:$W,IF(G10="Wholesale",21,22),FALSE)/4,IF(F10=50,VLOOKUP($E10,'Master Data'!$B:$W,IF(G10="Wholesale",21,22),FALSE)/6,IF(F10=25,VLOOKUP($E10,'Master Data'!$B:$W,IF(G10="Wholesale",21,22),FALSE)/8,VLOOKUP($E10,'Master Data'!$B:$W,IF(G10="Wholesale",21,22),FALSE)/8)))))) -> 0 | V10: =+VLOOKUP($I10,'Master Data'!$B:$V,IF(G10="Wholesale",20,21),FALSE) -> 40 | W10: =IF(F10=1000,'Master Data'!$AB$32,IF(F10=500,'Master Data'!$AB$33,IF(F10=250,'Master Data'!$AB$34,IF(F10=100,'Master Data'!$AB$35,IF(F10=50,'Master Data'!$AB$36,IF(F10=25,'Master Data'!$AB$37,'Master Data'!$AB$38)))))) -> 56.55 | X10: =+((K10*F10)+$Q10+$R10+$U10+S10)*($J10/100) -> 141.97354 | Y10: =+(F10*K10)+Q10+R10+S10+U10+(IF(F10=1000,V10,IF(F10=500,V10/2,IF(F10=250,V10/4,IF(F10=100,V10/10,IF(F10=50,V10/20,V10/40)))))+X10) -> 891.84123 | Z10: =+Y10/L10 -> 891.84123 | AA10: =(F10*K10)+Q10+R10+S10+T10+U10+W10+X10 -> 919.5079 | AB10: =+((K10*F10)+$Q10+$R10+$U10+$S10+$T10)*($J10/100) -> 144.19687 | AC10: =(F10*K10)+Q10+R10+S10+T10+U10+AB10 -> 865.18123 | AD10: =AC10*1.5 -> 1297.7718
A11: =+A10+1 -> 9 | B11: Black Pepper Whole | C11: काली मिर्च | D11: =+VLOOKUP($B11,'Master Data'!$B$20:$W$197,2,FALSE) -> Nadha Spices | E11: Recycle Box | F11: 1000 | G11: Wholesale | H11: Maruthi Plastics | I11: Shree Maruthi Couriers-Local | J11: 20 | K11: =IF(D11="In House Production",INDEX('Master Data'!$H$552:$J$580,MATCH('Production Cost'!B11,'Master Data'!$H$552:$H$580,0),3),VLOOKUP($B11,'Master Data'!$B:$W,IF(G11="Wholesale",21,22),FALSE)) -> 0.881 | L11: 1 | M11: =INDEX('Master Data'!$B$323:$K$376,MATCH('Production Cost'!$B11,'Master Data'!$B$323:$B$376,0),MATCH('Production Cost'!F$3,'Master Data'!$B$323:$K$323,0)) -> 1 | N11: =IF(H11="Maruthi Plastics",INDEX('Master Data'!$B$202:$L$255,MATCH('Production Cost'!B11,'Master Data'!$B$202:$B$255,0),MATCH('Production Cost'!F11,'Master Data'!$B$202:$L$202,0)),INDEX('Master Data'!$B$261:$L$314,MATCH('Production Cost'!B11,'Master Data'!$B$261:$B$314,0),MATCH('Production Cost'!F11,'Master Data'!$B$261:$L$261,0))) -> One side Transparent Flat Bottom with Zipper (1000Gm) | O11: =1000/L11 -> 1000 | P11: =+VLOOKUP($N11,'Master Data'!$B:$W,IF(G11="Wholesale",21,22),FALSE) -> 11.94 | Q11: =+P11*M11 -> 11.94 | R11: =IF(G11="Wholesale",'Master Data'!$V$127*$M11,'Master Data'!$W$127*$M11) -> 2.2 | S11: =IF(G11="Wholesale",'Master Data'!$V$111*$M11,'Master Data'!$W$111*$M11) -> 3.0769231 | T11: =IF(F11=1000,'Master Data'!$AF$40,IF(F11=500,'Master Data'!$AF$39,IF(F11=250,'Master Data'!$AF$39,'Master Data'!$AF$38))) -> 11.116667 | U11: =IF(F11=1000,VLOOKUP($E11,'Master Data'!$B:$W,IF(G11="Wholesale",21,22),FALSE),IF(F11=500,VLOOKUP($E11,'Master Data'!$B:$W,IF(G11="Wholesale",21,22),FALSE)/2,IF(F11=250,VLOOKUP($E11,'Master Data'!$B:$W,IF(G11="Wholesale",21,22),FALSE)/3,IF(F11=100,VLOOKUP($E11,'Master Data'!$B:$W,IF(G11="Wholesale",21,22),FALSE)/4,IF(F11=50,VLOOKUP($E11,'Master Data'!$B:$W,IF(G11="Wholesale",21,22),FALSE)/6,IF(F11=25,VLOOKUP($E11,'Master Data'!$B:$W,IF(G11="Wholesale",21,22),FALSE)/8,VLOOKUP($E11,'Master Data'!$B:$W,IF(G11="Wholesale",21,22),FALSE)/8)))))) -> 0 | V11: =+VLOOKUP($I11,'Master Data'!$B:$V,IF(G11="Wholesale",20,21),FALSE) -> 40 | W11: =IF(F11=1000,'Master Data'!$AB$32,IF(F11=500,'Master Data'!$AB$33,IF(F11=250,'Master Data'!$AB$34,IF(F11=100,'Master Data'!$AB$35,IF(F11=50,'Master Data'!$AB$36,IF(F11=25,'Master Data'!$AB$37,'Master Data'!$AB$38)))))) -> 56.55 | X11: =+((K11*F11)+$Q11+$R11+$U11+S11)*($J11/100) -> 179.64338 | Y11: =+(F11*K11)+Q11+R11+S11+U11+(IF(F11=1000,V11,IF(F11=500,V11/2,IF(F11=250,V11/4,IF(F11=100,V11/10,IF(F11=50,V11/20,V11/40)))))+X11) -> 1117.8603 | Z11: =+Y11/L11 -> 1117.8603 | AA11: =(F11*K11)+Q11+R11+S11+T11+U11+W11+X11 -> 1145.527 | AB11: =+((K11*F11)+$Q11+$R11+$U11+$S11+$T11)*($J11/100) -> 181.86672 | AC11: =(F11*K11)+Q11+R11+S11+T11+U11+AB11 -> 1091.2003 | AD11: =AC11*1.5 -> 1636.8005
A12: =+A11+1 -> 10 | B12: Coriander Seeds | C12: धनिया | D12: =+VLOOKUP($B12,'Master Data'!$B$20:$W$197,2,FALSE) -> Chandan Enterprise | E12: Recycle Box | F12: 1000 | G12: Wholesale | H12: Maruthi Plastics | I12: Shree Maruthi Couriers-Local | J12: 20 | K12: =IF(D12="In House Production",INDEX('Master Data'!$H$552:$J$580,MATCH('Production Cost'!B12,'Master Data'!$H$552:$H$580,0),3),VLOOKUP($B12,'Master Data'!$B:$W,IF(G12="Wholesale",21,22),FALSE)) -> 0.192 | L12: 1 | M12: =INDEX('Master Data'!$B$323:$K$376,MATCH('Production Cost'!$B12,'Master Data'!$B$323:$B$376,0),MATCH('Production Cost'!F$3,'Master Data'!$B$323:$K$323,0)) -> 2 | N12: =IF(H12="Maruthi Plastics",INDEX('Master Data'!$B$202:$L$255,MATCH('Production Cost'!B12,'Master Data'!$B$202:$B$255,0),MATCH('Production Cost'!F12,'Master Data'!$B$202:$L$202,0)),INDEX('Master Data'!$B$261:$L$314,MATCH('Production Cost'!B12,'Master Data'!$B$261:$B$314,0),MATCH('Production Cost'!F12,'Master Data'!$B$261:$L$261,0))) -> One side Transparent Flat Bottom with Zipper (1000Gm) | O12: =1000/L12 -> 1000 | P12: =+VLOOKUP($N12,'Master Data'!$B:$W,IF(G12="Wholesale",21,22),FALSE) -> 11.94 | Q12: =+P12*M12 -> 23.88 | R12: =IF(G12="Wholesale",'Master Data'!$V$127*$M12,'Master Data'!$W$127*$M12) -> 4.4 | S12: =IF(G12="Wholesale",'Master Data'!$V$111*$M12,'Master Data'!$W$111*$M12) -> 6.1538462 | T12: =IF(F12=1000,'Master Data'!$AF$40,IF(F12=500,'Master Data'!$AF$39,IF(F12=250,'Master Data'!$AF$39,'Master Data'!$AF$38))) -> 11.116667 | U12: =IF(F12=1000,VLOOKUP($E12,'Master Data'!$B:$W,IF(G12="Wholesale",21,22),FALSE),IF(F12=500,VLOOKUP($E12,'Master Data'!$B:$W,IF(G12="Wholesale",21,22),FALSE)/2,IF(F12=250,VLOOKUP($E12,'Master Data'!$B:$W,IF(G12="Wholesale",21,22),FALSE)/3,IF(F12=100,VLOOKUP($E12,'Master Data'!$B:$W,IF(G12="Wholesale",21,22),FALSE)/4,IF(F12=50,VLOOKUP($E12,'Master Data'!$B:$W,IF(G12="Wholesale",21,22),FALSE)/6,IF(F12=25,VLOOKUP($E12,'Master Data'!$B:$W,IF(G12="Wholesale",21,22),FALSE)/8,VLOOKUP($E12,'Master Data'!$B:$W,IF(G12="Wholesale",21,22),FALSE)/8)))))) -> 0 | V12: =+VLOOKUP($I12,'Master Data'!$B:$V,IF(G12="Wholesale",20,21),FALSE) -> 40 | W12: =IF(F12=1000,'Master Data'!$AB$32,IF(F12=500,'Master Data'!$AB$33,IF(F12=250,'Master Data'!$AB$34,IF(F12=100,'Master Data'!$AB$35,IF(F12=50,'Master Data'!$AB$36,IF(F12=25,'Master Data'!$AB$37,'Master Data'!$AB$38)))))) -> 56.55 | X12: =+((K12*F12)+$Q12+$R12+$U12+S12)*($J12/100) -> 45.286769 | Y12: =+(F12*K12)+Q12+R12+S12+U12+(IF(F12=1000,V12,IF(F12=500,V12/2,IF(F12=250,V12/4,IF(F12=100,V12/10,IF(F12=50,V12/20,V12/40)))))+X12) -> 311.72062 | Z12: =+Y12/L12 -> 311.72062 | AA12: =(F12*K12)+Q12+R12+S12+T12+U12+W12+X12 -> 339.38728 | AB12: =+((K12*F12)+$Q12+$R12+$U12+$S12+$T12)*($J12/100) -> 47.510103 | AC12: =(F12*K12)+Q12+R12+S12+T12+U12+AB12 -> 285.06062 | AD12: =AC12*1.5 -> 427.59092
A13: =+A12+1 -> 11 | B13: Cumin Seeds | C13: जीरा | D13: =+VLOOKUP($B13,'Master Data'!$B$20:$W$197,2,FALSE) -> Chandan Enterprise | E13: Recycle Box | F13: 1000 | G13: Wholesale | H13: Maruthi Plastics | I13: Shree Maruthi Couriers-Local | J13: 20 | K13: =IF(D13="In House Production",INDEX('Master Data'!$H$552:$J$580,MATCH('Production Cost'!B13,'Master Data'!$H$552:$H$580,0),3),VLOOKUP($B13,'Master Data'!$B:$W,IF(G13="Wholesale",21,22),FALSE)) -> 0.304 | L13: 1 | M13: =INDEX('Master Data'!$B$323:$K$376,MATCH('Production Cost'!$B13,'Master Data'!$B$323:$B$376,0),MATCH('Production Cost'!F$3,'Master Data'!$B$323:$K$323,0)) -> 1 | N13: =IF(H13="Maruthi Plastics",INDEX('Master Data'!$B$202:$L$255,MATCH('Production Cost'!B13,'Master Data'!$B$202:$B$255,0),MATCH('Production Cost'!F13,'Master Data'!$B$202:$L$202,0)),INDEX('Master Data'!$B$261:$L$314,MATCH('Production Cost'!B13,'Master Data'!$B$261:$B$314,0),MATCH('Production Cost'!F13,'Master Data'!$B$261:$L$261,0))) -> One side Transparent Flat Bottom with Zipper (1000Gm) | O13: =1000/L13 -> 1000 | P13: =+VLOOKUP($N13,'Master Data'!$B:$W,IF(G13="Wholesale",21,22),FALSE) -> 11.94 | Q13: =+P13*M13 -> 11.94 | R13: =IF(G13="Wholesale",'Master Data'!$V$127*$M13,'Master Data'!$W$127*$M13) -> 2.2 | S13: =IF(G13="Wholesale",'Master Data'!$V$111*$M13,'Master Data'!$W$111*$M13) -> 3.0769231 | T13: =IF(F13=1000,'Master Data'!$AF$40,IF(F13=500,'Master Data'!$AF$39,IF(F13=250,'Master Data'!$AF$39,'Master Data'!$AF$38))) -> 11.116667 | U13: =IF(F13=1000,VLOOKUP($E13,'Master Data'!$B:$W,IF(G13="Wholesale",21,22),FALSE),IF(F13=500,VLOOKUP($E13,'Master Data'!$B:$W,IF(G13="Wholesale",21,22),FALSE)/2,IF(F13=250,VLOOKUP($E13,'Master Data'!$B:$W,IF(G13="Wholesale",21,22),FALSE)/3,IF(F13=100,VLOOKUP($E13,'Master Data'!$B:$W,IF(G13="Wholesale",21,22),FALSE)/4,IF(F13=50,VLOOKUP($E13,'Master Data'!$B:$W,IF(G13="Wholesale",21,22),FALSE)/6,IF(F13=25,VLOOKUP($E13,'Master Data'!$B:$W,IF(G13="Wholesale",21,22),FALSE)/8,VLOOKUP($E13,'Master Data'!$B:$W,IF(G13="Wholesale",21,22),FALSE)/8)))))) -> 0 | V13: =+VLOOKUP($I13,'Master Data'!$B:$V,IF(G13="Wholesale",20,21),FALSE) -> 40 | W13: =IF(F13=1000,'Master Data'!$AB$32,IF(F13=500,'Master Data'!$AB$33,IF(F13=250,'Master Data'!$AB$34,IF(F13=100,'Master Data'!$AB$35,IF(F13=50,'Master Data'!$AB$36,IF(F13=25,'Master Data'!$AB$37,'Master Data'!$AB$38)))))) -> 56.55 | X13: =+((K13*F13)+$Q13+$R13+$U13+S13)*($J13/100) -> 64.243385 | Y13: =+(F13*K13)+Q13+R13+S13+U13+(IF(F13=1000,V13,IF(F13=500,V13/2,IF(F13=250,V13/4,IF(F13=100,V13/10,IF(F13=50,V13/20,V13/40)))))+X13) -> 425.46031 | Z13: =+Y13/L13 -> 425.46031 | AA13: =(F13*K13)+Q13+R13+S13+T13+U13+W13+X13 -> 453.12697 | AB13: =+((K13*F13)+$Q13+$R13+$U13+$S13+$T13)*($J13/100) -> 66.466718 | AC13: =(F13*K13)+Q13+R13+S13+T13+U13+AB13 -> 398.80031 | AD13: =AC13*1.5 -> 598.20046
A14: =+A13+1 -> 12 | B14: Mustard Seeds | C14: राइ | D14: =+VLOOKUP($B14,'Master Data'!$B$20:$W$197,2,FALSE) -> Chandan Enterprise | E14: Recycle Box | F14: 1000 | G14: Wholesale | H14: Maruthi Plastics | I14: Shree Maruthi Couriers-Local | J14: 20 | K14: =IF(D14="In House Production",INDEX('Master Data'!$H$552:$J$580,MATCH('Production Cost'!B14,'Master Data'!$H$552:$H$580,0),3),VLOOKUP($B14,'Master Data'!$B:$W,IF(G14="Wholesale",21,22),FALSE)) -> 0.132 | L14: 1 | M14: =INDEX('Master Data'!$B$323:$K$376,MATCH('Production Cost'!$B14,'Master Data'!$B$323:$B$376,0),MATCH('Production Cost'!F$3,'Master Data'!$B$323:$K$323,0)) -> 1 | N14: =IF(H14="Maruthi Plastics",INDEX('Master Data'!$B$202:$L$255,MATCH('Production Cost'!B14,'Master Data'!$B$202:$B$255,0),MATCH('Production Cost'!F14,'Master Data'!$B$202:$L$202,0)),INDEX('Master Data'!$B$261:$L$314,MATCH('Production Cost'!B14,'Master Data'!$B$261:$B$314,0),MATCH('Production Cost'!F14,'Master Data'!$B$261:$L$261,0))) -> One side Transparent Flat Bottom with Zipper (1000Gm) | O14: =1000/L14 -> 1000 | P14: =+VLOOKUP($N14,'Master Data'!$B:$W,IF(G14="Wholesale",21,22),FALSE) -> 11.94 | Q14: =+P14*M14 -> 11.94 | R14: =IF(G14="Wholesale",'Master Data'!$V$127*$M14,'Master Data'!$W$127*$M14) -> 2.2 | S14: =IF(G14="Wholesale",'Master Data'!$V$111*$M14,'Master Data'!$W$111*$M14) -> 3.0769231 | T14: =IF(F14=1000,'Master Data'!$AF$40,IF(F14=500,'Master Data'!$AF$39,IF(F14=250,'Master Data'!$AF$39,'Master Data'!$AF$38))) -> 11.116667 | U14: =IF(F14=1000,VLOOKUP($E14,'Master Data'!$B:$W,IF(G14="Wholesale",21,22),FALSE),IF(F14=500,VLOOKUP($E14,'Master Data'!$B:$W,IF(G14="Wholesale",21,22),FALSE)/2,IF(F14=250,VLOOKUP($E14,'Master Data'!$B:$W,IF(G14="Wholesale",21,22),FALSE)/3,IF(F14=100,VLOOKUP($E14,'Master Data'!$B:$W,IF(G14="Wholesale",21,22),FALSE)/4,IF(F14=50,VLOOKUP($E14,'Master Data'!$B:$W,IF(G14="Wholesale",21,22),FALSE)/6,IF(F14=25,VLOOKUP($E14,'Master Data'!$B:$W,IF(G14="Wholesale",21,22),FALSE)/8,VLOOKUP($E14,'Master Data'!$B:$W,IF(G14="Wholesale",21,22),FALSE)/8)))))) -> 0 | V14: =+VLOOKUP($I14,'Master Data'!$B:$V,IF(G14="Wholesale",20,21),FALSE) -> 40 | W14: =IF(F14=1000,'Master Data'!$AB$32,IF(F14=500,'Master Data'!$AB$33,IF(F14=250,'Master Data'!$AB$34,IF(F14=100,'Master Data'!$AB$35,IF(F14=50,'Master Data'!$AB$36,IF(F14=25,'Master Data'!$AB$37,'Master Data'!$AB$38)))))) -> 56.55 | X14: =+((K14*F14)+$Q14+$R14+$U14+S14)*($J14/100) -> 29.843385 | Y14: =+(F14*K14)+Q14+R14+S14+U14+(IF(F14=1000,V14,IF(F14=500,V14/2,IF(F14=250,V14/4,IF(F14=100,V14/10,IF(F14=50,V14/20,V14/40)))))+X14) -> 219.06031 | Z14: =+Y14/L14 -> 219.06031 | AA14: =(F14*K14)+Q14+R14+S14+T14+U14+W14+X14 -> 246.72697 | AB14: =+((K14*F14)+$Q14+$R14+$U14+$S14+$T14)*($J14/100) -> 32.066718 | AC14: =(F14*K14)+Q14+R14+S14+T14+U14+AB14 -> 192.40031 | AD14: =AC14*1.5 -> 288.60046
A15: =+A14+1 -> 13 | B15: Mace | C15: जावित्री | D15: Eternal Blooms | E15: Recycle Box | F15: 1000 | G15: Wholesale | H15: Maruthi Plastics | I15: Shree Maruthi Couriers-Local | J15: 20 | K15: =IF(D15="In House Production",INDEX('Master Data'!$H$552:$J$580,MATCH('Production Cost'!B15,'Master Data'!$H$552:$H$580,0),3),VLOOKUP($B15,'Master Data'!$B:$W,IF(G15="Wholesale",21,22),FALSE)) -> 2.741 | L15: 1 | M15: =INDEX('Master Data'!$B$323:$K$376,MATCH('Production Cost'!$B15,'Master Data'!$B$323:$B$376,0),MATCH('Production Cost'!F$3,'Master Data'!$B$323:$K$323,0)) -> 4 | N15: =IF(H15="Maruthi Plastics",INDEX('Master Data'!$B$202:$L$255,MATCH('Production Cost'!B15,'Master Data'!$B$202:$B$255,0),MATCH('Production Cost'!F15,'Master Data'!$B$202:$L$202,0)),INDEX('Master Data'!$B$261:$L$314,MATCH('Production Cost'!B15,'Master Data'!$B$261:$B$314,0),MATCH('Production Cost'!F15,'Master Data'!$B$261:$L$261,0))) -> One side Transparent Flat Bottom with Zipper (1000Gm) | O15: =1000/L15 -> 1000 | P15: =+VLOOKUP($N15,'Master Data'!$B:$W,IF(G15="Wholesale",21,22),FALSE) -> 11.94 | Q15: =+P15*M15 -> 47.76 | R15: =IF(G15="Wholesale",'Master Data'!$V$127*$M15,'Master Data'!$W$127*$M15) -> 8.8 | S15: =IF(G15="Wholesale",'Master Data'!$V$111*$M15,'Master Data'!$W$111*$M15) -> 12.307692 | T15: =IF(F15=1000,'Master Data'!$AF$40,IF(F15=500,'Master Data'!$AF$39,IF(F15=250,'Master Data'!$AF$39,'Master Data'!$AF$38))) -> 11.116667 | U15: =IF(F15=1000,VLOOKUP($E15,'Master Data'!$B:$W,IF(G15="Wholesale",21,22),FALSE),IF(F15=500,VLOOKUP($E15,'Master Data'!$B:$W,IF(G15="Wholesale",21,22),FALSE)/2,IF(F15=250,VLOOKUP($E15,'Master Data'!$B:$W,IF(G15="Wholesale",21,22),FALSE)/3,IF(F15=100,VLOOKUP($E15,'Master Data'!$B:$W,IF(G15="Wholesale",21,22),FALSE)/4,IF(F15=50,VLOOKUP($E15,'Master Data'!$B:$W,IF(G15="Wholesale",21,22),FALSE)/6,IF(F15=25,VLOOKUP($E15,'Master Data'!$B:$W,IF(G15="Wholesale",21,22),FALSE)/8,VLOOKUP($E15,'Master Data'!$B:$W,IF(G15="Wholesale",21,22),FALSE)/8)))))) -> 0 | V15: =+VLOOKUP($I15,'Master Data'!$B:$V,IF(G15="Wholesale",20,21),FALSE) -> 40 | W15: =IF(F15=1000,'Master Data'!$AB$32,IF(F15=500,'Master Data'!$AB$33,IF(F15=250,'Master Data'!$AB$34,IF(F15=100,'Master Data'!$AB$35,IF(F15=50,'Master Data'!$AB$36,IF(F15=25,'Master Data'!$AB$37,'Master Data'!$AB$38)))))) -> 56.55 | X15: =+((K15*F15)+$Q15+$R15+$U15+S15)*($J15/100) -> 561.97354 | Y15: =+(F15*K15)+Q15+R15+S15+U15+(IF(F15=1000,V15,IF(F15=500,V15/2,IF(F15=250,V15/4,IF(F15=100,V15/10,IF(F15=50,V15/20,V15/40)))))+X15) -> 3411.8412 | Z15: =+Y15/L15 -> 3411.8412 | AA15: =(F15*K15)+Q15+R15+S15+T15+U15+W15+X15 -> 3439.5079 | AB15: =+((K15*F15)+$Q15+$R15+$U15+$S15+$T15)*($J15/100) -> 564.19687 | AC15: =(F15*K15)+Q15+R15+S15+T15+U15+AB15 -> 3385.1812 | AD15: =AC15*1.5 -> 5077.7718
A16: =+A15+1 -> 14 | B16: Nutmeg | C16: जायफल | D16: =+VLOOKUP($B16,'Master Data'!$B$20:$W$197,2,FALSE) -> Nadha Spices | E16: Recycle Box | F16: 1000 | G16: Wholesale | H16: Maruthi Plastics | I16: Shree Maruthi Couriers-Local | J16: 20 | K16: =IF(D16="In House Production",INDEX('Master Data'!$H$552:$J$580,MATCH('Production Cost'!B16,'Master Data'!$H$552:$H$580,0),3),VLOOKUP($B16,'Master Data'!$B:$W,IF(G16="Wholesale",21,22),FALSE)) -> 0.941 | L16: 1 | M16: =INDEX('Master Data'!$B$323:$K$376,MATCH('Production Cost'!$B16,'Master Data'!$B$323:$B$376,0),MATCH('Production Cost'!F$3,'Master Data'!$B$323:$K$323,0)) -> 1 | N16: =IF(H16="Maruthi Plastics",INDEX('Master Data'!$B$202:$L$255,MATCH('Production Cost'!B16,'Master Data'!$B$202:$B$255,0),MATCH('Production Cost'!F16,'Master Data'!$B$202:$L$202,0)),INDEX('Master Data'!$B$261:$L$314,MATCH('Production Cost'!B16,'Master Data'!$B$261:$B$314,0),MATCH('Production Cost'!F16,'Master Data'!$B$261:$L$261,0))) -> One side Transparent Flat Bottom with Zipper (1000Gm) | O16: =1000/L16 -> 1000 | P16: =+VLOOKUP($N16,'Master Data'!$B:$W,IF(G16="Wholesale",21,22),FALSE) -> 11.94 | Q16: =+P16*M16 -> 11.94 | R16: =IF(G16="Wholesale",'Master Data'!$V$127*$M16,'Master Data'!$W$127*$M16) -> 2.2 | S16: =IF(G16="Wholesale",'Master Data'!$V$111*$M16,'Master Data'!$W$111*$M16) -> 3.0769231 | T16: =IF(F16=1000,'Master Data'!$AF$40,IF(F16=500,'Master Data'!$AF$39,IF(F16=250,'Master Data'!$AF$39,'Master Data'!$AF$38))) -> 11.116667 | U16: =IF(F16=1000,VLOOKUP($E16,'Master Data'!$B:$W,IF(G16="Wholesale",21,22),FALSE),IF(F16=500,VLOOKUP($E16,'Master Data'!$B:$W,IF(G16="Wholesale",21,22),FALSE)/2,IF(F16=250,VLOOKUP($E16,'Master Data'!$B:$W,IF(G16="Wholesale",21,22),FALSE)/3,IF(F16=100,VLOOKUP($E16,'Master Data'!$B:$W,IF(G16="Wholesale",21,22),FALSE)/4,IF(F16=50,VLOOKUP($E16,'Master Data'!$B:$W,IF(G16="Wholesale",21,22),FALSE)/6,IF(F16=25,VLOOKUP($E16,'Master Data'!$B:$W,IF(G16="Wholesale",21,22),FALSE)/8,VLOOKUP($E16,'Master Data'!$B:$W,IF(G16="Wholesale",21,22),FALSE)/8)))))) -> 0 | V16: =+VLOOKUP($I16,'Master Data'!$B:$V,IF(G16="Wholesale",20,21),FALSE) -> 40 | W16: =IF(F16=1000,'Master Data'!$AB$32,IF(F16=500,'Master Data'!$AB$33,IF(F16=250,'Master Data'!$AB$34,IF(F16=100,'Master Data'!$AB$35,IF(F16=50,'Master Data'!$AB$36,IF(F16=25,'Master Data'!$AB$37,'Master Data'!$AB$38)))))) -> 56.55 | X16: =+((K16*F16)+$Q16+$R16+$U16+S16)*($J16/100) -> 191.64338 | Y16: =+(F16*K16)+Q16+R16+S16+U16+(IF(F16=1000,V16,IF(F16=500,V16/2,IF(F16=250,V16/4,IF(F16=100,V16/10,IF(F16=50,V16/20,V16/40)))))+X16) -> 1189.8603 | Z16: =+Y16/L16 -> 1189.8603 | AA16: =(F16*K16)+Q16+R16+S16+T16+U16+W16+X16 -> 1217.527 | AB16: =+((K16*F16)+$Q16+$R16+$U16+$S16+$T16)*($J16/100) -> 193.86672 | AC16: =(F16*K16)+Q16+R16+S16+T16+U16+AB16 -> 1163.2003 | AD16: =AC16*1.5 -> 1744.8005
A17: =+A16+1 -> 15 | B17: Star Anise | C17: चक्र फूल | D17: =+VLOOKUP($B17,'Master Data'!$B$20:$W$197,2,FALSE) -> Ali Kikabai | E17: Recycle Box | F17: 1000 | G17: Wholesale | H17: Maruthi Plastics | I17: Shree Maruthi Couriers-Local | J17: 20 | K17: =IF(D17="In House Production",INDEX('Master Data'!$H$552:$J$580,MATCH('Production Cost'!B17,'Master Data'!$H$552:$H$580,0),3),VLOOKUP($B17,'Master Data'!$B:$W,IF(G17="Wholesale",21,22),FALSE)) -> 0.5196 | L17: 1 | M17: =INDEX('Master Data'!$B$323:$K$376,MATCH('Production Cost'!$B17,'Master Data'!$B$323:$B$376,0),MATCH('Production Cost'!F$3,'Master Data'!$B$323:$K$323,0)) -> 4 | N17: =IF(H17="Maruthi Plastics",INDEX('Master Data'!$B$202:$L$255,MATCH('Production Cost'!B17,'Master Data'!$B$202:$B$255,0),MATCH('Production Cost'!F17,'Master Data'!$B$202:$L$202,0)),INDEX('Master Data'!$B$261:$L$314,MATCH('Production Cost'!B17,'Master Data'!$B$261:$B$314,0),MATCH('Production Cost'!F17,'Master Data'!$B$261:$L$261,0))) -> One side Transparent Flat Bottom with Zipper (1000Gm) | O17: =1000/L17 -> 1000 | P17: =+VLOOKUP($N17,'Master Data'!$B:$W,IF(G17="Wholesale",21,22),FALSE) -> 11.94 | Q17: =+P17*M17 -> 47.76 | R17: =IF(G17="Wholesale",'Master Data'!$V$127*$M17,'Master Data'!$W$127*$M17) -> 8.8 | S17: =IF(G17="Wholesale",'Master Data'!$V$111*$M17,'Master Data'!$W$111*$M17) -> 12.307692 | T17: =IF(F17=1000,'Master Data'!$AF$40,IF(F17=500,'Master Data'!$AF$39,IF(F17=250,'Master Data'!$AF$39,'Master Data'!$AF$38))) -> 11.116667 | U17: =IF(F17=1000,VLOOKUP($E17,'Master Data'!$B:$W,IF(G17="Wholesale",21,22),FALSE),IF(F17=500,VLOOKUP($E17,'Master Data'!$B:$W,IF(G17="Wholesale",21,22),FALSE)/2,IF(F17=250,VLOOKUP($E17,'Master Data'!$B:$W,IF(G17="Wholesale",21,22),FALSE)/3,IF(F17=100,VLOOKUP($E17,'Master Data'!$B:$W,IF(G17="Wholesale",21,22),FALSE)/4,IF(F17=50,VLOOKUP($E17,'Master Data'!$B:$W,IF(G17="Wholesale",21,22),FALSE)/6,IF(F17=25,VLOOKUP($E17,'Master Data'!$B:$W,IF(G17="Wholesale",21,22),FALSE)/8,VLOOKUP($E17,'Master Data'!$B:$W,IF(G17="Wholesale",21,22),FALSE)/8)))))) -> 0 | V17: =+VLOOKUP($I17,'Master Data'!$B:$V,IF(G17="Wholesale",20,21),FALSE) -> 40 | W17: =IF(F17=1000,'Master Data'!$AB$32,IF(F17=500,'Master Data'!$AB$33,IF(F17=250,'Master Data'!$AB$34,IF(F17=100,'Master Data'!$AB$35,IF(F17=50,'Master Data'!$AB$36,IF(F17=25,'Master Data'!$AB$37,'Master Data'!$AB$38)))))) -> 56.55 | X17: =+((K17*F17)+$Q17+$R17+$U17+S17)*($J17/100) -> 117.69354 | Y17: =+(F17*K17)+Q17+R17+S17+U17+(IF(F17=1000,V17,IF(F17=500,V17/2,IF(F17=250,V17/4,IF(F17=100,V17/10,IF(F17=50,V17/20,V17/40)))))+X17) -> 746.16123 | Z17: =+Y17/L17 -> 746.16123 | AA17: =(F17*K17)+Q17+R17+S17+T17+U17+W17+X17 -> 773.8279 | AB17: =+((K17*F17)+$Q17+$R17+$U17+$S17+$T17)*($J17/100) -> 119.91687 | AC17: =(F17*K17)+Q17+R17+S17+T17+U17+AB17 -> 719.50123 | AD17: =AC17*1.5 -> 1079.2518
A18: =+A17+1 -> 16 | B18: Black Pepper Powder | C18: काली मिर्च पाउडर | D18: In House Production | E18: Recycle Box | F18: 1000 | G18: Wholesale | H18: Maruthi Plastics | I18: Shree Maruthi Couriers-Local | J18: 20 | K18: =IF(D18="In House Production",INDEX('Master Data'!$H$552:$J$580,MATCH('Production Cost'!B18,'Master Data'!$H$552:$H$580,0),3),VLOOKUP($B18,'Master Data'!$B:$W,IF(G18="Wholesale",21,22),FALSE)) -> 0.92505 | L18: 1 | M18: =INDEX('Master Data'!$B$323:$K$376,MATCH('Production Cost'!$B18,'Master Data'!$B$323:$B$376,0),MATCH('Production Cost'!F$3,'Master Data'!$B$323:$K$323,0)) -> 1 | N18: =IF(H18="Maruthi Plastics",INDEX('Master Data'!$B$202:$L$255,MATCH('Production Cost'!B18,'Master Data'!$B$202:$B$255,0),MATCH('Production Cost'!F18,'Master Data'!$B$202:$L$202,0)),INDEX('Master Data'!$B$261:$L$314,MATCH('Production Cost'!B18,'Master Data'!$B$261:$B$314,0),MATCH('Production Cost'!F18,'Master Data'!$B$261:$L$261,0))) -> Flat Bottom Pouches With Normal Zipper 1 kg | O18: =1000/L18 -> 1000 | P18: =+VLOOKUP($N18,'Master Data'!$B:$W,IF(G18="Wholesale",21,22),FALSE) -> 16.13 | Q18: =+P18*M18 -> 16.13 | R18: =IF(G18="Wholesale",'Master Data'!$V$127*$M18,'Master Data'!$W$127*$M18) -> 2.2 | S18: =IF(G18="Wholesale",'Master Data'!$V$111*$M18,'Master Data'!$W$111*$M18) -> 3.0769231 | T18: =IF(F18=1000,'Master Data'!$AF$40,IF(F18=500,'Master Data'!$AF$39,IF(F18=250,'Master Data'!$AF$39,'Master Data'!$AF$38))) -> 11.116667 | U18: =IF(F18=1000,VLOOKUP($E18,'Master Data'!$B:$W,IF(G18="Wholesale",21,22),FALSE),IF(F18=500,VLOOKUP($E18,'Master Data'!$B:$W,IF(G18="Wholesale",21,22),FALSE)/2,IF(F18=250,VLOOKUP($E18,'Master Data'!$B:$W,IF(G18="Wholesale",21,22),FALSE)/3,IF(F18=100,VLOOKUP($E18,'Master Data'!$B:$W,IF(G18="Wholesale",21,22),FALSE)/4,IF(F18=50,VLOOKUP($E18,'Master Data'!$B:$W,IF(G18="Wholesale",21,22),FALSE)/6,IF(F18=25,VLOOKUP($E18,'Master Data'!$B:$W,IF(G18="Wholesale",21,22),FALSE)/8,VLOOKUP($E18,'Master Data'!$B:$W,IF(G18="Wholesale",21,22),FALSE)/8)))))) -> 0 | V18: =+VLOOKUP($I18,'Master Data'!$B:$V,IF(G18="Wholesale",20,21),FALSE) -> 40 | W18: =IF(F18=1000,'Master Data'!$AB$32,IF(F18=500,'Master Data'!$AB$33,IF(F18=250,'Master Data'!$AB$34,IF(F18=100,'Master Data'!$AB$35,IF(F18=50,'Master Data'!$AB$36,IF(F18=25,'Master Data'!$AB$37,'Master Data'!$AB$38)))))) -> 56.55 | X18: =+((K18*F18)+$Q18+$R18+$U18+S18)*($J18/100) -> 189.29138 | Y18: =+(F18*K18)+Q18+R18+S18+U18+(IF(F18=1000,V18,IF(F18=500,V18/2,IF(F18=250,V18/4,IF(F18=100,V18/10,IF(F18=50,V18/20,V18/40)))))+X18) -> 1175.7483 | Z18: =+Y18/L18 -> 1175.7483 | AA18: =(F18*K18)+Q18+R18+S18+T18+U18+W18+X18 -> 1203.415 | AB18: =+((K18*F18)+$Q18+$R18+$U18+$S18+$T18)*($J18/100) -> 191.51472 | AC18: =(F18*K18)+Q18+R18+S18+T18+U18+AB18 -> 1149.0883 | AD18: =AC18*1.5 -> 1723.6325
A19: =+A18+1 -> 17 | B19: Coriander Seeds Powder | C19: धनिया पाउडर | D19: In House Production | E19: Recycle Box | F19: 1000 | G19: Wholesale | H19: Maruthi Plastics | I19: Shree Maruthi Couriers-Local | J19: 20 | K19: =IF(D19="In House Production",INDEX('Master Data'!$H$552:$J$580,MATCH('Production Cost'!B19,'Master Data'!$H$552:$H$580,0),3),VLOOKUP($B19,'Master Data'!$B:$W,IF(G19="Wholesale",21,22),FALSE)) -> 0.2016 | L19: 1 | M19: =INDEX('Master Data'!$B$323:$K$376,MATCH('Production Cost'!$B19,'Master Data'!$B$323:$B$376,0),MATCH('Production Cost'!F$3,'Master Data'!$B$323:$K$323,0)) -> 1 | N19: =IF(H19="Maruthi Plastics",INDEX('Master Data'!$B$202:$L$255,MATCH('Production Cost'!B19,'Master Data'!$B$202:$B$255,0),MATCH('Production Cost'!F19,'Master Data'!$B$202:$L$202,0)),INDEX('Master Data'!$B$261:$L$314,MATCH('Production Cost'!B19,'Master Data'!$B$261:$B$314,0),MATCH('Production Cost'!F19,'Master Data'!$B$261:$L$261,0))) -> One side Transparent Flat Bottom with Zipper (1000Gm) | O19: =1000/L19 -> 1000 | P19: =+VLOOKUP($N19,'Master Data'!$B:$W,IF(G19="Wholesale",21,22),FALSE) -> 11.94 | Q19: =+P19*M19 -> 11.94 | R19: =IF(G19="Wholesale",'Master Data'!$V$127*$M19,'Master Data'!$W$127*$M19) -> 2.2 | S19: =IF(G19="Wholesale",'Master Data'!$V$111*$M19,'Master Data'!$W$111*$M19) -> 3.0769231 | T19: =IF(F19=1000,'Master Data'!$AF$40,IF(F19=500,'Master Data'!$AF$39,IF(F19=250,'Master Data'!$AF$39,'Master Data'!$AF$38))) -> 11.116667 | U19: =IF(F19=1000,VLOOKUP($E19,'Master Data'!$B:$W,IF(G19="Wholesale",21,22),FALSE),IF(F19=500,VLOOKUP($E19,'Master Data'!$B:$W,IF(G19="Wholesale",21,22),FALSE)/2,IF(F19=250,VLOOKUP($E19,'Master Data'!$B:$W,IF(G19="Wholesale",21,22),FALSE)/3,IF(F19=100,VLOOKUP($E19,'Master Data'!$B:$W,IF(G19="Wholesale",21,22),FALSE)/4,IF(F19=50,VLOOKUP($E19,'Master Data'!$B:$W,IF(G19="Wholesale",21,22),FALSE)/6,IF(F19=25,VLOOKUP($E19,'Master Data'!$B:$W,IF(G19="Wholesale",21,22),FALSE)/8,VLOOKUP($E19,'Master Data'!$B:$W,IF(G19="Wholesale",21,22),FALSE)/8)))))) -> 0 | V19: =+VLOOKUP($I19,'Master Data'!$B:$V,IF(G19="Wholesale",20,21),FALSE) -> 40 | W19: =IF(F19=1000,'Master Data'!$AB$32,IF(F19=500,'Master Data'!$AB$33,IF(F19=250,'Master Data'!$AB$34,IF(F19=100,'Master Data'!$AB$35,IF(F19=50,'Master Data'!$AB$36,IF(F19=25,'Master Data'!$AB$37,'Master Data'!$AB$38)))))) -> 56.55 | X19: =+((K19*F19)+$Q19+$R19+$U19+S19)*($J19/100) -> 43.763385 | Y19: =+(F19*K19)+Q19+R19+S19+U19+(IF(F19=1000,V19,IF(F19=500,V19/2,IF(F19=250,V19/4,IF(F19=100,V19/10,IF(F19=50,V19/20,V19/40)))))+X19) -> 302.58031 | Z19: =+Y19/L19 -> 302.58031 | AA19: =(F19*K19)+Q19+R19+S19+T19+U19+W19+X19 -> 330.24697 | AB19: =+((K19*F19)+$Q19+$R19+$U19+$S19+$T19)*($J19/100) -> 45.986718 | AC19: =(F19*K19)+Q19+R19+S19+T19+U19+AB19 -> 275.92031 | AD19: =AC19*1.5 -> 413.88046
A20: =+A19+1 -> 18 | B20: Cumin Seeds Powder | C20: जीरा पाउडर | D20: In House Production | E20: Recycle Box | F20: 1000 | G20: Wholesale | H20: Maruthi Plastics | I20: Shree Maruthi Couriers-Local | J20: 20 | K20: =IF(D20="In House Production",INDEX('Master Data'!$H$552:$J$580,MATCH('Production Cost'!B20,'Master Data'!$H$552:$H$580,0),3),VLOOKUP($B20,'Master Data'!$B:$W,IF(G20="Wholesale",21,22),FALSE)) -> 0.3192 | L20: 0 | M20: =INDEX('Master Data'!$B$323:$K$376,MATCH('Production Cost'!$B20,'Master Data'!$B$323:$B$376,0),MATCH('Production Cost'!F$3,'Master Data'!$B$323:$K$323,0)) -> 1 | N20: =IF(H20="Maruthi Plastics",INDEX('Master Data'!$B$202:$L$255,MATCH('Production Cost'!B20,'Master Data'!$B$202:$B$255,0),MATCH('Production Cost'!F20,'Master Data'!$B$202:$L$202,0)),INDEX('Master Data'!$B$261:$L$314,MATCH('Production Cost'!B20,'Master Data'!$B$261:$B$314,0),MATCH('Production Cost'!F20,'Master Data'!$B$261:$L$261,0))) -> One side Transparent Flat Bottom with Zipper (1000Gm) | O20: =1000/L20 -> #DIV/0! | P20: =+VLOOKUP($N20,'Master Data'!$B:$W,IF(G20="Wholesale",21,22),FALSE) -> 11.94 | Q20: =+P20*M20 -> 11.94 | R20: =IF(G20="Wholesale",'Master Data'!$V$127*$M20,'Master Data'!$W$127*$M20) -> 2.2 | S20: =IF(G20="Wholesale",'Master Data'!$V$111*$M20,'Master Data'!$W$111*$M20) -> 3.0769231 | T20: =IF(F20=1000,'Master Data'!$AF$40,IF(F20=500,'Master Data'!$AF$39,IF(F20=250,'Master Data'!$AF$39,'Master Data'!$AF$38))) -> 11.116667 | U20: =IF(F20=1000,VLOOKUP($E20,'Master Data'!$B:$W,IF(G20="Wholesale",21,22),FALSE),IF(F20=500,VLOOKUP($E20,'Master Data'!$B:$W,IF(G20="Wholesale",21,22),FALSE)/2,IF(F20=250,VLOOKUP($E20,'Master Data'!$B:$W,IF(G20="Wholesale",21,22),FALSE)/3,IF(F20=100,VLOOKUP($E20,'Master Data'!$B:$W,IF(G20="Wholesale",21,22),FALSE)/4,IF(F20=50,VLOOKUP($E20,'Master Data'!$B:$W,IF(G20="Wholesale",21,22),FALSE)/6,IF(F20=25,VLOOKUP($E20,'Master Data'!$B:$W,IF(G20="Wholesale",21,22),FALSE)/8,VLOOKUP($E20,'Master Data'!$B:$W,IF(G20="Wholesale",21,22),FALSE)/8)))))) -> 0 | V20: =+VLOOKUP($I20,'Master Data'!$B:$V,IF(G20="Wholesale",20,21),FALSE) -> 40 | W20: =IF(F20=1000,'Master Data'!$AB$32,IF(F20=500,'Master Data'!$AB$33,IF(F20=250,'Master Data'!$AB$34,IF(F20=100,'Master Data'!$AB$35,IF(F20=50,'Master Data'!$AB$36,IF(F20=25,'Master Data'!$AB$37,'Master Data'!$AB$38)))))) -> 56.55 | X20: =+((K20*F20)+$Q20+$R20+$U20+S20)*($J20/100) -> 67.283385 | Y20: =+(F20*K20)+Q20+R20+S20+U20+(IF(F20=1000,V20,IF(F20=500,V20/2,IF(F20=250,V20/4,IF(F20=100,V20/10,IF(F20=50,V20/20,V20/40)))))+X20) -> 443.70031 | Z20: =+Y20/L20 -> #DIV/0! | AA20: =(F20*K20)+Q20+R20+S20+T20+U20+W20+X20 -> 471.36697 | AB20: =+((K20*F20)+$Q20+$R20+$U20+$S20+$T20)*($J20/100) -> 69.506718 | AC20: =(F20*K20)+Q20+R20+S20+T20+U20+AB20 -> 417.04031 | AD20: =AC20*1.5 -> 625.56046
A21: =+A20+1 -> 19 | B21: Coriander Cumin Seeds Powder | C21: धनिया - जीरा पाउडर | D21: In House Production | E21: Recycle Box | F21: 1000 | G21: Wholesale | H21: Maruthi Plastics | I21: Shree Maruthi Couriers-Local | J21: 20 | K21: =IF(D21="In House Production",INDEX('Master Data'!$H$552:$J$580,MATCH('Production Cost'!B21,'Master Data'!$H$552:$H$580,0),3),VLOOKUP($B21,'Master Data'!$B:$W,IF(G21="Wholesale",21,22),FALSE)) -> 0.22512 | L21: 1 | M21: =INDEX('Master Data'!$B$323:$K$376,MATCH('Production Cost'!$B21,'Master Data'!$B$323:$B$376,0),MATCH('Production Cost'!F$3,'Master Data'!$B$323:$K$323,0)) -> 1 | N21: =IF(H21="Maruthi Plastics",INDEX('Master Data'!$B$202:$L$255,MATCH('Production Cost'!B21,'Master Data'!$B$202:$B$255,0),MATCH('Production Cost'!F21,'Master Data'!$B$202:$L$202,0)),INDEX('Master Data'!$B$261:$L$314,MATCH('Production Cost'!B21,'Master Data'!$B$261:$B$314,0),MATCH('Production Cost'!F21,'Master Data'!$B$261:$L$261,0))) -> One side Transparent Flat Bottom with Zipper (1000Gm) | O21: =1000/L21 -> 1000 | P21: =+VLOOKUP($N21,'Master Data'!$B:$W,IF(G21="Wholesale",21,22),FALSE) -> 11.94 | Q21: =+P21*M21 -> 11.94 | R21: =IF(G21="Wholesale",'Master Data'!$V$127*$M21,'Master Data'!$W$127*$M21) -> 2.2 | S21: =IF(G21="Wholesale",'Master Data'!$V$111*$M21,'Master Data'!$W$111*$M21) -> 3.0769231 | T21: =IF(F21=1000,'Master Data'!$AF$40,IF(F21=500,'Master Data'!$AF$39,IF(F21=250,'Master Data'!$AF$39,'Master Data'!$AF$38))) -> 11.116667 | U21: =IF(F21=1000,VLOOKUP($E21,'Master Data'!$B:$W,IF(G21="Wholesale",21,22),FALSE),IF(F21=500,VLOOKUP($E21,'Master Data'!$B:$W,IF(G21="Wholesale",21,22),FALSE)/2,IF(F21=250,VLOOKUP($E21,'Master Data'!$B:$W,IF(G21="Wholesale",21,22),FALSE)/3,IF(F21=100,VLOOKUP($E21,'Master Data'!$B:$W,IF(G21="Wholesale",21,22),FALSE)/4,IF(F21=50,VLOOKUP($E21,'Master Data'!$B:$W,IF(G21="Wholesale",21,22),FALSE)/6,IF(F21=25,VLOOKUP($E21,'Master Data'!$B:$W,IF(G21="Wholesale",21,22),FALSE)/8,VLOOKUP($E21,'Master Data'!$B:$W,IF(G21="Wholesale",21,22),FALSE)/8)))))) -> 0 | V21: =+VLOOKUP($I21,'Master Data'!$B:$V,IF(G21="Wholesale",20,21),FALSE) -> 40 | W21: =IF(F21=1000,'Master Data'!$AB$32,IF(F21=500,'Master Data'!$AB$33,IF(F21=250,'Master Data'!$AB$34,IF(F21=100,'Master Data'!$AB$35,IF(F21=50,'Master Data'!$AB$36,IF(F21=25,'Master Data'!$AB$37,'Master Data'!$AB$38)))))) -> 56.55 | X21: =+((K21*F21)+$Q21+$R21+$U21+S21)*($J21/100) -> 48.467385 | Y21: =+(F21*K21)+Q21+R21+S21+U21+(IF(F21=1000,V21,IF(F21=500,V21/2,IF(F21=250,V21/4,IF(F21=100,V21/10,IF(F21=50,V21/20,V21/40)))))+X21) -> 330.80431 | Z21: =+Y21/L21 -> 330.80431 | AA21: =(F21*K21)+Q21+R21+S21+T21+U21+W21+X21 -> 358.47097 | AB21: =+((K21*F21)+$Q21+$R21+$U21+$S21+$T21)*($J21/100) -> 50.690718 | AC21: =(F21*K21)+Q21+R21+S21+T21+U21+AB21 -> 304.14431 | AD21: =AC21*1.5 -> 456.21646
A22: =+A21+1 -> 20 | B22: Haldi Doodh Powder | D22: In House Production | E22: Recycle Box | F22: 1000 | G22: Wholesale | H22: Maruthi Plastics | I22: Shree Maruthi Couriers-Local | J22: 21 | K22: =IF(D22="In House Production",INDEX('Master Data'!$H$552:$J$580,MATCH('Production Cost'!B22,'Master Data'!$H$552:$H$580,0),3),VLOOKUP($B22,'Master Data'!$B:$W,IF(G22="Wholesale",21,22),FALSE)) -> 0.57141498 | L22: 2 | M22: =INDEX('Master Data'!$B$323:$K$376,MATCH('Production Cost'!$B22,'Master Data'!$B$323:$B$376,0),MATCH('Production Cost'!F$3,'Master Data'!$B$323:$K$323,0)) -> 1 | N22: =IF(H22="Maruthi Plastics",INDEX('Master Data'!$B$202:$L$255,MATCH('Production Cost'!B22,'Master Data'!$B$202:$B$255,0),MATCH('Production Cost'!F22,'Master Data'!$B$202:$L$202,0)),INDEX('Master Data'!$B$261:$L$314,MATCH('Production Cost'!B22,'Master Data'!$B$261:$B$314,0),MATCH('Production Cost'!F22,'Master Data'!$B$261:$L$261,0))) -> One side Transparent Flat Bottom with Zipper (1000Gm) | O22: =1000/L22 -> 500 | P22: =+VLOOKUP($N22,'Master Data'!$B:$W,IF(G22="Wholesale",21,22),FALSE) -> 11.94 | Q22: =+P22*M22 -> 11.94 | R22: =IF(G22="Wholesale",'Master Data'!$V$127*$M22,'Master Data'!$W$127*$M22) -> 2.2 | S22: =IF(G22="Wholesale",'Master Data'!$V$111*$M22,'Master Data'!$W$111*$M22) -> 3.0769231 | T22: =IF(F22=1000,'Master Data'!$AF$40,IF(F22=500,'Master Data'!$AF$39,IF(F22=250,'Master Data'!$AF$39,'Master Data'!$AF$38))) -> 11.116667 | U22: =IF(F22=1000,VLOOKUP($E22,'Master Data'!$B:$W,IF(G22="Wholesale",21,22),FALSE),IF(F22=500,VLOOKUP($E22,'Master Data'!$B:$W,IF(G22="Wholesale",21,22),FALSE)/2,IF(F22=250,VLOOKUP($E22,'Master Data'!$B:$W,IF(G22="Wholesale",21,22),FALSE)/3,IF(F22=100,VLOOKUP($E22,'Master Data'!$B:$W,IF(G22="Wholesale",21,22),FALSE)/4,IF(F22=50,VLOOKUP($E22,'Master Data'!$B:$W,IF(G22="Wholesale",21,22),FALSE)/6,IF(F22=25,VLOOKUP($E22,'Master Data'!$B:$W,IF(G22="Wholesale",21,22),FALSE)/8,VLOOKUP($E22,'Master Data'!$B:$W,IF(G22="Wholesale",21,22),FALSE)/8)))))) -> 0 | V22: =+VLOOKUP($I22,'Master Data'!$B:$V,IF(G22="Wholesale",20,21),FALSE) -> 40 | W22: =IF(F22=1000,'Master Data'!$AB$32,IF(F22=500,'Master Data'!$AB$33,IF(F22=250,'Master Data'!$AB$34,IF(F22=100,'Master Data'!$AB$35,IF(F22=50,'Master Data'!$AB$36,IF(F22=25,'Master Data'!$AB$37,'Master Data'!$AB$38)))))) -> 56.55 | X22: =+((K22*F22)+$Q22+$R22+$U22+S22)*($J22/100) -> 123.6127 | Y22: =+(F22*K22)+Q22+R22+S22+U22+(IF(F22=1000,V22,IF(F22=500,V22/2,IF(F22=250,V22/4,IF(F22=100,V22/10,IF(F22=50,V22/20,V22/40)))))+X22) -> 752.2446 | Z22: =+Y22/L22 -> 376.1223 | AA22: =(F22*K22)+Q22+R22+S22+T22+U22+W22+X22 -> 779.91127 | AB22: =+((K22*F22)+$Q22+$R22+$U22+$S22+$T22)*($J22/100) -> 125.9472 | AC22: =(F22*K22)+Q22+R22+S22+T22+U22+AB22 -> 725.69577 | AD22: =AC22*1.5 -> 1088.5437
A23: =+A22+1 -> 21 | B23: Original Kerala Cinnamon Powder | D23: In House Production | E23: Recycle Box | F23: 1000 | G23: Wholesale | H23: Maruthi Plastics | I23: Shree Maruthi Couriers-Local | J23: 22 | K23: =IF(D23="In House Production",INDEX('Master Data'!$H$552:$J$580,MATCH('Production Cost'!B23,'Master Data'!$H$552:$H$580,0),3),VLOOKUP($B23,'Master Data'!$B:$W,IF(G23="Wholesale",21,22),FALSE)) -> 1.0563 | L23: 3 | M23: =INDEX('Master Data'!$B$323:$K$376,MATCH('Production Cost'!$B23,'Master Data'!$B$323:$B$376,0),MATCH('Production Cost'!F$3,'Master Data'!$B$323:$K$323,0)) -> 1 | N23: =IF(H23="Maruthi Plastics",INDEX('Master Data'!$B$202:$L$255,MATCH('Production Cost'!B23,'Master Data'!$B$202:$B$255,0),MATCH('Production Cost'!F23,'Master Data'!$B$202:$L$202,0)),INDEX('Master Data'!$B$261:$L$314,MATCH('Production Cost'!B23,'Master Data'!$B$261:$B$314,0),MATCH('Production Cost'!F23,'Master Data'!$B$261:$L$261,0))) -> One side Transparent Flat Bottom with Zipper (1000Gm) | O23: =1000/L23 -> 333.33333 | P23: =+VLOOKUP($N23,'Master Data'!$B:$W,IF(G23="Wholesale",21,22),FALSE) -> 11.94 | Q23: =+P23*M23 -> 11.94 | R23: =IF(G23="Wholesale",'Master Data'!$V$127*$M23,'Master Data'!$W$127*$M23) -> 2.2 | S23: =IF(G23="Wholesale",'Master Data'!$V$111*$M23,'Master Data'!$W$111*$M23) -> 3.0769231 | T23: =IF(F23=1000,'Master Data'!$AF$40,IF(F23=500,'Master Data'!$AF$39,IF(F23=250,'Master Data'!$AF$39,'Master Data'!$AF$38))) -> 11.116667 | U23: =IF(F23=1000,VLOOKUP($E23,'Master Data'!$B:$W,IF(G23="Wholesale",21,22),FALSE),IF(F23=500,VLOOKUP($E23,'Master Data'!$B:$W,IF(G23="Wholesale",21,22),FALSE)/2,IF(F23=250,VLOOKUP($E23,'Master Data'!$B:$W,IF(G23="Wholesale",21,22),FALSE)/3,IF(F23=100,VLOOKUP($E23,'Master Data'!$B:$W,IF(G23="Wholesale",21,22),FALSE)/4,IF(F23=50,VLOOKUP($E23,'Master Data'!$B:$W,IF(G23="Wholesale",21,22),FALSE)/6,IF(F23=25,VLOOKUP($E23,'Master Data'!$B:$W,IF(G23="Wholesale",21,22),FALSE)/8,VLOOKUP($E23,'Master Data'!$B:$W,IF(G23="Wholesale",21,22),FALSE)/8)))))) -> 0 | V23: =+VLOOKUP($I23,'Master Data'!$B:$V,IF(G23="Wholesale",20,21),FALSE) -> 40 | W23: =IF(F23=1000,'Master Data'!$AB$32,IF(F23=500,'Master Data'!$AB$33,IF(F23=250,'Master Data'!$AB$34,IF(F23=100,'Master Data'!$AB$35,IF(F23=50,'Master Data'!$AB$36,IF(F23=25,'Master Data'!$AB$37,'Master Data'!$AB$38)))))) -> 56.55 | X23: =+((K23*F23)+$Q23+$R23+$U23+S23)*($J23/100) -> 236.17372 | Y23: =+(F23*K23)+Q23+R23+S23+U23+(IF(F23=1000,V23,IF(F23=500,V23/2,IF(F23=250,V23/4,IF(F23=100,V23/10,IF(F23=50,V23/20,V23/40)))))+X23) -> 1349.6906 | Z23: =+Y23/L23 -> 449.89688 | AA23: =(F23*K23)+Q23+R23+S23+T23+U23+W23+X23 -> 1377.3573 | AB23: =+((K23*F23)+$Q23+$R23+$U23+$S23+$T23)*($J23/100) -> 238.61939 | AC23: =(F23*K23)+Q23+R23+S23+T23+U23+AB23 -> 1323.253 | AD23: =AC23*1.5 -> 1984.8795
A24: =+A23+1 -> 22 | B24: Red Chilli Powder - Mildly Spicy | C24: लाल मिर्च पाउडर – सौम्य मसालेदार | D24: =+VLOOKUP($B24,'Master Data'!$B$20:$W$197,2,FALSE) -> MS Malagi | E24: Recycle Box | F24: 1000 | G24: Wholesale | H24: Maruthi Plastics | I24: Shree Maruthi Couriers-Local | J24: 10 | K24: =IF(D24="In House Production",INDEX('Master Data'!$H$552:$J$580,MATCH('Production Cost'!B24,'Master Data'!$H$552:$H$580,0),3),VLOOKUP($B24,'Master Data'!$B:$W,IF(G24="Wholesale",21,22),FALSE)) -> 0.281 | L24: 1 | M24: =INDEX('Master Data'!$B$323:$K$376,MATCH('Production Cost'!$B24,'Master Data'!$B$323:$B$376,0),MATCH('Production Cost'!F$3,'Master Data'!$B$323:$K$323,0)) -> 1 | N24: =IF(H24="Maruthi Plastics",INDEX('Master Data'!$B$202:$L$255,MATCH('Production Cost'!B24,'Master Data'!$B$202:$B$255,0),MATCH('Production Cost'!F24,'Master Data'!$B$202:$L$202,0)),INDEX('Master Data'!$B$261:$L$314,MATCH('Production Cost'!B24,'Master Data'!$B$261:$B$314,0),MATCH('Production Cost'!F24,'Master Data'!$B$261:$L$261,0))) -> One side Transparent Flat Bottom with Zipper (1000Gm) | O24: =1000/L24 -> 1000 | P24: =+VLOOKUP($N24,'Master Data'!$B:$W,IF(G24="Wholesale",21,22),FALSE) -> 11.94 | Q24: =+P24*M24 -> 11.94 | R24: =IF(G24="Wholesale",'Master Data'!$V$127*$M24,'Master Data'!$W$127*$M24) -> 2.2 | S24: =IF(G24="Wholesale",'Master Data'!$V$111*$M24,'Master Data'!$W$111*$M24) -> 3.0769231 | T24: =IF(F24=1000,'Master Data'!$AF$40,IF(F24=500,'Master Data'!$AF$39,IF(F24=250,'Master Data'!$AF$39,'Master Data'!$AF$38))) -> 11.116667 | U24: =IF(F24=1000,VLOOKUP($E24,'Master Data'!$B:$W,IF(G24="Wholesale",21,22),FALSE),IF(F24=500,VLOOKUP($E24,'Master Data'!$B:$W,IF(G24="Wholesale",21,22),FALSE)/2,IF(F24=250,VLOOKUP($E24,'Master Data'!$B:$W,IF(G24="Wholesale",21,22),FALSE)/3,IF(F24=100,VLOOKUP($E24,'Master Data'!$B:$W,IF(G24="Wholesale",21,22),FALSE)/4,IF(F24=50,VLOOKUP($E24,'Master Data'!$B:$W,IF(G24="Wholesale",21,22),FALSE)/6,IF(F24=25,VLOOKUP($E24,'Master Data'!$B:$W,IF(G24="Wholesale",21,22),FALSE)/8,VLOOKUP($E24,'Master Data'!$B:$W,IF(G24="Wholesale",21,22),FALSE)/8)))))) -> 0 | V24: =+VLOOKUP($I24,'Master Data'!$B:$V,IF(G24="Wholesale",20,21),FALSE) -> 40 | W24: =IF(F24=1000,'Master Data'!$AB$32,IF(F24=500,'Master Data'!$AB$33,IF(F24=250,'Master Data'!$AB$34,IF(F24=100,'Master Data'!$AB$35,IF(F24=50,'Master Data'!$AB$36,IF(F24=25,'Master Data'!$AB$37,'Master Data'!$AB$38)))))) -> 56.55 | X24: =+((K24*F24)+$Q24+$R24+$U24+S24)*($J24/100) -> 29.821692 | Y24: =+(F24*K24)+Q24+R24+S24+U24+(IF(F24=1000,V24,IF(F24=500,V24/2,IF(F24=250,V24/4,IF(F24=100,V24/10,IF(F24=50,V24/20,V24/40)))))+X24) -> 368.03862 | Z24: =+Y24/L24 -> 368.03862 | AA24: =(F24*K24)+Q24+R24+S24+T24+U24+W24+X24 -> 395.70528 | AB24: =+((K24*F24)+$Q24+$R24+$U24+$S24+$T24)*($J24/100) -> 30.933359 | AC24: =(F24*K24)+Q24+R24+S24+T24+U24+AB24 -> 340.26695 | AD24: =AC24*1.5 -> 510.40042
A25: =+A24+1 -> 23 | B25: Red Chilli Powder - Medium Spicy | C25: लाल मिर्च पाउडर मध्यम मसालेदार | D25: =+VLOOKUP($B25,'Master Data'!$B$20:$W$197,2,FALSE) -> MS Malagi | E25: Recycle Box | F25: 1000 | G25: Wholesale | H25: Maruthi Plastics | I25: Shree Maruthi Couriers-Local | J25: 10 | K25: =IF(D25="In House Production",INDEX('Master Data'!$H$552:$J$580,MATCH('Production Cost'!B25,'Master Data'!$H$552:$H$580,0),3),VLOOKUP($B25,'Master Data'!$B:$W,IF(G25="Wholesale",21,22),FALSE)) -> 0.286 | L25: 1 | M25: =INDEX('Master Data'!$B$323:$K$376,MATCH('Production Cost'!$B25,'Master Data'!$B$323:$B$376,0),MATCH('Production Cost'!F$3,'Master Data'!$B$323:$K$323,0)) -> 1 | N25: =IF(H25="Maruthi Plastics",INDEX('Master Data'!$B$202:$L$255,MATCH('Production Cost'!B25,'Master Data'!$B$202:$B$255,0),MATCH('Production Cost'!F25,'Master Data'!$B$202:$L$202,0)),INDEX('Master Data'!$B$261:$L$314,MATCH('Production Cost'!B25,'Master Data'!$B$261:$B$314,0),MATCH('Production Cost'!F25,'Master Data'!$B$261:$L$261,0))) -> One side Transparent Flat Bottom with Zipper (1000Gm) | O25: =1000/L25 -> 1000 | P25: =+VLOOKUP($N25,'Master Data'!$B:$W,IF(G25="Wholesale",21,22),FALSE) -> 11.94 | Q25: =+P25*M25 -> 11.94 | R25: =IF(G25="Wholesale",'Master Data'!$V$127*$M25,'Master Data'!$W$127*$M25) -> 2.2 | S25: =IF(G25="Wholesale",'Master Data'!$V$111*$M25,'Master Data'!$W$111*$M25) -> 3.0769231 | T25: =IF(F25=1000,'Master Data'!$AF$40,IF(F25=500,'Master Data'!$AF$39,IF(F25=250,'Master Data'!$AF$39,'Master Data'!$AF$38))) -> 11.116667 | U25: =IF(F25=1000,VLOOKUP($E25,'Master Data'!$B:$W,IF(G25="Wholesale",21,22),FALSE),IF(F25=500,VLOOKUP($E25,'Master Data'!$B:$W,IF(G25="Wholesale",21,22),FALSE)/2,IF(F25=250,VLOOKUP($E25,'Master Data'!$B:$W,IF(G25="Wholesale",21,22),FALSE)/3,IF(F25=100,VLOOKUP($E25,'Master Data'!$B:$W,IF(G25="Wholesale",21,22),FALSE)/4,IF(F25=50,VLOOKUP($E25,'Master Data'!$B:$W,IF(G25="Wholesale",21,22),FALSE)/6,IF(F25=25,VLOOKUP($E25,'Master Data'!$B:$W,IF(G25="Wholesale",21,22),FALSE)/8,VLOOKUP($E25,'Master Data'!$B:$W,IF(G25="Wholesale",21,22),FALSE)/8)))))) -> 0 | V25: =+VLOOKUP($I25,'Master Data'!$B:$V,IF(G25="Wholesale",20,21),FALSE) -> 40 | W25: =IF(F25=1000,'Master Data'!$AB$32,IF(F25=500,'Master Data'!$AB$33,IF(F25=250,'Master Data'!$AB$34,IF(F25=100,'Master Data'!$AB$35,IF(F25=50,'Master Data'!$AB$36,IF(F25=25,'Master Data'!$AB$37,'Master Data'!$AB$38)))))) -> 56.55 | X25: =+((K25*F25)+$Q25+$R25+$U25+S25)*($J25/100) -> 30.321692 | Y25: =+(F25*K25)+Q25+R25+S25+U25+(IF(F25=1000,V25,IF(F25=500,V25/2,IF(F25=250,V25/4,IF(F25=100,V25/10,IF(F25=50,V25/20,V25/40)))))+X25) -> 373.53862 | Z25: =+Y25/L25 -> 373.53862 | AA25: =(F25*K25)+Q25+R25+S25+T25+U25+W25+X25 -> 401.20528 | AB25: =+((K25*F25)+$Q25+$R25+$U25+$S25+$T25)*($J25/100) -> 31.433359 | AC25: =(F25*K25)+Q25+R25+S25+T25+U25+AB25 -> 345.76695 | AD25: =AC25*1.5 -> 518.65042
A26: =+A25+1 -> 24 | B26: Red Chilli Powder - Very Spicy | C26: लाल मिर्च पाउडर – तीव्र मसालेदार | D26: =+VLOOKUP($B26,'Master Data'!$B$20:$W$197,2,FALSE) -> MS Malagi | E26: Recycle Box | F26: 1000 | G26: Wholesale | H26: Maruthi Plastics | I26: Shree Maruthi Couriers-Local | J26: 10 | K26: =IF(D26="In House Production",INDEX('Master Data'!$H$552:$J$580,MATCH('Production Cost'!B26,'Master Data'!$H$552:$H$580,0),3),VLOOKUP($B26,'Master Data'!$B:$W,IF(G26="Wholesale",21,22),FALSE)) -> 0.281 | L26: 1 | M26: =INDEX('Master Data'!$B$323:$K$376,MATCH('Production Cost'!$B26,'Master Data'!$B$323:$B$376,0),MATCH('Production Cost'!F$3,'Master Data'!$B$323:$K$323,0)) -> 1 | N26: =IF(H26="Maruthi Plastics",INDEX('Master Data'!$B$202:$L$255,MATCH('Production Cost'!B26,'Master Data'!$B$202:$B$255,0),MATCH('Production Cost'!F26,'Master Data'!$B$202:$L$202,0)),INDEX('Master Data'!$B$261:$L$314,MATCH('Production Cost'!B26,'Master Data'!$B$261:$B$314,0),MATCH('Production Cost'!F26,'Master Data'!$B$261:$L$261,0))) -> One side Transparent Flat Bottom with Zipper (1000Gm) | O26: =1000/L26 -> 1000 | P26: =+VLOOKUP($N26,'Master Data'!$B:$W,IF(G26="Wholesale",21,22),FALSE) -> 11.94 | Q26: =+P26*M26 -> 11.94 | R26: =IF(G26="Wholesale",'Master Data'!$V$127*$M26,'Master Data'!$W$127*$M26) -> 2.2 | S26: =IF(G26="Wholesale",'Master Data'!$V$111*$M26,'Master Data'!$W$111*$M26) -> 3.0769231 | T26: =IF(F26=1000,'Master Data'!$AF$40,IF(F26=500,'Master Data'!$AF$39,IF(F26=250,'Master Data'!$AF$39,'Master Data'!$AF$38))) -> 11.116667 | U26: =IF(F26=1000,VLOOKUP($E26,'Master Data'!$B:$W,IF(G26="Wholesale",21,22),FALSE),IF(F26=500,VLOOKUP($E26,'Master Data'!$B:$W,IF(G26="Wholesale",21,22),FALSE)/2,IF(F26=250,VLOOKUP($E26,'Master Data'!$B:$W,IF(G26="Wholesale",21,22),FALSE)/3,IF(F26=100,VLOOKUP($E26,'Master Data'!$B:$W,IF(G26="Wholesale",21,22),FALSE)/4,IF(F26=50,VLOOKUP($E26,'Master Data'!$B:$W,IF(G26="Wholesale",21,22),FALSE)/6,IF(F26=25,VLOOKUP($E26,'Master Data'!$B:$W,IF(G26="Wholesale",21,22),FALSE)/8,VLOOKUP($E26,'Master Data'!$B:$W,IF(G26="Wholesale",21,22),FALSE)/8)))))) -> 0 | V26: =+VLOOKUP($I26,'Master Data'!$B:$V,IF(G26="Wholesale",20,21),FALSE) -> 40 | W26: =IF(F26=1000,'Master Data'!$AB$32,IF(F26=500,'Master Data'!$AB$33,IF(F26=250,'Master Data'!$AB$34,IF(F26=100,'Master Data'!$AB$35,IF(F26=50,'Master Data'!$AB$36,IF(F26=25,'Master Data'!$AB$37,'Master Data'!$AB$38)))))) -> 56.55 | X26: =+((K26*F26)+$Q26+$R26+$U26+S26)*($J26/100) -> 29.821692 | Y26: =+(F26*K26)+Q26+R26+S26+U26+(IF(F26=1000,V26,IF(F26=500,V26/2,IF(F26=250,V26/4,IF(F26=100,V26/10,IF(F26=50,V26/20,V26/40)))))+X26) -> 368.03862 | Z26: =+Y26/L26 -> 368.03862 | AA26: =(F26*K26)+Q26+R26+S26+T26+U26+W26+X26 -> 395.70528 | AB26: =+((K26*F26)+$Q26+$R26+$U26+$S26+$T26)*($J26/100) -> 30.933359 | AC26: =(F26*K26)+Q26+R26+S26+T26+U26+AB26 -> 340.26695 | AD26: =AC26*1.5 -> 510.40042
A27: =+A26+1 -> 25 | B27: Red Chilli Powder - Premium Kashmiri | C27: लाल मिर्च पाउडर – प्रीमियम कश्मीरी | D27: =+VLOOKUP($B27,'Master Data'!$B$20:$W$197,2,FALSE) -> MS Malagi | E27: Recycle Box | F27: 1000 | G27: Wholesale | H27: Maruthi Plastics | I27: Shree Maruthi Couriers-Local | J27: 10 | K27: =IF(D27="In House Production",INDEX('Master Data'!$H$552:$J$580,MATCH('Production Cost'!B27,'Master Data'!$H$552:$H$580,0),3),VLOOKUP($B27,'Master Data'!$B:$W,IF(G27="Wholesale",21,22),FALSE)) -> 0.601 | L27: 1 | M27: =INDEX('Master Data'!$B$323:$K$376,MATCH('Production Cost'!$B27,'Master Data'!$B$323:$B$376,0),MATCH('Production Cost'!F$3,'Master Data'!$B$323:$K$323,0)) -> 1 | N27: =IF(H27="Maruthi Plastics",INDEX('Master Data'!$B$202:$L$255,MATCH('Production Cost'!B27,'Master Data'!$B$202:$B$255,0),MATCH('Production Cost'!F27,'Master Data'!$B$202:$L$202,0)),INDEX('Master Data'!$B$261:$L$314,MATCH('Production Cost'!B27,'Master Data'!$B$261:$B$314,0),MATCH('Production Cost'!F27,'Master Data'!$B$261:$L$261,0))) -> One side Transparent Flat Bottom with Zipper (1000Gm) | O27: =1000/L27 -> 1000 | P27: =+VLOOKUP($N27,'Master Data'!$B:$W,IF(G27="Wholesale",21,22),FALSE) -> 11.94 | Q27: =+P27*M27 -> 11.94 | R27: =IF(G27="Wholesale",'Master Data'!$V$127*$M27,'Master Data'!$W$127*$M27) -> 2.2 | S27: =IF(G27="Wholesale",'Master Data'!$V$111*$M27,'Master Data'!$W$111*$M27) -> 3.0769231 | T27: =IF(F27=1000,'Master Data'!$AF$40,IF(F27=500,'Master Data'!$AF$39,IF(F27=250,'Master Data'!$AF$39,'Master Data'!$AF$38))) -> 11.116667 | U27: =IF(F27=1000,VLOOKUP($E27,'Master Data'!$B:$W,IF(G27="Wholesale",21,22),FALSE),IF(F27=500,VLOOKUP($E27,'Master Data'!$B:$W,IF(G27="Wholesale",21,22),FALSE)/2,IF(F27=250,VLOOKUP($E27,'Master Data'!$B:$W,IF(G27="Wholesale",21,22),FALSE)/3,IF(F27=100,VLOOKUP($E27,'Master Data'!$B:$W,IF(G27="Wholesale",21,22),FALSE)/4,IF(F27=50,VLOOKUP($E27,'Master Data'!$B:$W,IF(G27="Wholesale",21,22),FALSE)/6,IF(F27=25,VLOOKUP($E27,'Master Data'!$B:$W,IF(G27="Wholesale",21,22),FALSE)/8,VLOOKUP($E27,'Master Data'!$B:$W,IF(G27="Wholesale",21,22),FALSE)/8)))))) -> 0 | V27: =+VLOOKUP($I27,'Master Data'!$B:$V,IF(G27="Wholesale",20,21),FALSE) -> 40 | W27: =IF(F27=1000,'Master Data'!$AB$32,IF(F27=500,'Master Data'!$AB$33,IF(F27=250,'Master Data'!$AB$34,IF(F27=100,'Master Data'!$AB$35,IF(F27=50,'Master Data'!$AB$36,IF(F27=25,'Master Data'!$AB$37,'Master Data'!$AB$38)))))) -> 56.55 | X27: =+((K27*F27)+$Q27+$R27+$U27+S27)*($J27/100) -> 61.821692 | Y27: =+(F27*K27)+Q27+R27+S27+U27+(IF(F27=1000,V27,IF(F27=500,V27/2,IF(F27=250,V27/4,IF(F27=100,V27/10,IF(F27=50,V27/20,V27/40)))))+X27) -> 720.03862 | Z27: =+Y27/L27 -> 720.03862 | AA27: =(F27*K27)+Q27+R27+S27+T27+U27+W27+X27 -> 747.70528 | AB27: =+((K27*F27)+$Q27+$R27+$U27+$S27+$T27)*($J27/100) -> 62.933359 | AC27: =(F27*K27)+Q27+R27+S27+T27+U27+AB27 -> 692.26695 | AD27: =AC27*1.5 -> 1038.4004
A28: =+A27+1 -> 26 | B28: Turmeric Powder - Erode | C28: हल्दी पाउडर - इरोड | D28: =+VLOOKUP($B28,'Master Data'!$B$20:$W$197,2,FALSE) -> SMR | E28: Recycle Box | F28: 1000 | G28: Wholesale | H28: Maruthi Plastics | I28: Shree Maruthi Couriers-Local | J28: 10 | K28: =IF(D28="In House Production",INDEX('Master Data'!$H$552:$J$580,MATCH('Production Cost'!B28,'Master Data'!$H$552:$H$580,0),3),VLOOKUP($B28,'Master Data'!$B:$W,IF(G28="Wholesale",21,22),FALSE)) -> 0.217 | L28: 1 | M28: =INDEX('Master Data'!$B$323:$K$376,MATCH('Production Cost'!$B28,'Master Data'!$B$323:$B$376,0),MATCH('Production Cost'!F$3,'Master Data'!$B$323:$K$323,0)) -> 1 | N28: =IF(H28="Maruthi Plastics",INDEX('Master Data'!$B$202:$L$255,MATCH('Production Cost'!B28,'Master Data'!$B$202:$B$255,0),MATCH('Production Cost'!F28,'Master Data'!$B$202:$L$202,0)),INDEX('Master Data'!$B$261:$L$314,MATCH('Production Cost'!B28,'Master Data'!$B$261:$B$314,0),MATCH('Production Cost'!F28,'Master Data'!$B$261:$L$261,0))) -> One side Transparent Flat Bottom with Zipper (1000Gm) | O28: =1000/L28 -> 1000 | P28: =+VLOOKUP($N28,'Master Data'!$B:$W,IF(G28="Wholesale",21,22),FALSE) -> 11.94 | Q28: =+P28*M28 -> 11.94 | R28: =IF(G28="Wholesale",'Master Data'!$V$127*$M28,'Master Data'!$W$127*$M28) -> 2.2 | S28: =IF(G28="Wholesale",'Master Data'!$V$111*$M28,'Master Data'!$W$111*$M28) -> 3.0769231 | T28: =IF(F28=1000,'Master Data'!$AF$40,IF(F28=500,'Master Data'!$AF$39,IF(F28=250,'Master Data'!$AF$39,'Master Data'!$AF$38))) -> 11.116667 | U28: =IF(F28=1000,VLOOKUP($E28,'Master Data'!$B:$W,IF(G28="Wholesale",21,22),FALSE),IF(F28=500,VLOOKUP($E28,'Master Data'!$B:$W,IF(G28="Wholesale",21,22),FALSE)/2,IF(F28=250,VLOOKUP($E28,'Master Data'!$B:$W,IF(G28="Wholesale",21,22),FALSE)/3,IF(F28=100,VLOOKUP($E28,'Master Data'!$B:$W,IF(G28="Wholesale",21,22),FALSE)/4,IF(F28=50,VLOOKUP($E28,'Master Data'!$B:$W,IF(G28="Wholesale",21,22),FALSE)/6,IF(F28=25,VLOOKUP($E28,'Master Data'!$B:$W,IF(G28="Wholesale",21,22),FALSE)/8,VLOOKUP($E28,'Master Data'!$B:$W,IF(G28="Wholesale",21,22),FALSE)/8)))))) -> 0 | V28: =+VLOOKUP($I28,'Master Data'!$B:$V,IF(G28="Wholesale",20,21),FALSE) -> 40 | W28: =IF(F28=1000,'Master Data'!$AB$32,IF(F28=500,'Master Data'!$AB$33,IF(F28=250,'Master Data'!$AB$34,IF(F28=100,'Master Data'!$AB$35,IF(F28=50,'Master Data'!$AB$36,IF(F28=25,'Master Data'!$AB$37,'Master Data'!$AB$38)))))) -> 56.55 | X28: =+((K28*F28)+$Q28+$R28+$U28+S28)*($J28/100) -> 23.421692 | Y28: =+(F28*K28)+Q28+R28+S28+U28+(IF(F28=1000,V28,IF(F28=500,V28/2,IF(F28=250,V28/4,IF(F28=100,V28/10,IF(F28=50,V28/20,V28/40)))))+X28) -> 297.63862 | Z28: =+Y28/L28 -> 297.63862 | AA28: =(F28*K28)+Q28+R28+S28+T28+U28+W28+X28 -> 325.30528 | AB28: =+((K28*F28)+$Q28+$R28+$U28+$S28+$T28)*($J28/100) -> 24.533359 | AC28: =(F28*K28)+Q28+R28+S28+T28+U28+AB28 -> 269.86695 | AD28: =AC28*1.5 -> 404.80042
A29: =+A28+1 -> 27 | B29: Turmeric Powder - Lakadong | C29: हल्दी पाउडर - लकडोंग | D29: =+VLOOKUP($B29,'Master Data'!$B$20:$W$197,2,FALSE) -> Na Risa | E29: Recycle Box | F29: 1000 | G29: Wholesale | H29: Maruthi Plastics | I29: Shree Maruthi Couriers-Local | J29: 10 | K29: =IF(D29="In House Production",INDEX('Master Data'!$H$552:$J$580,MATCH('Production Cost'!B29,'Master Data'!$H$552:$H$580,0),3),VLOOKUP($B29,'Master Data'!$B:$W,IF(G29="Wholesale",21,22),FALSE)) -> 0.447 | L29: 1 | M29: =INDEX('Master Data'!$B$323:$K$376,MATCH('Production Cost'!$B29,'Master Data'!$B$323:$B$376,0),MATCH('Production Cost'!F$3,'Master Data'!$B$323:$K$323,0)) -> 1 | N29: =IF(H29="Maruthi Plastics",INDEX('Master Data'!$B$202:$L$255,MATCH('Production Cost'!B29,'Master Data'!$B$202:$B$255,0),MATCH('Production Cost'!F29,'Master Data'!$B$202:$L$202,0)),INDEX('Master Data'!$B$261:$L$314,MATCH('Production Cost'!B29,'Master Data'!$B$261:$B$314,0),MATCH('Production Cost'!F29,'Master Data'!$B$261:$L$261,0))) -> One side Transparent Flat Bottom with Zipper (1000Gm) | O29: =1000/L29 -> 1000 | P29: =+VLOOKUP($N29,'Master Data'!$B:$W,IF(G29="Wholesale",21,22),FALSE) -> 11.94 | Q29: =+P29*M29 -> 11.94 | R29: =IF(G29="Wholesale",'Master Data'!$V$127*$M29,'Master Data'!$W$127*$M29) -> 2.2 | S29: =IF(G29="Wholesale",'Master Data'!$V$111*$M29,'Master Data'!$W$111*$M29) -> 3.0769231 | T29: =IF(F29=1000,'Master Data'!$AF$40,IF(F29=500,'Master Data'!$AF$39,IF(F29=250,'Master Data'!$AF$39,'Master Data'!$AF$38))) -> 11.116667 | U29: =IF(F29=1000,VLOOKUP($E29,'Master Data'!$B:$W,IF(G29="Wholesale",21,22),FALSE),IF(F29=500,VLOOKUP($E29,'Master Data'!$B:$W,IF(G29="Wholesale",21,22),FALSE)/2,IF(F29=250,VLOOKUP($E29,'Master Data'!$B:$W,IF(G29="Wholesale",21,22),FALSE)/3,IF(F29=100,VLOOKUP($E29,'Master Data'!$B:$W,IF(G29="Wholesale",21,22),FALSE)/4,IF(F29=50,VLOOKUP($E29,'Master Data'!$B:$W,IF(G29="Wholesale",21,22),FALSE)/6,IF(F29=25,VLOOKUP($E29,'Master Data'!$B:$W,IF(G29="Wholesale",21,22),FALSE)/8,VLOOKUP($E29,'Master Data'!$B:$W,IF(G29="Wholesale",21,22),FALSE)/8)))))) -> 0 | V29: =+VLOOKUP($I29,'Master Data'!$B:$V,IF(G29="Wholesale",20,21),FALSE) -> 40 | W29: =IF(F29=1000,'Master Data'!$AB$32,IF(F29=500,'Master Data'!$AB$33,IF(F29=250,'Master Data'!$AB$34,IF(F29=100,'Master Data'!$AB$35,IF(F29=50,'Master Data'!$AB$36,IF(F29=25,'Master Data'!$AB$37,'Master Data'!$AB$38)))))) -> 56.55 | X29: =+((K29*F29)+$Q29+$R29+$U29+S29)*($J29/100) -> 46.421692 | Y29: =+(F29*K29)+Q29+R29+S29+U29+(IF(F29=1000,V29,IF(F29=500,V29/2,IF(F29=250,V29/4,IF(F29=100,V29/10,IF(F29=50,V29/20,V29/40)))))+X29) -> 550.63862 | Z29: =+Y29/L29 -> 550.63862 | AA29: =(F29*K29)+Q29+R29+S29+T29+U29+W29+X29 -> 578.30528 | AB29: =+((K29*F29)+$Q29+$R29+$U29+$S29+$T29)*($J29/100) -> 47.533359 | AC29: =(F29*K29)+Q29+R29+S29+T29+U29+AB29 -> 522.86695 | AD29: =AC29*1.5 -> 784.30042
A30: =+A29+1 -> 28 | B30: Asafoetida | C30: हींग | D30: =+VLOOKUP($B30,'Master Data'!$B$20:$W$197,2,FALSE) -> Chandan Enterprise | E30: Recycle Box | F30: 1000 | G30: Wholesale | H30: Maruthi Plastics | I30: Shree Maruthi Couriers-Local | J30: 10 | K30: =IF(D30="In House Production",INDEX('Master Data'!$H$552:$J$580,MATCH('Production Cost'!B30,'Master Data'!$H$552:$H$580,0),3),VLOOKUP($B30,'Master Data'!$B:$W,IF(G30="Wholesale",21,22),FALSE)) -> 0.538 | L30: 1 | M30: =INDEX('Master Data'!$B$323:$K$376,MATCH('Production Cost'!$B30,'Master Data'!$B$323:$B$376,0),MATCH('Production Cost'!F$3,'Master Data'!$B$323:$K$323,0)) -> 1 | N30: =IF(H30="Maruthi Plastics",INDEX('Master Data'!$B$202:$L$255,MATCH('Production Cost'!B30,'Master Data'!$B$202:$B$255,0),MATCH('Production Cost'!F30,'Master Data'!$B$202:$L$202,0)),INDEX('Master Data'!$B$261:$L$314,MATCH('Production Cost'!B30,'Master Data'!$B$261:$B$314,0),MATCH('Production Cost'!F30,'Master Data'!$B$261:$L$261,0))) -> Flat Bottom Pouches With Normal Zipper 1 kg | O30: =1000/L30 -> 1000 | P30: =+VLOOKUP($N30,'Master Data'!$B:$W,IF(G30="Wholesale",21,22),FALSE) -> 16.13 | Q30: =+P30*M30 -> 16.13 | R30: =IF(G30="Wholesale",'Master Data'!$V$127*$M30,'Master Data'!$W$127*$M30) -> 2.2 | S30: =IF(G30="Wholesale",'Master Data'!$V$111*$M30,'Master Data'!$W$111*$M30) -> 3.0769231 | T30: =IF(F30=1000,'Master Data'!$AF$40,IF(F30=500,'Master Data'!$AF$39,IF(F30=250,'Master Data'!$AF$39,'Master Data'!$AF$38))) -> 11.116667 | U30: =IF(F30=1000,VLOOKUP($E30,'Master Data'!$B:$W,IF(G30="Wholesale",21,22),FALSE),IF(F30=500,VLOOKUP($E30,'Master Data'!$B:$W,IF(G30="Wholesale",21,22),FALSE)/2,IF(F30=250,VLOOKUP($E30,'Master Data'!$B:$W,IF(G30="Wholesale",21,22),FALSE)/3,IF(F30=100,VLOOKUP($E30,'Master Data'!$B:$W,IF(G30="Wholesale",21,22),FALSE)/4,IF(F30=50,VLOOKUP($E30,'Master Data'!$B:$W,IF(G30="Wholesale",21,22),FALSE)/6,IF(F30=25,VLOOKUP($E30,'Master Data'!$B:$W,IF(G30="Wholesale",21,22),FALSE)/8,VLOOKUP($E30,'Master Data'!$B:$W,IF(G30="Wholesale",21,22),FALSE)/8)))))) -> 0 | V30: =+VLOOKUP($I30,'Master Data'!$B:$V,IF(G30="Wholesale",20,21),FALSE) -> 40 | W30: =IF(F30=1000,'Master Data'!$AB$32,IF(F30=500,'Master Data'!$AB$33,IF(F30=250,'Master Data'!$AB$34,IF(F30=100,'Master Data'!$AB$35,IF(F30=50,'Master Data'!$AB$36,IF(F30=25,'Master Data'!$AB$37,'Master Data'!$AB$38)))))) -> 56.55 | X30: =+((K30*F30)+$Q30+$R30+$U30+S30)*($J30/100) -> 55.940692 | Y30: =+(F30*K30)+Q30+R30+S30+U30+(IF(F30=1000,V30,IF(F30=500,V30/2,IF(F30=250,V30/4,IF(F30=100,V30/10,IF(F30=50,V30/20,V30/40)))))+X30) -> 655.34762 | Z30: =+Y30/L30 -> 655.34762 | AA30: =(F30*K30)+Q30+R30+S30+T30+U30+W30+X30 -> 683.01428 | AB30: =+((K30*F30)+$Q30+$R30+$U30+$S30+$T30)*($J30/100) -> 57.052359 | AC30: =(F30*K30)+Q30+R30+S30+T30+U30+AB30 -> 627.57595 | AD30: =AC30*1.5 -> 941.36392
A31: =+A30+1 -> 29 | B31: Chaat Masala | C31: चाट मसाला | D31: In House Production | E31: Recycle Box | F31: 1000 | G31: Wholesale | H31: Maruthi Plastics | I31: Shree Maruthi Couriers-Local | J31: 10 | K31: =IF(D31="In House Production",INDEX('Master Data'!$H$552:$J$580,MATCH('Production Cost'!B31,'Master Data'!$H$552:$H$580,0),3),VLOOKUP($B31,'Master Data'!$B:$W,IF(G31="Wholesale",21,22),FALSE)) -> 0.27010133 | L31: 1 | M31: =INDEX('Master Data'!$B$323:$K$376,MATCH('Production Cost'!$B31,'Master Data'!$B$323:$B$376,0),MATCH('Production Cost'!F$3,'Master Data'!$B$323:$K$323,0)) -> 1 | N31: =IF(H31="Maruthi Plastics",INDEX('Master Data'!$B$202:$L$255,MATCH('Production Cost'!B31,'Master Data'!$B$202:$B$255,0),MATCH('Production Cost'!F31,'Master Data'!$B$202:$L$202,0)),INDEX('Master Data'!$B$261:$L$314,MATCH('Production Cost'!B31,'Master Data'!$B$261:$B$314,0),MATCH('Production Cost'!F31,'Master Data'!$B$261:$L$261,0))) -> One side Transparent Flat Bottom with Zipper (1000Gm) | O31: =1000/L31 -> 1000 | P31: =+VLOOKUP($N31,'Master Data'!$B:$W,IF(G31="Wholesale",21,22),FALSE) -> 11.94 | Q31: =+P31*M31 -> 11.94 | R31: =IF(G31="Wholesale",'Master Data'!$V$127*$M31,'Master Data'!$W$127*$M31) -> 2.2 | S31: =IF(G31="Wholesale",'Master Data'!$V$111*$M31,'Master Data'!$W$111*$M31) -> 3.0769231 | T31: =IF(F31=1000,'Master Data'!$AF$40,IF(F31=500,'Master Data'!$AF$39,IF(F31=250,'Master Data'!$AF$39,'Master Data'!$AF$38))) -> 11.116667 | U31: =IF(F31=1000,VLOOKUP($E31,'Master Data'!$B:$W,IF(G31="Wholesale",21,22),FALSE),IF(F31=500,VLOOKUP($E31,'Master Data'!$B:$W,IF(G31="Wholesale",21,22),FALSE)/2,IF(F31=250,VLOOKUP($E31,'Master Data'!$B:$W,IF(G31="Wholesale",21,22),FALSE)/3,IF(F31=100,VLOOKUP($E31,'Master Data'!$B:$W,IF(G31="Wholesale",21,22),FALSE)/4,IF(F31=50,VLOOKUP($E31,'Master Data'!$B:$W,IF(G31="Wholesale",21,22),FALSE)/6,IF(F31=25,VLOOKUP($E31,'Master Data'!$B:$W,IF(G31="Wholesale",21,22),FALSE)/8,VLOOKUP($E31,'Master Data'!$B:$W,IF(G31="Wholesale",21,22),FALSE)/8)))))) -> 0 | V31: =+VLOOKUP($I31,'Master Data'!$B:$V,IF(G31="Wholesale",20,21),FALSE) -> 40 | W31: =IF(F31=1000,'Master Data'!$AB$32,IF(F31=500,'Master Data'!$AB$33,IF(F31=250,'Master Data'!$AB$34,IF(F31=100,'Master Data'!$AB$35,IF(F31=50,'Master Data'!$AB$36,IF(F31=25,'Master Data'!$AB$37,'Master Data'!$AB$38)))))) -> 56.55 | X31: =+((K31*F31)+$Q31+$R31+$U31+S31)*($J31/100) -> 28.731826 | Y31: =+(F31*K31)+Q31+R31+S31+U31+(IF(F31=1000,V31,IF(F31=500,V31/2,IF(F31=250,V31/4,IF(F31=100,V31/10,IF(F31=50,V31/20,V31/40)))))+X31) -> 356.05008 | Z31: =+Y31/L31 -> 356.05008 | AA31: =(F31*K31)+Q31+R31+S31+T31+U31+W31+X31 -> 383.71675 | AB31: =+((K31*F31)+$Q31+$R31+$U31+$S31+$T31)*($J31/100) -> 29.843492 | AC31: =(F31*K31)+Q31+R31+S31+T31+U31+AB31 -> 328.27842 | AD31: =AC31*1.5 -> 492.41762
A32: =+A31+1 -> 30 | B32: Punjabi Chole Masala | C32: पंजाबी चना मसाला | D32: In House Production | E32: Recycle Box | F32: 1000 | G32: Wholesale | H32: Maruthi Plastics | I32: Shree Maruthi Couriers-Local | J32: 10 | K32: =IF(D32="In House Production",INDEX('Master Data'!$H$552:$J$580,MATCH('Production Cost'!B32,'Master Data'!$H$552:$H$580,0),3),VLOOKUP($B32,'Master Data'!$B:$W,IF(G32="Wholesale",21,22),FALSE)) -> 0.42411286 | L32: 1 | M32: =INDEX('Master Data'!$B$323:$K$376,MATCH('Production Cost'!$B32,'Master Data'!$B$323:$B$376,0),MATCH('Production Cost'!F$3,'Master Data'!$B$323:$K$323,0)) -> 1 | N32: =IF(H32="Maruthi Plastics",INDEX('Master Data'!$B$202:$L$255,MATCH('Production Cost'!B32,'Master Data'!$B$202:$B$255,0),MATCH('Production Cost'!F32,'Master Data'!$B$202:$L$202,0)),INDEX('Master Data'!$B$261:$L$314,MATCH('Production Cost'!B32,'Master Data'!$B$261:$B$314,0),MATCH('Production Cost'!F32,'Master Data'!$B$261:$L$261,0))) -> One side Transparent Flat Bottom with Zipper (1000Gm) | O32: =1000/L32 -> 1000 | P32: =+VLOOKUP($N32,'Master Data'!$B:$W,IF(G32="Wholesale",21,22),FALSE) -> 11.94 | Q32: =+P32*M32 -> 11.94 | R32: =IF(G32="Wholesale",'Master Data'!$V$127*$M32,'Master Data'!$W$127*$M32) -> 2.2 | S32: =IF(G32="Wholesale",'Master Data'!$V$111*$M32,'Master Data'!$W$111*$M32) -> 3.0769231 | T32: =IF(F32=1000,'Master Data'!$AF$40,IF(F32=500,'Master Data'!$AF$39,IF(F32=250,'Master Data'!$AF$39,'Master Data'!$AF$38))) -> 11.116667 | U32: =IF(F32=1000,VLOOKUP($E32,'Master Data'!$B:$W,IF(G32="Wholesale",21,22),FALSE),IF(F32=500,VLOOKUP($E32,'Master Data'!$B:$W,IF(G32="Wholesale",21,22),FALSE)/2,IF(F32=250,VLOOKUP($E32,'Master Data'!$B:$W,IF(G32="Wholesale",21,22),FALSE)/3,IF(F32=100,VLOOKUP($E32,'Master Data'!$B:$W,IF(G32="Wholesale",21,22),FALSE)/4,IF(F32=50,VLOOKUP($E32,'Master Data'!$B:$W,IF(G32="Wholesale",21,22),FALSE)/6,IF(F32=25,VLOOKUP($E32,'Master Data'!$B:$W,IF(G32="Wholesale",21,22),FALSE)/8,VLOOKUP($E32,'Master Data'!$B:$W,IF(G32="Wholesale",21,22),FALSE)/8)))))) -> 0 | V32: =+VLOOKUP($I32,'Master Data'!$B:$V,IF(G32="Wholesale",20,21),FALSE) -> 40 | W32: =IF(F32=1000,'Master Data'!$AB$32,IF(F32=500,'Master Data'!$AB$33,IF(F32=250,'Master Data'!$AB$34,IF(F32=100,'Master Data'!$AB$35,IF(F32=50,'Master Data'!$AB$36,IF(F32=25,'Master Data'!$AB$37,'Master Data'!$AB$38)))))) -> 56.55 | X32: =+((K32*F32)+$Q32+$R32+$U32+S32)*($J32/100) -> 44.132978 | Y32: =+(F32*K32)+Q32+R32+S32+U32+(IF(F32=1000,V32,IF(F32=500,V32/2,IF(F32=250,V32/4,IF(F32=100,V32/10,IF(F32=50,V32/20,V32/40)))))+X32) -> 525.46276 | Z32: =+Y32/L32 -> 525.46276 | AA32: =(F32*K32)+Q32+R32+S32+T32+U32+W32+X32 -> 553.12942 | AB32: =+((K32*F32)+$Q32+$R32+$U32+$S32+$T32)*($J32/100) -> 45.244645 | AC32: =(F32*K32)+Q32+R32+S32+T32+U32+AB32 -> 497.69109 | AD32: =AC32*1.5 -> 746.53664
A33: =+A32+1 -> 31 | B33: Premium Garam Masala | C33: गरम मसाला | D33: In House Production | E33: Recycle Box | F33: 1000 | G33: Wholesale | H33: Maruthi Plastics | I33: Shree Maruthi Couriers-Local | J33: 10 | K33: =IF(D33="In House Production",INDEX('Master Data'!$H$552:$J$580,MATCH('Production Cost'!B33,'Master Data'!$H$552:$H$580,0),3),VLOOKUP($B33,'Master Data'!$B:$W,IF(G33="Wholesale",21,22),FALSE)) -> 0.92878988 | L33: 1 | M33: =INDEX('Master Data'!$B$323:$K$376,MATCH('Production Cost'!$B33,'Master Data'!$B$323:$B$376,0),MATCH('Production Cost'!F$3,'Master Data'!$B$323:$K$323,0)) -> 1 | N33: =IF(H33="Maruthi Plastics",INDEX('Master Data'!$B$202:$L$255,MATCH('Production Cost'!B33,'Master Data'!$B$202:$B$255,0),MATCH('Production Cost'!F33,'Master Data'!$B$202:$L$202,0)),INDEX('Master Data'!$B$261:$L$314,MATCH('Production Cost'!B33,'Master Data'!$B$261:$B$314,0),MATCH('Production Cost'!F33,'Master Data'!$B$261:$L$261,0))) -> One side Transparent Flat Bottom with Zipper (1000Gm) | O33: =1000/L33 -> 1000 | P33: =+VLOOKUP($N33,'Master Data'!$B:$W,IF(G33="Wholesale",21,22),FALSE) -> 11.94 | Q33: =+P33*M33 -> 11.94 | R33: =IF(G33="Wholesale",'Master Data'!$V$127*$M33,'Master Data'!$W$127*$M33) -> 2.2 | S33: =IF(G33="Wholesale",'Master Data'!$V$111*$M33,'Master Data'!$W$111*$M33) -> 3.0769231 | T33: =IF(F33=1000,'Master Data'!$AF$40,IF(F33=500,'Master Data'!$AF$39,IF(F33=250,'Master Data'!$AF$39,'Master Data'!$AF$38))) -> 11.116667 | U33: =IF(F33=1000,VLOOKUP($E33,'Master Data'!$B:$W,IF(G33="Wholesale",21,22),FALSE),IF(F33=500,VLOOKUP($E33,'Master Data'!$B:$W,IF(G33="Wholesale",21,22),FALSE)/2,IF(F33=250,VLOOKUP($E33,'Master Data'!$B:$W,IF(G33="Wholesale",21,22),FALSE)/3,IF(F33=100,VLOOKUP($E33,'Master Data'!$B:$W,IF(G33="Wholesale",21,22),FALSE)/4,IF(F33=50,VLOOKUP($E33,'Master Data'!$B:$W,IF(G33="Wholesale",21,22),FALSE)/6,IF(F33=25,VLOOKUP($E33,'Master Data'!$B:$W,IF(G33="Wholesale",21,22),FALSE)/8,VLOOKUP($E33,'Master Data'!$B:$W,IF(G33="Wholesale",21,22),FALSE)/8)))))) -> 0 | V33: =+VLOOKUP($I33,'Master Data'!$B:$V,IF(G33="Wholesale",20,21),FALSE) -> 40 | W33: =IF(F33=1000,'Master Data'!$AB$32,IF(F33=500,'Master Data'!$AB$33,IF(F33=250,'Master Data'!$AB$34,IF(F33=100,'Master Data'!$AB$35,IF(F33=50,'Master Data'!$AB$36,IF(F33=25,'Master Data'!$AB$37,'Master Data'!$AB$38)))))) -> 56.55 | X33: =+((K33*F33)+$Q33+$R33+$U33+S33)*($J33/100) -> 94.60068 | Y33: =+(F33*K33)+Q33+R33+S33+U33+(IF(F33=1000,V33,IF(F33=500,V33/2,IF(F33=250,V33/4,IF(F33=100,V33/10,IF(F33=50,V33/20,V33/40)))))+X33) -> 1080.6075 | Z33: =+Y33/L33 -> 1080.6075 | AA33: =(F33*K33)+Q33+R33+S33+T33+U33+W33+X33 -> 1108.2741 | AB33: =+((K33*F33)+$Q33+$R33+$U33+$S33+$T33)*($J33/100) -> 95.712347 | AC33: =(F33*K33)+Q33+R33+S33+T33+U33+AB33 -> 1052.8358 | AD33: =AC33*1.5 -> 1579.2537
A34: =+A33+1 -> 32 | B34: Shahi Garam Masala | D34: In House Production | E34: Five Ply Box | F34: 1000 | G34: Wholesale | H34: Maruthi Plastics | I34: Shree Maruthi Couriers-Local | J34: 10 | K34: =IF(D34="In House Production",INDEX('Master Data'!$H$552:$J$580,MATCH('Production Cost'!B34,'Master Data'!$H$552:$H$580,0),3),VLOOKUP($B34,'Master Data'!$B:$W,IF(G34="Wholesale",21,22),FALSE)) -> 1.9052031 | L34: 2 | M34: =INDEX('Master Data'!$B$323:$K$376,MATCH('Production Cost'!$B34,'Master Data'!$B$323:$B$376,0),MATCH('Production Cost'!F$3,'Master Data'!$B$323:$K$323,0)) -> 1 | N34: =IF(H34="Maruthi Plastics",INDEX('Master Data'!$B$202:$L$255,MATCH('Production Cost'!B34,'Master Data'!$B$202:$B$255,0),MATCH('Production Cost'!F34,'Master Data'!$B$202:$L$202,0)),INDEX('Master Data'!$B$261:$L$314,MATCH('Production Cost'!B34,'Master Data'!$B$261:$B$314,0),MATCH('Production Cost'!F34,'Master Data'!$B$261:$L$261,0))) -> One side Transparent Flat Bottom with Zipper (1000Gm) | O34: =1000/L34 -> 500 | P34: =+VLOOKUP($N34,'Master Data'!$B:$W,IF(G34="Wholesale",21,22),FALSE) -> 11.94 | Q34: =+P34*M34 -> 11.94 | R34: =IF(G34="Wholesale",'Master Data'!$V$127*$M34,'Master Data'!$W$127*$M34) -> 2.2 | S34: =IF(G34="Wholesale",'Master Data'!$V$111*$M34,'Master Data'!$W$111*$M34) -> 3.0769231 | T34: =IF(F34=1000,'Master Data'!$AF$40,IF(F34=500,'Master Data'!$AF$39,IF(F34=250,'Master Data'!$AF$39,'Master Data'!$AF$38))) -> 11.116667 | U34: =IF(F34=1000,VLOOKUP($E34,'Master Data'!$B:$W,IF(G34="Wholesale",21,22),FALSE),IF(F34=500,VLOOKUP($E34,'Master Data'!$B:$W,IF(G34="Wholesale",21,22),FALSE)/2,IF(F34=250,VLOOKUP($E34,'Master Data'!$B:$W,IF(G34="Wholesale",21,22),FALSE)/3,IF(F34=100,VLOOKUP($E34,'Master Data'!$B:$W,IF(G34="Wholesale",21,22),FALSE)/4,IF(F34=50,VLOOKUP($E34,'Master Data'!$B:$W,IF(G34="Wholesale",21,22),FALSE)/6,IF(F34=25,VLOOKUP($E34,'Master Data'!$B:$W,IF(G34="Wholesale",21,22),FALSE)/8,VLOOKUP($E34,'Master Data'!$B:$W,IF(G34="Wholesale",21,22),FALSE)/8)))))) -> 55.02 | V34: =+VLOOKUP($I34,'Master Data'!$B:$V,IF(G34="Wholesale",20,21),FALSE) -> 40 | W34: =IF(F34=1000,'Master Data'!$AB$32,IF(F34=500,'Master Data'!$AB$33,IF(F34=250,'Master Data'!$AB$34,IF(F34=100,'Master Data'!$AB$35,IF(F34=50,'Master Data'!$AB$36,IF(F34=25,'Master Data'!$AB$37,'Master Data'!$AB$38)))))) -> 56.55 | X34: =+((K34*F34)+$Q34+$R34+$U34+S34)*($J34/100) -> 197.74401 | Y34: =+(F34*K34)+Q34+R34+S34+U34+(IF(F34=1000,V34,IF(F34=500,V34/2,IF(F34=250,V34/4,IF(F34=100,V34/10,IF(F34=50,V34/20,V34/40)))))+X34) -> 2215.1841 | Z34: =+Y34/L34 -> 1107.592 | AA34: =(F34*K34)+Q34+R34+S34+T34+U34+W34+X34 -> 2242.8507 | AB34: =+((K34*F34)+$Q34+$R34+$U34+$S34+$T34)*($J34/100) -> 198.85567 | AC34: =(F34*K34)+Q34+R34+S34+T34+U34+AB34 -> 2187.4124 | AD34: =AC34*1.5 -> 3281.1186
A35: =+A34+1 -> 33 | B35: Premium Biryani Masala | D35: In House Production | E35: Recycle Box | F35: 1000 | G35: Wholesale | H35: Maruthi Plastics | I35: Shree Maruthi Couriers-Local | J35: 10 | K35: =IF(D35="In House Production",INDEX('Master Data'!$H$552:$J$580,MATCH('Production Cost'!B35,'Master Data'!$H$552:$H$580,0),3),VLOOKUP($B35,'Master Data'!$B:$W,IF(G35="Wholesale",21,22),FALSE)) -> 0.45646741 | L35: 3 | M35: =INDEX('Master Data'!$B$323:$K$376,MATCH('Production Cost'!$B35,'Master Data'!$B$323:$B$376,0),MATCH('Production Cost'!F$3,'Master Data'!$B$323:$K$323,0)) -> 1 | N35: =IF(H35="Maruthi Plastics",INDEX('Master Data'!$B$202:$L$255,MATCH('Production Cost'!B35,'Master Data'!$B$202:$B$255,0),MATCH('Production Cost'!F35,'Master Data'!$B$202:$L$202,0)),INDEX('Master Data'!$B$261:$L$314,MATCH('Production Cost'!B35,'Master Data'!$B$261:$B$314,0),MATCH('Production Cost'!F35,'Master Data'!$B$261:$L$261,0))) -> One side Transparent Flat Bottom with Zipper (1000Gm) | O35: =1000/L35 -> 333.33333 | P35: =+VLOOKUP($N35,'Master Data'!$B:$W,IF(G35="Wholesale",21,22),FALSE) -> 11.94 | Q35: =+P35*M35 -> 11.94 | R35: =IF(G35="Wholesale",'Master Data'!$V$127*$M35,'Master Data'!$W$127*$M35) -> 2.2 | S35: =IF(G35="Wholesale",'Master Data'!$V$111*$M35,'Master Data'!$W$111*$M35) -> 3.0769231 | T35: =IF(F35=1000,'Master Data'!$AF$40,IF(F35=500,'Master Data'!$AF$39,IF(F35=250,'Master Data'!$AF$39,'Master Data'!$AF$38))) -> 11.116667 | U35: =IF(F35=1000,VLOOKUP($E35,'Master Data'!$B:$W,IF(G35="Wholesale",21,22),FALSE),IF(F35=500,VLOOKUP($E35,'Master Data'!$B:$W,IF(G35="Wholesale",21,22),FALSE)/2,IF(F35=250,VLOOKUP($E35,'Master Data'!$B:$W,IF(G35="Wholesale",21,22),FALSE)/3,IF(F35=100,VLOOKUP($E35,'Master Data'!$B:$W,IF(G35="Wholesale",21,22),FALSE)/4,IF(F35=50,VLOOKUP($E35,'Master Data'!$B:$W,IF(G35="Wholesale",21,22),FALSE)/6,IF(F35=25,VLOOKUP($E35,'Master Data'!$B:$W,IF(G35="Wholesale",21,22),FALSE)/8,VLOOKUP($E35,'Master Data'!$B:$W,IF(G35="Wholesale",21,22),FALSE)/8)))))) -> 0 | V35: =+VLOOKUP($I35,'Master Data'!$B:$V,IF(G35="Wholesale",20,21),FALSE) -> 40 | W35: =IF(F35=1000,'Master Data'!$AB$32,IF(F35=500,'Master Data'!$AB$33,IF(F35=250,'Master Data'!$AB$34,IF(F35=100,'Master Data'!$AB$35,IF(F35=50,'Master Data'!$AB$36,IF(F35=25,'Master Data'!$AB$37,'Master Data'!$AB$38)))))) -> 56.55 | X35: =+((K35*F35)+$Q35+$R35+$U35+S35)*($J35/100) -> 47.368433 | Y35: =+(F35*K35)+Q35+R35+S35+U35+(IF(F35=1000,V35,IF(F35=500,V35/2,IF(F35=250,V35/4,IF(F35=100,V35/10,IF(F35=50,V35/20,V35/40)))))+X35) -> 561.05276 | Z35: =+Y35/L35 -> 187.01759 | AA35: =(F35*K35)+Q35+R35+S35+T35+U35+W35+X35 -> 588.71943 | AB35: =+((K35*F35)+$Q35+$R35+$U35+$S35+$T35)*($J35/100) -> 48.4801 | AC35: =(F35*K35)+Q35+R35+S35+T35+U35+AB35 -> 533.2811 | AD35: =AC35*1.5 -> 799.92165
A36: =+A35+1 -> 34 | B36: Rasam Masala Powder | C36: रसम मसाला | D36: In House Production | E36: Recycle Box | F36: 1000 | G36: Wholesale | H36: Maruthi Plastics | I36: Shree Maruthi Couriers-Local | J36: 10 | K36: =IF(D36="In House Production",INDEX('Master Data'!$H$552:$J$580,MATCH('Production Cost'!B36,'Master Data'!$H$552:$H$580,0),3),VLOOKUP($B36,'Master Data'!$B:$W,IF(G36="Wholesale",21,22),FALSE)) -> 0.24647333 | L36: 1 | M36: =INDEX('Master Data'!$B$323:$K$376,MATCH('Production Cost'!$B36,'Master Data'!$B$323:$B$376,0),MATCH('Production Cost'!F$3,'Master Data'!$B$323:$K$323,0)) -> 1 | N36: =IF(H36="Maruthi Plastics",INDEX('Master Data'!$B$202:$L$255,MATCH('Production Cost'!B36,'Master Data'!$B$202:$B$255,0),MATCH('Production Cost'!F36,'Master Data'!$B$202:$L$202,0)),INDEX('Master Data'!$B$261:$L$314,MATCH('Production Cost'!B36,'Master Data'!$B$261:$B$314,0),MATCH('Production Cost'!F36,'Master Data'!$B$261:$L$261,0))) -> One side Transparent Flat Bottom with Zipper (1000Gm) | O36: =1000/L36 -> 1000 | P36: =+VLOOKUP($N36,'Master Data'!$B:$W,IF(G36="Wholesale",21,22),FALSE) -> 11.94 | Q36: =+P36*M36 -> 11.94 | R36: =IF(G36="Wholesale",'Master Data'!$V$127*$M36,'Master Data'!$W$127*$M36) -> 2.2 | S36: =IF(G36="Wholesale",'Master Data'!$V$111*$M36,'Master Data'!$W$111*$M36) -> 3.0769231 | T36: =IF(F36=1000,'Master Data'!$AF$40,IF(F36=500,'Master Data'!$AF$39,IF(F36=250,'Master Data'!$AF$39,'Master Data'!$AF$38))) -> 11.116667 | U36: =IF(F36=1000,VLOOKUP($E36,'Master Data'!$B:$W,IF(G36="Wholesale",21,22),FALSE),IF(F36=500,VLOOKUP($E36,'Master Data'!$B:$W,IF(G36="Wholesale",21,22),FALSE)/2,IF(F36=250,VLOOKUP($E36,'Master Data'!$B:$W,IF(G36="Wholesale",21,22),FALSE)/3,IF(F36=100,VLOOKUP($E36,'Master Data'!$B:$W,IF(G36="Wholesale",21,22),FALSE)/4,IF(F36=50,VLOOKUP($E36,'Master Data'!$B:$W,IF(G36="Wholesale",21,22),FALSE)/6,IF(F36=25,VLOOKUP($E36,'Master Data'!$B:$W,IF(G36="Wholesale",21,22),FALSE)/8,VLOOKUP($E36,'Master Data'!$B:$W,IF(G36="Wholesale",21,22),FALSE)/8)))))) -> 0 | V36: =+VLOOKUP($I36,'Master Data'!$B:$V,IF(G36="Wholesale",20,21),FALSE) -> 40 | W36: =IF(F36=1000,'Master Data'!$AB$32,IF(F36=500,'Master Data'!$AB$33,IF(F36=250,'Master Data'!$AB$34,IF(F36=100,'Master Data'!$AB$35,IF(F36=50,'Master Data'!$AB$36,IF(F36=25,'Master Data'!$AB$37,'Master Data'!$AB$38)))))) -> 56.55 | X36: =+((K36*F36)+$Q36+$R36+$U36+S36)*($J36/100) -> 26.369026 | Y36: =+(F36*K36)+Q36+R36+S36+U36+(IF(F36=1000,V36,IF(F36=500,V36/2,IF(F36=250,V36/4,IF(F36=100,V36/10,IF(F36=50,V36/20,V36/40)))))+X36) -> 330.05928 | Z36: =+Y36/L36 -> 330.05928 | AA36: =(F36*K36)+Q36+R36+S36+T36+U36+W36+X36 -> 357.72595 | AB36: =+((K36*F36)+$Q36+$R36+$U36+$S36+$T36)*($J36/100) -> 27.480692 | AC36: =(F36*K36)+Q36+R36+S36+T36+U36+AB36 -> 302.28762 | AD36: =AC36*1.5 -> 453.43142
A37: =+A36+1 -> 35 | B37: Sambar Masala Powder | C37: सांभर मसाला | D37: In House Production | E37: Recycle Box | F37: 1000 | G37: Wholesale | H37: Maruthi Plastics | I37: Shree Maruthi Couriers-Local | J37: 10 | K37: =IF(D37="In House Production",INDEX('Master Data'!$H$552:$J$580,MATCH('Production Cost'!B37,'Master Data'!$H$552:$H$580,0),3),VLOOKUP($B37,'Master Data'!$B:$W,IF(G37="Wholesale",21,22),FALSE)) -> 0.3538876 | L37: 1 | M37: =INDEX('Master Data'!$B$323:$K$376,MATCH('Production Cost'!$B37,'Master Data'!$B$323:$B$376,0),MATCH('Production Cost'!F$3,'Master Data'!$B$323:$K$323,0)) -> 1 | N37: =IF(H37="Maruthi Plastics",INDEX('Master Data'!$B$202:$L$255,MATCH('Production Cost'!B37,'Master Data'!$B$202:$B$255,0),MATCH('Production Cost'!F37,'Master Data'!$B$202:$L$202,0)),INDEX('Master Data'!$B$261:$L$314,MATCH('Production Cost'!B37,'Master Data'!$B$261:$B$314,0),MATCH('Production Cost'!F37,'Master Data'!$B$261:$L$261,0))) -> One side Transparent Flat Bottom with Zipper (1000Gm) | O37: =1000/L37 -> 1000 | P37: =+VLOOKUP($N37,'Master Data'!$B:$W,IF(G37="Wholesale",21,22),FALSE) -> 11.94 | Q37: =+P37*M37 -> 11.94 | R37: =IF(G37="Wholesale",'Master Data'!$V$127*$M37,'Master Data'!$W$127*$M37) -> 2.2 | S37: =IF(G37="Wholesale",'Master Data'!$V$111*$M37,'Master Data'!$W$111*$M37) -> 3.0769231 | T37: =IF(F37=1000,'Master Data'!$AF$40,IF(F37=500,'Master Data'!$AF$39,IF(F37=250,'Master Data'!$AF$39,'Master Data'!$AF$38))) -> 11.116667 | U37: =IF(F37=1000,VLOOKUP($E37,'Master Data'!$B:$W,IF(G37="Wholesale",21,22),FALSE),IF(F37=500,VLOOKUP($E37,'Master Data'!$B:$W,IF(G37="Wholesale",21,22),FALSE)/2,IF(F37=250,VLOOKUP($E37,'Master Data'!$B:$W,IF(G37="Wholesale",21,22),FALSE)/3,IF(F37=100,VLOOKUP($E37,'Master Data'!$B:$W,IF(G37="Wholesale",21,22),FALSE)/4,IF(F37=50,VLOOKUP($E37,'Master Data'!$B:$W,IF(G37="Wholesale",21,22),FALSE)/6,IF(F37=25,VLOOKUP($E37,'Master Data'!$B:$W,IF(G37="Wholesale",21,22),FALSE)/8,VLOOKUP($E37,'Master Data'!$B:$W,IF(G37="Wholesale",21,22),FALSE)/8)))))) -> 0 | V37: =+VLOOKUP($I37,'Master Data'!$B:$V,IF(G37="Wholesale",20,21),FALSE) -> 40 | W37: =IF(F37=1000,'Master Data'!$AB$32,IF(F37=500,'Master Data'!$AB$33,IF(F37=250,'Master Data'!$AB$34,IF(F37=100,'Master Data'!$AB$35,IF(F37=50,'Master Data'!$AB$36,IF(F37=25,'Master Data'!$AB$37,'Master Data'!$AB$38)))))) -> 56.55 | X37: =+((K37*F37)+$Q37+$R37+$U37+S37)*($J37/100) -> 37.110453 | Y37: =+(F37*K37)+Q37+R37+S37+U37+(IF(F37=1000,V37,IF(F37=500,V37/2,IF(F37=250,V37/4,IF(F37=100,V37/10,IF(F37=50,V37/20,V37/40)))))+X37) -> 448.21498 | Z37: =+Y37/L37 -> 448.21498 | AA37: =(F37*K37)+Q37+R37+S37+T37+U37+W37+X37 -> 475.88165 | AB37: =+((K37*F37)+$Q37+$R37+$U37+$S37+$T37)*($J37/100) -> 38.222119 | AC37: =(F37*K37)+Q37+R37+S37+T37+U37+AB37 -> 420.44331 | AD37: =AC37*1.5 -> 630.66497
A38: =+A37+1 -> 36 | B38: Sabji Masala Powder | C38: सब्जी मसाला | D38: In House Production | E38: Recycle Box | F38: 1000 | G38: Wholesale | H38: Maruthi Plastics | I38: Shree Maruthi Couriers-Local | J38: 10 | K38: =IF(D38="In House Production",INDEX('Master Data'!$H$552:$J$580,MATCH('Production Cost'!B38,'Master Data'!$H$552:$H$580,0),3),VLOOKUP($B38,'Master Data'!$B:$W,IF(G38="Wholesale",21,22),FALSE)) -> 0.78418859 | L38: 1 | M38: =INDEX('Master Data'!$B$323:$K$376,MATCH('Production Cost'!$B38,'Master Data'!$B$323:$B$376,0),MATCH('Production Cost'!F$3,'Master Data'!$B$323:$K$323,0)) -> 1 | N38: =IF(H38="Maruthi Plastics",INDEX('Master Data'!$B$202:$L$255,MATCH('Production Cost'!B38,'Master Data'!$B$202:$B$255,0),MATCH('Production Cost'!F38,'Master Data'!$B$202:$L$202,0)),INDEX('Master Data'!$B$261:$L$314,MATCH('Production Cost'!B38,'Master Data'!$B$261:$B$314,0),MATCH('Production Cost'!F38,'Master Data'!$B$261:$L$261,0))) -> One side Transparent Flat Bottom with Zipper (1000Gm) | O38: =1000/L38 -> 1000 | P38: =+VLOOKUP($N38,'Master Data'!$B:$W,IF(G38="Wholesale",21,22),FALSE) -> 11.94 | Q38: =+P38*M38 -> 11.94 | R38: =IF(G38="Wholesale",'Master Data'!$V$127*$M38,'Master Data'!$W$127*$M38) -> 2.2 | S38: =IF(G38="Wholesale",'Master Data'!$V$111*$M38,'Master Data'!$W$111*$M38) -> 3.0769231 | T38: =IF(F38=1000,'Master Data'!$AF$40,IF(F38=500,'Master Data'!$AF$39,IF(F38=250,'Master Data'!$AF$39,'Master Data'!$AF$38))) -> 11.116667 | U38: =IF(F38=1000,VLOOKUP($E38,'Master Data'!$B:$W,IF(G38="Wholesale",21,22),FALSE),IF(F38=500,VLOOKUP($E38,'Master Data'!$B:$W,IF(G38="Wholesale",21,22),FALSE)/2,IF(F38=250,VLOOKUP($E38,'Master Data'!$B:$W,IF(G38="Wholesale",21,22),FALSE)/3,IF(F38=100,VLOOKUP($E38,'Master Data'!$B:$W,IF(G38="Wholesale",21,22),FALSE)/4,IF(F38=50,VLOOKUP($E38,'Master Data'!$B:$W,IF(G38="Wholesale",21,22),FALSE)/6,IF(F38=25,VLOOKUP($E38,'Master Data'!$B:$W,IF(G38="Wholesale",21,22),FALSE)/8,VLOOKUP($E38,'Master Data'!$B:$W,IF(G38="Wholesale",21,22),FALSE)/8)))))) -> 0 | V38: =+VLOOKUP($I38,'Master Data'!$B:$V,IF(G38="Wholesale",20,21),FALSE) -> 40 | W38: =IF(F38=1000,'Master Data'!$AB$32,IF(F38=500,'Master Data'!$AB$33,IF(F38=250,'Master Data'!$AB$34,IF(F38=100,'Master Data'!$AB$35,IF(F38=50,'Master Data'!$AB$36,IF(F38=25,'Master Data'!$AB$37,'Master Data'!$AB$38)))))) -> 56.55 | X38: =+((K38*F38)+$Q38+$R38+$U38+S38)*($J38/100) -> 80.140551 | Y38: =+(F38*K38)+Q38+R38+S38+U38+(IF(F38=1000,V38,IF(F38=500,V38/2,IF(F38=250,V38/4,IF(F38=100,V38/10,IF(F38=50,V38/20,V38/40)))))+X38) -> 921.54606 | Z38: =+Y38/L38 -> 921.54606 | AA38: =(F38*K38)+Q38+R38+S38+T38+U38+W38+X38 -> 949.21273 | AB38: =+((K38*F38)+$Q38+$R38+$U38+$S38+$T38)*($J38/100) -> 81.252218 | AC38: =(F38*K38)+Q38+R38+S38+T38+U38+AB38 -> 893.77439 | AD38: =AC38*1.5 -> 1340.6616
A39: =+A38+1 -> 37 | B39: Pav Bhaji Masala | C39: पाव भाजी मसाला | D39: In House Production | E39: Recycle Box | F39: 1000 | G39: Wholesale | H39: Maruthi Plastics | I39: Shree Maruthi Couriers-Local | J39: 10 | K39: =IF(D39="In House Production",INDEX('Master Data'!$H$552:$J$580,MATCH('Production Cost'!B39,'Master Data'!$H$552:$H$580,0),3),VLOOKUP($B39,'Master Data'!$B:$W,IF(G39="Wholesale",21,22),FALSE)) -> 0.4816092 | L39: 1 | M39: =INDEX('Master Data'!$B$323:$K$376,MATCH('Production Cost'!$B39,'Master Data'!$B$323:$B$376,0),MATCH('Production Cost'!F$3,'Master Data'!$B$323:$K$323,0)) -> 1 | N39: =IF(H39="Maruthi Plastics",INDEX('Master Data'!$B$202:$L$255,MATCH('Production Cost'!B39,'Master Data'!$B$202:$B$255,0),MATCH('Production Cost'!F39,'Master Data'!$B$202:$L$202,0)),INDEX('Master Data'!$B$261:$L$314,MATCH('Production Cost'!B39,'Master Data'!$B$261:$B$314,0),MATCH('Production Cost'!F39,'Master Data'!$B$261:$L$261,0))) -> One side Transparent Flat Bottom with Zipper (1000Gm) | O39: =1000/L39 -> 1000 | P39: =+VLOOKUP($N39,'Master Data'!$B:$W,IF(G39="Wholesale",21,22),FALSE) -> 11.94 | Q39: =+P39*M39 -> 11.94 | R39: =IF(G39="Wholesale",'Master Data'!$V$127*$M39,'Master Data'!$W$127*$M39) -> 2.2 | S39: =IF(G39="Wholesale",'Master Data'!$V$111*$M39,'Master Data'!$W$111*$M39) -> 3.0769231 | T39: =IF(F39=1000,'Master Data'!$AF$40,IF(F39=500,'Master Data'!$AF$39,IF(F39=250,'Master Data'!$AF$39,'Master Data'!$AF$38))) -> 11.116667 | U39: =IF(F39=1000,VLOOKUP($E39,'Master Data'!$B:$W,IF(G39="Wholesale",21,22),FALSE),IF(F39=500,VLOOKUP($E39,'Master Data'!$B:$W,IF(G39="Wholesale",21,22),FALSE)/2,IF(F39=250,VLOOKUP($E39,'Master Data'!$B:$W,IF(G39="Wholesale",21,22),FALSE)/3,IF(F39=100,VLOOKUP($E39,'Master Data'!$B:$W,IF(G39="Wholesale",21,22),FALSE)/4,IF(F39=50,VLOOKUP($E39,'Master Data'!$B:$W,IF(G39="Wholesale",21,22),FALSE)/6,IF(F39=25,VLOOKUP($E39,'Master Data'!$B:$W,IF(G39="Wholesale",21,22),FALSE)/8,VLOOKUP($E39,'Master Data'!$B:$W,IF(G39="Wholesale",21,22),FALSE)/8)))))) -> 0 | V39: =+VLOOKUP($I39,'Master Data'!$B:$V,IF(G39="Wholesale",20,21),FALSE) -> 40 | W39: =IF(F39=1000,'Master Data'!$AB$32,IF(F39=500,'Master Data'!$AB$33,IF(F39=250,'Master Data'!$AB$34,IF(F39=100,'Master Data'!$AB$35,IF(F39=50,'Master Data'!$AB$36,IF(F39=25,'Master Data'!$AB$37,'Master Data'!$AB$38)))))) -> 56.55 | X39: =+((K39*F39)+$Q39+$R39+$U39+S39)*($J39/100) -> 49.882613 | Y39: =+(F39*K39)+Q39+R39+S39+U39+(IF(F39=1000,V39,IF(F39=500,V39/2,IF(F39=250,V39/4,IF(F39=100,V39/10,IF(F39=50,V39/20,V39/40)))))+X39) -> 588.70874 | Z39: =+Y39/L39 -> 588.70874 | AA39: =(F39*K39)+Q39+R39+S39+T39+U39+W39+X39 -> 616.37541 | AB39: =+((K39*F39)+$Q39+$R39+$U39+$S39+$T39)*($J39/100) -> 50.994279 | AC39: =(F39*K39)+Q39+R39+S39+T39+U39+AB39 -> 560.93707 | AD39: =AC39*1.5 -> 841.40561
A40: =+A39+1 -> 38 | B40: Bisibele Bhat Masala | C40: बिसिबेले भात मसाला | D40: In House Production | E40: Recycle Box | F40: 1000 | G40: Wholesale | H40: Maruthi Plastics | I40: Shree Maruthi Couriers-Local | J40: 10 | K40: =IF(D40="In House Production",INDEX('Master Data'!$H$552:$J$580,MATCH('Production Cost'!B40,'Master Data'!$H$552:$H$580,0),3),VLOOKUP($B40,'Master Data'!$B:$W,IF(G40="Wholesale",21,22),FALSE)) -> 0.32715958 | L40: 1 | M40: =INDEX('Master Data'!$B$323:$K$376,MATCH('Production Cost'!$B40,'Master Data'!$B$323:$B$376,0),MATCH('Production Cost'!F$3,'Master Data'!$B$323:$K$323,0)) -> 1 | N40: =IF(H40="Maruthi Plastics",INDEX('Master Data'!$B$202:$L$255,MATCH('Production Cost'!B40,'Master Data'!$B$202:$B$255,0),MATCH('Production Cost'!F40,'Master Data'!$B$202:$L$202,0)),INDEX('Master Data'!$B$261:$L$314,MATCH('Production Cost'!B40,'Master Data'!$B$261:$B$314,0),MATCH('Production Cost'!F40,'Master Data'!$B$261:$L$261,0))) -> One side Transparent Flat Bottom with Zipper (1000Gm) | O40: =1000/L40 -> 1000 | P40: =+VLOOKUP($N40,'Master Data'!$B:$W,IF(G40="Wholesale",21,22),FALSE) -> 11.94 | Q40: =+P40*M40 -> 11.94 | R40: =IF(G40="Wholesale",'Master Data'!$V$127*$M40,'Master Data'!$W$127*$M40) -> 2.2 | S40: =IF(G40="Wholesale",'Master Data'!$V$111*$M40,'Master Data'!$W$111*$M40) -> 3.0769231 | T40: =IF(F40=1000,'Master Data'!$AF$40,IF(F40=500,'Master Data'!$AF$39,IF(F40=250,'Master Data'!$AF$39,'Master Data'!$AF$38))) -> 11.116667 | U40: =IF(F40=1000,VLOOKUP($E40,'Master Data'!$B:$W,IF(G40="Wholesale",21,22),FALSE),IF(F40=500,VLOOKUP($E40,'Master Data'!$B:$W,IF(G40="Wholesale",21,22),FALSE)/2,IF(F40=250,VLOOKUP($E40,'Master Data'!$B:$W,IF(G40="Wholesale",21,22),FALSE)/3,IF(F40=100,VLOOKUP($E40,'Master Data'!$B:$W,IF(G40="Wholesale",21,22),FALSE)/4,IF(F40=50,VLOOKUP($E40,'Master Data'!$B:$W,IF(G40="Wholesale",21,22),FALSE)/6,IF(F40=25,VLOOKUP($E40,'Master Data'!$B:$W,IF(G40="Wholesale",21,22),FALSE)/8,VLOOKUP($E40,'Master Data'!$B:$W,IF(G40="Wholesale",21,22),FALSE)/8)))))) -> 0 | V40: =+VLOOKUP($I40,'Master Data'!$B:$V,IF(G40="Wholesale",20,21),FALSE) -> 40 | W40: =IF(F40=1000,'Master Data'!$AB$32,IF(F40=500,'Master Data'!$AB$33,IF(F40=250,'Master Data'!$AB$34,IF(F40=100,'Master Data'!$AB$35,IF(F40=50,'Master Data'!$AB$36,IF(F40=25,'Master Data'!$AB$37,'Master Data'!$AB$38)))))) -> 56.55 | X40: =+((K40*F40)+$Q40+$R40+$U40+S40)*($J40/100) -> 34.43765 | Y40: =+(F40*K40)+Q40+R40+S40+U40+(IF(F40=1000,V40,IF(F40=500,V40/2,IF(F40=250,V40/4,IF(F40=100,V40/10,IF(F40=50,V40/20,V40/40)))))+X40) -> 418.81415 | Z40: =+Y40/L40 -> 418.81415 | AA40: =(F40*K40)+Q40+R40+S40+T40+U40+W40+X40 -> 446.48082 | AB40: =+((K40*F40)+$Q40+$R40+$U40+$S40+$T40)*($J40/100) -> 35.549317 | AC40: =(F40*K40)+Q40+R40+S40+T40+U40+AB40 -> 391.04249 | AD40: =AC40*1.5 -> 586.56373
A41: =+A40+1 -> 39 | B41: Premium Chai Masala | C41: प्रीमियम चाय मसाला | D41: In House Production | E41: Recycle Box | F41: 1000 | G41: Wholesale | H41: Maruthi Plastics | I41: Shree Maruthi Couriers-Local | J41: 10 | K41: =IF(D41="In House Production",INDEX('Master Data'!$H$552:$J$580,MATCH('Production Cost'!B41,'Master Data'!$H$552:$H$580,0),3),VLOOKUP($B41,'Master Data'!$B:$W,IF(G41="Wholesale",21,22),FALSE)) -> 1.2879825 | L41: 1 | M41: =INDEX('Master Data'!$B$323:$K$376,MATCH('Production Cost'!$B41,'Master Data'!$B$323:$B$376,0),MATCH('Production Cost'!F$3,'Master Data'!$B$323:$K$323,0)) -> 1 | N41: =IF(H41="Maruthi Plastics",INDEX('Master Data'!$B$202:$L$255,MATCH('Production Cost'!B41,'Master Data'!$B$202:$B$255,0),MATCH('Production Cost'!F41,'Master Data'!$B$202:$L$202,0)),INDEX('Master Data'!$B$261:$L$314,MATCH('Production Cost'!B41,'Master Data'!$B$261:$B$314,0),MATCH('Production Cost'!F41,'Master Data'!$B$261:$L$261,0))) -> One side Transparent Flat Bottom with Zipper (1000Gm) | O41: =1000/L41 -> 1000 | P41: =+VLOOKUP($N41,'Master Data'!$B:$W,IF(G41="Wholesale",21,22),FALSE) -> 11.94 | Q41: =+P41*M41 -> 11.94 | R41: =IF(G41="Wholesale",'Master Data'!$V$127*$M41,'Master Data'!$W$127*$M41) -> 2.2 | S41: =IF(G41="Wholesale",'Master Data'!$V$111*$M41,'Master Data'!$W$111*$M41) -> 3.0769231 | T41: =IF(F41=1000,'Master Data'!$AF$40,IF(F41=500,'Master Data'!$AF$39,IF(F41=250,'Master Data'!$AF$39,'Master Data'!$AF$38))) -> 11.116667 | U41: =IF(F41=1000,VLOOKUP($E41,'Master Data'!$B:$W,IF(G41="Wholesale",21,22),FALSE),IF(F41=500,VLOOKUP($E41,'Master Data'!$B:$W,IF(G41="Wholesale",21,22),FALSE)/2,IF(F41=250,VLOOKUP($E41,'Master Data'!$B:$W,IF(G41="Wholesale",21,22),FALSE)/3,IF(F41=100,VLOOKUP($E41,'Master Data'!$B:$W,IF(G41="Wholesale",21,22),FALSE)/4,IF(F41=50,VLOOKUP($E41,'Master Data'!$B:$W,IF(G41="Wholesale",21,22),FALSE)/6,IF(F41=25,VLOOKUP($E41,'Master Data'!$B:$W,IF(G41="Wholesale",21,22),FALSE)/8,VLOOKUP($E41,'Master Data'!$B:$W,IF(G41="Wholesale",21,22),FALSE)/8)))))) -> 0 | V41: =+VLOOKUP($I41,'Master Data'!$B:$V,IF(G41="Wholesale",20,21),FALSE) -> 40 | W41: =IF(F41=1000,'Master Data'!$AB$32,IF(F41=500,'Master Data'!$AB$33,IF(F41=250,'Master Data'!$AB$34,IF(F41=100,'Master Data'!$AB$35,IF(F41=50,'Master Data'!$AB$36,IF(F41=25,'Master Data'!$AB$37,'Master Data'!$AB$38)))))) -> 56.55 | X41: =+((K41*F41)+$Q41+$R41+$U41+S41)*($J41/100) -> 130.51994 | Y41: =+(F41*K41)+Q41+R41+S41+U41+(IF(F41=1000,V41,IF(F41=500,V41/2,IF(F41=250,V41/4,IF(F41=100,V41/10,IF(F41=50,V41/20,V41/40)))))+X41) -> 1475.7194 | Z41: =+Y41/L41 -> 1475.7194 | AA41: =(F41*K41)+Q41+R41+S41+T41+U41+W41+X41 -> 1503.3861 | AB41: =+((K41*F41)+$Q41+$R41+$U41+$S41+$T41)*($J41/100) -> 131.63161 | AC41: =(F41*K41)+Q41+R41+S41+T41+U41+AB41 -> 1447.9477 | AD41: =AC41*1.5 -> 2171.9216
A42: =+A41+1 -> 40 | B42: Premium Kashmiri Saffron | C42: प्रीमियम कश्मीरी केसर | D42: =+VLOOKUP($B42,'Master Data'!$B$20:$W$197,2,FALSE) -> True Ventures | E42: Recycle Box | F42: 1000 | G42: Wholesale | H42: Maruthi Plastics | I42: Shree Maruthi Couriers-Local | J42: 10 | K42: =IF(D42="In House Production",INDEX('Master Data'!$H$552:$J$580,MATCH('Production Cost'!B42,'Master Data'!$H$552:$H$580,0),3),VLOOKUP($B42,'Master Data'!$B:$W,IF(G42="Wholesale",21,22),FALSE)) -> 183.5 | L42: 1 | M42: =INDEX('Master Data'!$B$323:$K$376,MATCH('Production Cost'!$B42,'Master Data'!$B$323:$B$376,0),MATCH('Production Cost'!F$3,'Master Data'!$B$323:$K$323,0)) -> 1 | N42: =IF(H42="Maruthi Plastics",INDEX('Master Data'!$B$202:$L$255,MATCH('Production Cost'!B42,'Master Data'!$B$202:$B$255,0),MATCH('Production Cost'!F42,'Master Data'!$B$202:$L$202,0)),INDEX('Master Data'!$B$261:$L$314,MATCH('Production Cost'!B42,'Master Data'!$B$261:$B$314,0),MATCH('Production Cost'!F42,'Master Data'!$B$261:$L$261,0))) -> 0 | O42: =1000/L42 -> 1000 | P42: =+VLOOKUP($N42,'Master Data'!$B:$W,IF(G42="Wholesale",21,22),FALSE) -> #N/A | Q42: =+P42*M42 -> #N/A | R42: =IF(G42="Wholesale",'Master Data'!$V$127*$M42,'Master Data'!$W$127*$M42) -> 2.2 | S42: =IF(G42="Wholesale",'Master Data'!$V$111*$M42,'Master Data'!$W$111*$M42) -> 3.0769231 | T42: =IF(F42=1000,'Master Data'!$AF$40,IF(F42=500,'Master Data'!$AF$39,IF(F42=250,'Master Data'!$AF$39,'Master Data'!$AF$38))) -> 11.116667 | U42: =IF(F42=1000,VLOOKUP($E42,'Master Data'!$B:$W,IF(G42="Wholesale",21,22),FALSE),IF(F42=500,VLOOKUP($E42,'Master Data'!$B:$W,IF(G42="Wholesale",21,22),FALSE)/2,IF(F42=250,VLOOKUP($E42,'Master Data'!$B:$W,IF(G42="Wholesale",21,22),FALSE)/3,IF(F42=100,VLOOKUP($E42,'Master Data'!$B:$W,IF(G42="Wholesale",21,22),FALSE)/4,IF(F42=50,VLOOKUP($E42,'Master Data'!$B:$W,IF(G42="Wholesale",21,22),FALSE)/6,IF(F42=25,VLOOKUP($E42,'Master Data'!$B:$W,IF(G42="Wholesale",21,22),FALSE)/8,VLOOKUP($E42,'Master Data'!$B:$W,IF(G42="Wholesale",21,22),FALSE)/8)))))) -> 0 | V42: =+VLOOKUP($I42,'Master Data'!$B:$V,IF(G42="Wholesale",20,21),FALSE) -> 40 | W42: =IF(F42=1000,'Master Data'!$AB$32,IF(F42=500,'Master Data'!$AB$33,IF(F42=250,'Master Data'!$AB$34,IF(F42=100,'Master Data'!$AB$35,IF(F42=50,'Master Data'!$AB$36,IF(F42=25,'Master Data'!$AB$37,'Master Data'!$AB$38)))))) -> 56.55 | X42: =+((K42*F42)+$Q42+$R42+$U42+S42)*($J42/100) -> #N/A | Y42: =+(F42*K42)+Q42+R42+S42+U42+(IF(F42=1000,V42,IF(F42=500,V42/2,IF(F42=250,V42/4,IF(F42=100,V42/10,IF(F42=50,V42/20,V42/40)))))+X42) -> #N/A | Z42: =+Y42/L42 -> #N/A | AA42: =(F42*K42)+Q42+R42+S42+T42+U42+W42+X42 -> #N/A | AB42: =+((K42*F42)+$Q42+$R42+$U42+$S42+$T42)*($J42/100) -> #N/A | AC42: =(F42*K42)+Q42+R42+S42+T42+U42+AB42 -> #N/A | AD42: =AC42*1.5 -> #N/A
A43: =+A42+1 -> 41 | B43: Gun Powder - Without Garlic | C43: गन पाउडर चटनी | D43: In House Production | E43: Recycle Box | F43: 1000 | G43: Wholesale | H43: Maruthi Plastics | I43: Shree Maruthi Couriers-Local | J43: 10 | K43: =IF(D43="In House Production",INDEX('Master Data'!$H$552:$J$580,MATCH('Production Cost'!B43,'Master Data'!$H$552:$H$580,0),3),VLOOKUP($B43,'Master Data'!$B:$W,IF(G43="Wholesale",21,22),FALSE)) -> 0.23149856 | L43: 1 | M43: =INDEX('Master Data'!$B$323:$K$376,MATCH('Production Cost'!$B43,'Master Data'!$B$323:$B$376,0),MATCH('Production Cost'!F$3,'Master Data'!$B$323:$K$323,0)) -> 1 | N43: =IF(H43="Maruthi Plastics",INDEX('Master Data'!$B$202:$L$255,MATCH('Production Cost'!B43,'Master Data'!$B$202:$B$255,0),MATCH('Production Cost'!F43,'Master Data'!$B$202:$L$202,0)),INDEX('Master Data'!$B$261:$L$314,MATCH('Production Cost'!B43,'Master Data'!$B$261:$B$314,0),MATCH('Production Cost'!F43,'Master Data'!$B$261:$L$261,0))) -> Flat Bottom Pouches With Normal Zipper 1 kg | O43: =1000/L43 -> 1000 | P43: =+VLOOKUP($N43,'Master Data'!$B:$W,IF(G43="Wholesale",21,22),FALSE) -> 16.13 | Q43: =+P43*M43 -> 16.13 | R43: =IF(G43="Wholesale",'Master Data'!$V$127*$M43,'Master Data'!$W$127*$M43) -> 2.2 | S43: =IF(G43="Wholesale",'Master Data'!$V$111*$M43,'Master Data'!$W$111*$M43) -> 3.0769231 | T43: =IF(F43=1000,'Master Data'!$AF$40,IF(F43=500,'Master Data'!$AF$39,IF(F43=250,'Master Data'!$AF$39,'Master Data'!$AF$38))) -> 11.116667 | U43: =IF(F43=1000,VLOOKUP($E43,'Master Data'!$B:$W,IF(G43="Wholesale",21,22),FALSE),IF(F43=500,VLOOKUP($E43,'Master Data'!$B:$W,IF(G43="Wholesale",21,22),FALSE)/2,IF(F43=250,VLOOKUP($E43,'Master Data'!$B:$W,IF(G43="Wholesale",21,22),FALSE)/3,IF(F43=100,VLOOKUP($E43,'Master Data'!$B:$W,IF(G43="Wholesale",21,22),FALSE)/4,IF(F43=50,VLOOKUP($E43,'Master Data'!$B:$W,IF(G43="Wholesale",21,22),FALSE)/6,IF(F43=25,VLOOKUP($E43,'Master Data'!$B:$W,IF(G43="Wholesale",21,22),FALSE)/8,VLOOKUP($E43,'Master Data'!$B:$W,IF(G43="Wholesale",21,22),FALSE)/8)))))) -> 0 | V43: =+VLOOKUP($I43,'Master Data'!$B:$V,IF(G43="Wholesale",20,21),FALSE) -> 40 | W43: =IF(F43=1000,'Master Data'!$AB$32,IF(F43=500,'Master Data'!$AB$33,IF(F43=250,'Master Data'!$AB$34,IF(F43=100,'Master Data'!$AB$35,IF(F43=50,'Master Data'!$AB$36,IF(F43=25,'Master Data'!$AB$37,'Master Data'!$AB$38)))))) -> 56.55 | X43: =+((K43*F43)+$Q43+$R43+$U43+S43)*($J43/100) -> 25.290548 | Y43: =+(F43*K43)+Q43+R43+S43+U43+(IF(F43=1000,V43,IF(F43=500,V43/2,IF(F43=250,V43/4,IF(F43=100,V43/10,IF(F43=50,V43/20,V43/40)))))+X43) -> 318.19603 | Z43: =+Y43/L43 -> 318.19603 | AA43: =(F43*K43)+Q43+R43+S43+T43+U43+W43+X43 -> 345.86269 | AB43: =+((K43*F43)+$Q43+$R43+$U43+$S43+$T43)*($J43/100) -> 26.402215 | AC43: =(F43*K43)+Q43+R43+S43+T43+U43+AB43 -> 290.42436 | AD43: =AC43*1.5 -> 435.63654
A44: =+A43+1 -> 42 | B44: Multi-grain Special Chutney Powder | C44: मल्टी ग्रेन स्पेशल चटनी पाउडर | D44: In House Production | E44: Recycle Box | F44: 1000 | G44: Wholesale | H44: Maruthi Plastics | I44: Shree Maruthi Couriers-Local | J44: 10 | K44: =IF(D44="In House Production",INDEX('Master Data'!$H$552:$J$580,MATCH('Production Cost'!B44,'Master Data'!$H$552:$H$580,0),3),VLOOKUP($B44,'Master Data'!$B:$W,IF(G44="Wholesale",21,22),FALSE)) -> 0.210837 | L44: 1 | M44: =INDEX('Master Data'!$B$323:$K$376,MATCH('Production Cost'!$B44,'Master Data'!$B$323:$B$376,0),MATCH('Production Cost'!F$3,'Master Data'!$B$323:$K$323,0)) -> 1 | N44: =IF(H44="Maruthi Plastics",INDEX('Master Data'!$B$202:$L$255,MATCH('Production Cost'!B44,'Master Data'!$B$202:$B$255,0),MATCH('Production Cost'!F44,'Master Data'!$B$202:$L$202,0)),INDEX('Master Data'!$B$261:$L$314,MATCH('Production Cost'!B44,'Master Data'!$B$261:$B$314,0),MATCH('Production Cost'!F44,'Master Data'!$B$261:$L$261,0))) -> Flat Bottom Pouches With Normal Zipper 1 kg | O44: =1000/L44 -> 1000 | P44: =+VLOOKUP($N44,'Master Data'!$B:$W,IF(G44="Wholesale",21,22),FALSE) -> 16.13 | Q44: =+P44*M44 -> 16.13 | R44: =IF(G44="Wholesale",'Master Data'!$V$127*$M44,'Master Data'!$W$127*$M44) -> 2.2 | S44: =IF(G44="Wholesale",'Master Data'!$V$111*$M44,'Master Data'!$W$111*$M44) -> 3.0769231 | T44: =IF(F44=1000,'Master Data'!$AF$40,IF(F44=500,'Master Data'!$AF$39,IF(F44=250,'Master Data'!$AF$39,'Master Data'!$AF$38))) -> 11.116667 | U44: =IF(F44=1000,VLOOKUP($E44,'Master Data'!$B:$W,IF(G44="Wholesale",21,22),FALSE),IF(F44=500,VLOOKUP($E44,'Master Data'!$B:$W,IF(G44="Wholesale",21,22),FALSE)/2,IF(F44=250,VLOOKUP($E44,'Master Data'!$B:$W,IF(G44="Wholesale",21,22),FALSE)/3,IF(F44=100,VLOOKUP($E44,'Master Data'!$B:$W,IF(G44="Wholesale",21,22),FALSE)/4,IF(F44=50,VLOOKUP($E44,'Master Data'!$B:$W,IF(G44="Wholesale",21,22),FALSE)/6,IF(F44=25,VLOOKUP($E44,'Master Data'!$B:$W,IF(G44="Wholesale",21,22),FALSE)/8,VLOOKUP($E44,'Master Data'!$B:$W,IF(G44="Wholesale",21,22),FALSE)/8)))))) -> 0 | V44: =+VLOOKUP($I44,'Master Data'!$B:$V,IF(G44="Wholesale",20,21),FALSE) -> 40 | W44: =IF(F44=1000,'Master Data'!$AB$32,IF(F44=500,'Master Data'!$AB$33,IF(F44=250,'Master Data'!$AB$34,IF(F44=100,'Master Data'!$AB$35,IF(F44=50,'Master Data'!$AB$36,IF(F44=25,'Master Data'!$AB$37,'Master Data'!$AB$38)))))) -> 56.55 | X44: =+((K44*F44)+$Q44+$R44+$U44+S44)*($J44/100) -> 23.224392 | Y44: =+(F44*K44)+Q44+R44+S44+U44+(IF(F44=1000,V44,IF(F44=500,V44/2,IF(F44=250,V44/4,IF(F44=100,V44/10,IF(F44=50,V44/20,V44/40)))))+X44) -> 295.46832 | Z44: =+Y44/L44 -> 295.46832 | AA44: =(F44*K44)+Q44+R44+S44+T44+U44+W44+X44 -> 323.13498 | AB44: =+((K44*F44)+$Q44+$R44+$U44+$S44+$T44)*($J44/100) -> 24.336059 | AC44: =(F44*K44)+Q44+R44+S44+T44+U44+AB44 -> 267.69665 | AD44: =AC44*1.5 -> 401.54497
A45: =+A44+1 -> 43 | B45: Peanut Chutney Powder - Without Garlic | C45: मूंगफली चटनी पाउडर | D45: In House Production | E45: Recycle Box | F45: 1000 | G45: Wholesale | H45: Maruthi Plastics | I45: Shree Maruthi Couriers-Local | J45: 10 | K45: =IF(D45="In House Production",INDEX('Master Data'!$H$552:$J$580,MATCH('Production Cost'!B45,'Master Data'!$H$552:$H$580,0),3),VLOOKUP($B45,'Master Data'!$B:$W,IF(G45="Wholesale",21,22),FALSE)) -> 0.18899548 | L45: 1 | M45: =INDEX('Master Data'!$B$323:$K$376,MATCH('Production Cost'!$B45,'Master Data'!$B$323:$B$376,0),MATCH('Production Cost'!F$3,'Master Data'!$B$323:$K$323,0)) -> 1 | N45: =IF(H45="Maruthi Plastics",INDEX('Master Data'!$B$202:$L$255,MATCH('Production Cost'!B45,'Master Data'!$B$202:$B$255,0),MATCH('Production Cost'!F45,'Master Data'!$B$202:$L$202,0)),INDEX('Master Data'!$B$261:$L$314,MATCH('Production Cost'!B45,'Master Data'!$B$261:$B$314,0),MATCH('Production Cost'!F45,'Master Data'!$B$261:$L$261,0))) -> Flat Bottom Pouches With Normal Zipper 1 kg | O45: =1000/L45 -> 1000 | P45: =+VLOOKUP($N45,'Master Data'!$B:$W,IF(G45="Wholesale",21,22),FALSE) -> 16.13 | Q45: =+P45*M45 -> 16.13 | R45: =IF(G45="Wholesale",'Master Data'!$V$127*$M45,'Master Data'!$W$127*$M45) -> 2.2 | S45: =IF(G45="Wholesale",'Master Data'!$V$111*$M45,'Master Data'!$W$111*$M45) -> 3.0769231 | T45: =IF(F45=1000,'Master Data'!$AF$40,IF(F45=500,'Master Data'!$AF$39,IF(F45=250,'Master Data'!$AF$39,'Master Data'!$AF$38))) -> 11.116667 | U45: =IF(F45=1000,VLOOKUP($E45,'Master Data'!$B:$W,IF(G45="Wholesale",21,22),FALSE),IF(F45=500,VLOOKUP($E45,'Master Data'!$B:$W,IF(G45="Wholesale",21,22),FALSE)/2,IF(F45=250,VLOOKUP($E45,'Master Data'!$B:$W,IF(G45="Wholesale",21,22),FALSE)/3,IF(F45=100,VLOOKUP($E45,'Master Data'!$B:$W,IF(G45="Wholesale",21,22),FALSE)/4,IF(F45=50,VLOOKUP($E45,'Master Data'!$B:$W,IF(G45="Wholesale",21,22),FALSE)/6,IF(F45=25,VLOOKUP($E45,'Master Data'!$B:$W,IF(G45="Wholesale",21,22),FALSE)/8,VLOOKUP($E45,'Master Data'!$B:$W,IF(G45="Wholesale",21,22),FALSE)/8)))))) -> 0 | V45: =+VLOOKUP($I45,'Master Data'!$B:$V,IF(G45="Wholesale",20,21),FALSE) -> 40 | W45: =IF(F45=1000,'Master Data'!$AB$32,IF(F45=500,'Master Data'!$AB$33,IF(F45=250,'Master Data'!$AB$34,IF(F45=100,'Master Data'!$AB$35,IF(F45=50,'Master Data'!$AB$36,IF(F45=25,'Master Data'!$AB$37,'Master Data'!$AB$38)))))) -> 56.55 | X45: =+((K45*F45)+$Q45+$R45+$U45+S45)*($J45/100) -> 21.040241 | Y45: =+(F45*K45)+Q45+R45+S45+U45+(IF(F45=1000,V45,IF(F45=500,V45/2,IF(F45=250,V45/4,IF(F45=100,V45/10,IF(F45=50,V45/20,V45/40)))))+X45) -> 271.44265 | Z45: =+Y45/L45 -> 271.44265 | AA45: =(F45*K45)+Q45+R45+S45+T45+U45+W45+X45 -> 299.10931 | AB45: =+((K45*F45)+$Q45+$R45+$U45+$S45+$T45)*($J45/100) -> 22.151907 | AC45: =(F45*K45)+Q45+R45+S45+T45+U45+AB45 -> 243.67098 | AD45: =AC45*1.5 -> 365.50647
A46: =+A45+1 -> 44 | B46: Pulihora Masala Powder | C46: पुलिहोरा | D46: In House Production | E46: Recycle Box | F46: 1000 | G46: Wholesale | H46: Maruthi Plastics | I46: Shree Maruthi Couriers-Local | J46: 10 | K46: =IF(D46="In House Production",INDEX('Master Data'!$H$552:$J$580,MATCH('Production Cost'!B46,'Master Data'!$H$552:$H$580,0),3),VLOOKUP($B46,'Master Data'!$B:$W,IF(G46="Wholesale",21,22),FALSE)) -> 0.28101194 | L46: 1 | M46: =INDEX('Master Data'!$B$323:$K$376,MATCH('Production Cost'!$B46,'Master Data'!$B$323:$B$376,0),MATCH('Production Cost'!F$3,'Master Data'!$B$323:$K$323,0)) -> 1 | N46: =IF(H46="Maruthi Plastics",INDEX('Master Data'!$B$202:$L$255,MATCH('Production Cost'!B46,'Master Data'!$B$202:$B$255,0),MATCH('Production Cost'!F46,'Master Data'!$B$202:$L$202,0)),INDEX('Master Data'!$B$261:$L$314,MATCH('Production Cost'!B46,'Master Data'!$B$261:$B$314,0),MATCH('Production Cost'!F46,'Master Data'!$B$261:$L$261,0))) -> Flat Bottom Pouches With Normal Zipper 1 kg | O46: =1000/L46 -> 1000 | P46: =+VLOOKUP($N46,'Master Data'!$B:$W,IF(G46="Wholesale",21,22),FALSE) -> 16.13 | Q46: =+P46*M46 -> 16.13 | R46: =IF(G46="Wholesale",'Master Data'!$V$127*$M46,'Master Data'!$W$127*$M46) -> 2.2 | S46: =IF(G46="Wholesale",'Master Data'!$V$111*$M46,'Master Data'!$W$111*$M46) -> 3.0769231 | T46: =IF(F46=1000,'Master Data'!$AF$40,IF(F46=500,'Master Data'!$AF$39,IF(F46=250,'Master Data'!$AF$39,'Master Data'!$AF$38))) -> 11.116667 | U46: =IF(F46=1000,VLOOKUP($E46,'Master Data'!$B:$W,IF(G46="Wholesale",21,22),FALSE),IF(F46=500,VLOOKUP($E46,'Master Data'!$B:$W,IF(G46="Wholesale",21,22),FALSE)/2,IF(F46=250,VLOOKUP($E46,'Master Data'!$B:$W,IF(G46="Wholesale",21,22),FALSE)/3,IF(F46=100,VLOOKUP($E46,'Master Data'!$B:$W,IF(G46="Wholesale",21,22),FALSE)/4,IF(F46=50,VLOOKUP($E46,'Master Data'!$B:$W,IF(G46="Wholesale",21,22),FALSE)/6,IF(F46=25,VLOOKUP($E46,'Master Data'!$B:$W,IF(G46="Wholesale",21,22),FALSE)/8,VLOOKUP($E46,'Master Data'!$B:$W,IF(G46="Wholesale",21,22),FALSE)/8)))))) -> 0 | V46: =+VLOOKUP($I46,'Master Data'!$B:$V,IF(G46="Wholesale",20,21),FALSE) -> 40 | W46: =IF(F46=1000,'Master Data'!$AB$32,IF(F46=500,'Master Data'!$AB$33,IF(F46=250,'Master Data'!$AB$34,IF(F46=100,'Master Data'!$AB$35,IF(F46=50,'Master Data'!$AB$36,IF(F46=25,'Master Data'!$AB$37,'Master Data'!$AB$38)))))) -> 56.55 | X46: =+((K46*F46)+$Q46+$R46+$U46+S46)*($J46/100) -> 30.241886 | Y46: =+(F46*K46)+Q46+R46+S46+U46+(IF(F46=1000,V46,IF(F46=500,V46/2,IF(F46=250,V46/4,IF(F46=100,V46/10,IF(F46=50,V46/20,V46/40)))))+X46) -> 372.66075 | Z46: =+Y46/L46 -> 372.66075 | AA46: =(F46*K46)+Q46+R46+S46+T46+U46+W46+X46 -> 400.32742 | AB46: =+((K46*F46)+$Q46+$R46+$U46+$S46+$T46)*($J46/100) -> 31.353553 | AC46: =(F46*K46)+Q46+R46+S46+T46+U46+AB46 -> 344.88908 | AD46: =AC46*1.5 -> 517.33363
A47: =+A46+1 -> 45 | B47: Multi-grain Metkut Powder | C47: मल्टीग्रैन मेतकूट पाउडर | D47: In House Production | E47: Recycle Box | F47: 1000 | G47: Wholesale | H47: Maruthi Plastics | I47: Shree Maruthi Couriers-Local | J47: 10 | K47: =IF(D47="In House Production",INDEX('Master Data'!$H$552:$J$580,MATCH('Production Cost'!B47,'Master Data'!$H$552:$H$580,0),3),VLOOKUP($B47,'Master Data'!$B:$W,IF(G47="Wholesale",21,22),FALSE)) -> 0.12519 | L47: 1 | M47: =INDEX('Master Data'!$B$323:$K$376,MATCH('Production Cost'!$B47,'Master Data'!$B$323:$B$376,0),MATCH('Production Cost'!F$3,'Master Data'!$B$323:$K$323,0)) -> 1 | N47: =IF(H47="Maruthi Plastics",INDEX('Master Data'!$B$202:$L$255,MATCH('Production Cost'!B47,'Master Data'!$B$202:$B$255,0),MATCH('Production Cost'!F47,'Master Data'!$B$202:$L$202,0)),INDEX('Master Data'!$B$261:$L$314,MATCH('Production Cost'!B47,'Master Data'!$B$261:$B$314,0),MATCH('Production Cost'!F47,'Master Data'!$B$261:$L$261,0))) -> Flat Bottom Pouches With Normal Zipper 1 kg | O47: =1000/L47 -> 1000 | P47: =+VLOOKUP($N47,'Master Data'!$B:$W,IF(G47="Wholesale",21,22),FALSE) -> 16.13 | Q47: =+P47*M47 -> 16.13 | R47: =IF(G47="Wholesale",'Master Data'!$V$127*$M47,'Master Data'!$W$127*$M47) -> 2.2 | S47: =IF(G47="Wholesale",'Master Data'!$V$111*$M47,'Master Data'!$W$111*$M47) -> 3.0769231 | T47: =IF(F47=1000,'Master Data'!$AF$40,IF(F47=500,'Master Data'!$AF$39,IF(F47=250,'Master Data'!$AF$39,'Master Data'!$AF$38))) -> 11.116667 | U47: =IF(F47=1000,VLOOKUP($E47,'Master Data'!$B:$W,IF(G47="Wholesale",21,22),FALSE),IF(F47=500,VLOOKUP($E47,'Master Data'!$B:$W,IF(G47="Wholesale",21,22),FALSE)/2,IF(F47=250,VLOOKUP($E47,'Master Data'!$B:$W,IF(G47="Wholesale",21,22),FALSE)/3,IF(F47=100,VLOOKUP($E47,'Master Data'!$B:$W,IF(G47="Wholesale",21,22),FALSE)/4,IF(F47=50,VLOOKUP($E47,'Master Data'!$B:$W,IF(G47="Wholesale",21,22),FALSE)/6,IF(F47=25,VLOOKUP($E47,'Master Data'!$B:$W,IF(G47="Wholesale",21,22),FALSE)/8,VLOOKUP($E47,'Master Data'!$B:$W,IF(G47="Wholesale",21,22),FALSE)/8)))))) -> 0 | V47: =+VLOOKUP($I47,'Master Data'!$B:$V,IF(G47="Wholesale",20,21),FALSE) -> 40 | W47: =IF(F47=1000,'Master Data'!$AB$32,IF(F47=500,'Master Data'!$AB$33,IF(F47=250,'Master Data'!$AB$34,IF(F47=100,'Master Data'!$AB$35,IF(F47=50,'Master Data'!$AB$36,IF(F47=25,'Master Data'!$AB$37,'Master Data'!$AB$38)))))) -> 56.55 | X47: =+((K47*F47)+$Q47+$R47+$U47+S47)*($J47/100) -> 14.659692 | Y47: =+(F47*K47)+Q47+R47+S47+U47+(IF(F47=1000,V47,IF(F47=500,V47/2,IF(F47=250,V47/4,IF(F47=100,V47/10,IF(F47=50,V47/20,V47/40)))))+X47) -> 201.25662 | Z47: =+Y47/L47 -> 201.25662 | AA47: =(F47*K47)+Q47+R47+S47+T47+U47+W47+X47 -> 228.92328 | AB47: =+((K47*F47)+$Q47+$R47+$U47+$S47+$T47)*($J47/100) -> 15.771359 | AC47: =(F47*K47)+Q47+R47+S47+T47+U47+AB47 -> 173.48495 | AD47: =AC47*1.5 -> 260.22742
A48: =+A47+1 -> 46 | B48: Immunity Booster | C48: इम्युनिटी बूस्टर | D48: In House Production | E48: Recycle Box | F48: 1000 | G48: Wholesale | H48: Maruthi Plastics | I48: Shree Maruthi Couriers-Local | J48: 10 | K48: =IF(D48="In House Production",INDEX('Master Data'!$H$552:$J$580,MATCH('Production Cost'!B48,'Master Data'!$H$552:$H$580,0),3),VLOOKUP($B48,'Master Data'!$B:$W,IF(G48="Wholesale",21,22),FALSE)) -> 0.57141498 | L48: 1 | M48: =INDEX('Master Data'!$B$323:$K$376,MATCH('Production Cost'!$B48,'Master Data'!$B$323:$B$376,0),MATCH('Production Cost'!F$3,'Master Data'!$B$323:$K$323,0)) -> 1 | N48: =IF(H48="Maruthi Plastics",INDEX('Master Data'!$B$202:$L$255,MATCH('Production Cost'!B48,'Master Data'!$B$202:$B$255,0),MATCH('Production Cost'!F48,'Master Data'!$B$202:$L$202,0)),INDEX('Master Data'!$B$261:$L$314,MATCH('Production Cost'!B48,'Master Data'!$B$261:$B$314,0),MATCH('Production Cost'!F48,'Master Data'!$B$261:$L$261,0))) -> Flat Bottom Pouches With Normal Zipper 1 kg | O48: =1000/L48 -> 1000 | P48: =+VLOOKUP($N48,'Master Data'!$B:$W,IF(G48="Wholesale",21,22),FALSE) -> 16.13 | Q48: =+P48*M48 -> 16.13 | R48: =IF(G48="Wholesale",'Master Data'!$V$127*$M48,'Master Data'!$W$127*$M48) -> 2.2 | S48: =IF(G48="Wholesale",'Master Data'!$V$111*$M48,'Master Data'!$W$111*$M48) -> 3.0769231 | T48: =IF(F48=1000,'Master Data'!$AF$40,IF(F48=500,'Master Data'!$AF$39,IF(F48=250,'Master Data'!$AF$39,'Master Data'!$AF$38))) -> 11.116667 | U48: =IF(F48=1000,VLOOKUP($E48,'Master Data'!$B:$W,IF(G48="Wholesale",21,22),FALSE),IF(F48=500,VLOOKUP($E48,'Master Data'!$B:$W,IF(G48="Wholesale",21,22),FALSE)/2,IF(F48=250,VLOOKUP($E48,'Master Data'!$B:$W,IF(G48="Wholesale",21,22),FALSE)/3,IF(F48=100,VLOOKUP($E48,'Master Data'!$B:$W,IF(G48="Wholesale",21,22),FALSE)/4,IF(F48=50,VLOOKUP($E48,'Master Data'!$B:$W,IF(G48="Wholesale",21,22),FALSE)/6,IF(F48=25,VLOOKUP($E48,'Master Data'!$B:$W,IF(G48="Wholesale",21,22),FALSE)/8,VLOOKUP($E48,'Master Data'!$B:$W,IF(G48="Wholesale",21,22),FALSE)/8)))))) -> 0 | V48: =+VLOOKUP($I48,'Master Data'!$B:$V,IF(G48="Wholesale",20,21),FALSE) -> 40 | W48: =IF(F48=1000,'Master Data'!$AB$32,IF(F48=500,'Master Data'!$AB$33,IF(F48=250,'Master Data'!$AB$34,IF(F48=100,'Master Data'!$AB$35,IF(F48=50,'Master Data'!$AB$36,IF(F48=25,'Master Data'!$AB$37,'Master Data'!$AB$38)))))) -> 56.55 | X48: =+((K48*F48)+$Q48+$R48+$U48+S48)*($J48/100) -> 59.28219 | Y48: =+(F48*K48)+Q48+R48+S48+U48+(IF(F48=1000,V48,IF(F48=500,V48/2,IF(F48=250,V48/4,IF(F48=100,V48/10,IF(F48=50,V48/20,V48/40)))))+X48) -> 692.1041 | Z48: =+Y48/L48 -> 692.1041 | AA48: =(F48*K48)+Q48+R48+S48+T48+U48+W48+X48 -> 719.77076 | AB48: =+((K48*F48)+$Q48+$R48+$U48+$S48+$T48)*($J48/100) -> 60.393857 | AC48: =(F48*K48)+Q48+R48+S48+T48+U48+AB48 -> 664.33243 | AD48: =AC48*1.5 -> 996.49864
A49: =+A48+1 -> 47 | B49: Spicy Lime Pickle | D49: =+VLOOKUP($B49,'Master Data'!$B$20:$W$197,2,FALSE) -> SMR | E49: Recycle Box | F49: 1000 | G49: Wholesale | H49: Maruthi Plastics | I49: Shree Maruthi Couriers-Local | J49: 11 | K49: =IF(D49="In House Production",INDEX('Master Data'!$H$552:$J$580,MATCH('Production Cost'!B49,'Master Data'!$H$552:$H$580,0),3),VLOOKUP($B49,'Master Data'!$B:$W,IF(G49="Wholesale",21,22),FALSE)) -> 0.322 | L49: 2 | M49: =INDEX('Master Data'!$B$323:$K$376,MATCH('Production Cost'!$B49,'Master Data'!$B$323:$B$376,0),MATCH('Production Cost'!F$3,'Master Data'!$B$323:$K$323,0)) -> 4 | N49: =IF(H49="Maruthi Plastics",INDEX('Master Data'!$B$202:$L$255,MATCH('Production Cost'!B49,'Master Data'!$B$202:$B$255,0),MATCH('Production Cost'!F49,'Master Data'!$B$202:$L$202,0)),INDEX('Master Data'!$B$261:$L$314,MATCH('Production Cost'!B49,'Master Data'!$B$261:$B$314,0),MATCH('Production Cost'!F49,'Master Data'!$B$261:$L$261,0))) -> Foil Stand Up Pouches 70 g | O49: =1000/L49 -> 500 | P49: =+VLOOKUP($N49,'Master Data'!$B:$W,IF(G49="Wholesale",21,22),FALSE) -> 4.227 | Q49: =+P49*M49 -> 16.908 | R49: =IF(G49="Wholesale",'Master Data'!$V$127*$M49,'Master Data'!$W$127*$M49) -> 8.8 | S49: =IF(G49="Wholesale",'Master Data'!$V$111*$M49,'Master Data'!$W$111*$M49) -> 12.307692 | T49: =IF(F49=1000,'Master Data'!$AF$40,IF(F49=500,'Master Data'!$AF$39,IF(F49=250,'Master Data'!$AF$39,'Master Data'!$AF$38))) -> 11.116667 | U49: =IF(F49=1000,VLOOKUP($E49,'Master Data'!$B:$W,IF(G49="Wholesale",21,22),FALSE),IF(F49=500,VLOOKUP($E49,'Master Data'!$B:$W,IF(G49="Wholesale",21,22),FALSE)/2,IF(F49=250,VLOOKUP($E49,'Master Data'!$B:$W,IF(G49="Wholesale",21,22),FALSE)/3,IF(F49=100,VLOOKUP($E49,'Master Data'!$B:$W,IF(G49="Wholesale",21,22),FALSE)/4,IF(F49=50,VLOOKUP($E49,'Master Data'!$B:$W,IF(G49="Wholesale",21,22),FALSE)/6,IF(F49=25,VLOOKUP($E49,'Master Data'!$B:$W,IF(G49="Wholesale",21,22),FALSE)/8,VLOOKUP($E49,'Master Data'!$B:$W,IF(G49="Wholesale",21,22),FALSE)/8)))))) -> 0 | V49: =+VLOOKUP($I49,'Master Data'!$B:$V,IF(G49="Wholesale",20,21),FALSE) -> 40 | W49: =IF(F49=1000,'Master Data'!$AB$32,IF(F49=500,'Master Data'!$AB$33,IF(F49=250,'Master Data'!$AB$34,IF(F49=100,'Master Data'!$AB$35,IF(F49=50,'Master Data'!$AB$36,IF(F49=25,'Master Data'!$AB$37,'Master Data'!$AB$38)))))) -> 56.55 | X49: =+((K49*F49)+$Q49+$R49+$U49+S49)*($J49/100) -> 39.601726 | Y49: =+(F49*K49)+Q49+R49+S49+U49+(IF(F49=1000,V49,IF(F49=500,V49/2,IF(F49=250,V49/4,IF(F49=100,V49/10,IF(F49=50,V49/20,V49/40)))))+X49) -> 439.61742 | Z49: =+Y49/L49 -> 219.80871 | AA49: =(F49*K49)+Q49+R49+S49+T49+U49+W49+X49 -> 467.28409 | AB49: =+((K49*F49)+$Q49+$R49+$U49+$S49+$T49)*($J49/100) -> 40.824559 | AC49: =(F49*K49)+Q49+R49+S49+T49+U49+AB49 -> 411.95692 | AD49: =AC49*1.5 -> 617.93538
A50: =+A49+1 -> 48 | B50: Very Spicy Mango Pickle | C50: आम का अचार – तीव्र मसालेदार | D50: =+VLOOKUP($B50,'Master Data'!$B$20:$W$197,2,FALSE) -> SMR | E50: Recycle Box | F50: 1000 | G50: Wholesale | H50: Maruthi Plastics | I50: Shree Maruthi Couriers-Local | J50: 10 | K50: =IF(D50="In House Production",INDEX('Master Data'!$H$552:$J$580,MATCH('Production Cost'!B50,'Master Data'!$H$552:$H$580,0),3),VLOOKUP($B50,'Master Data'!$B:$W,IF(G50="Wholesale",21,22),FALSE)) -> 0.322 | L50: 1 | M50: =INDEX('Master Data'!$B$323:$K$376,MATCH('Production Cost'!$B50,'Master Data'!$B$323:$B$376,0),MATCH('Production Cost'!F$3,'Master Data'!$B$323:$K$323,0)) -> 4 | N50: =IF(H50="Maruthi Plastics",INDEX('Master Data'!$B$202:$L$255,MATCH('Production Cost'!B50,'Master Data'!$B$202:$B$255,0),MATCH('Production Cost'!F50,'Master Data'!$B$202:$L$202,0)),INDEX('Master Data'!$B$261:$L$314,MATCH('Production Cost'!B50,'Master Data'!$B$261:$B$314,0),MATCH('Production Cost'!F50,'Master Data'!$B$261:$L$261,0))) -> Foil Stand Up Pouches 70 g | O50: =1000/L50 -> 1000 | P50: =+VLOOKUP($N50,'Master Data'!$B:$W,IF(G50="Wholesale",21,22),FALSE) -> 4.227 | Q50: =+P50*M50 -> 16.908 | R50: =IF(G50="Wholesale",'Master Data'!$V$127*$M50,'Master Data'!$W$127*$M50) -> 8.8 | S50: =IF(G50="Wholesale",'Master Data'!$V$111*$M50,'Master Data'!$W$111*$M50) -> 12.307692 | T50: =IF(F50=1000,'Master Data'!$AF$40,IF(F50=500,'Master Data'!$AF$39,IF(F50=250,'Master Data'!$AF$39,'Master Data'!$AF$38))) -> 11.116667 | U50: =IF(F50=1000,VLOOKUP($E50,'Master Data'!$B:$W,IF(G50="Wholesale",21,22),FALSE),IF(F50=500,VLOOKUP($E50,'Master Data'!$B:$W,IF(G50="Wholesale",21,22),FALSE)/2,IF(F50=250,VLOOKUP($E50,'Master Data'!$B:$W,IF(G50="Wholesale",21,22),FALSE)/3,IF(F50=100,VLOOKUP($E50,'Master Data'!$B:$W,IF(G50="Wholesale",21,22),FALSE)/4,IF(F50=50,VLOOKUP($E50,'Master Data'!$B:$W,IF(G50="Wholesale",21,22),FALSE)/6,IF(F50=25,VLOOKUP($E50,'Master Data'!$B:$W,IF(G50="Wholesale",21,22),FALSE)/8,VLOOKUP($E50,'Master Data'!$B:$W,IF(G50="Wholesale",21,22),FALSE)/8)))))) -> 0 | V50: =+VLOOKUP($I50,'Master Data'!$B:$V,IF(G50="Wholesale",20,21),FALSE) -> 40 | W50: =IF(F50=1000,'Master Data'!$AB$32,IF(F50=500,'Master Data'!$AB$33,IF(F50=250,'Master Data'!$AB$34,IF(F50=100,'Master Data'!$AB$35,IF(F50=50,'Master Data'!$AB$36,IF(F50=25,'Master Data'!$AB$37,'Master Data'!$AB$38)))))) -> 56.55 | X50: =+((K50*F50)+$Q50+$R50+$U50+S50)*($J50/100) -> 36.001569 | Y50: =+(F50*K50)+Q50+R50+S50+U50+(IF(F50=1000,V50,IF(F50=500,V50/2,IF(F50=250,V50/4,IF(F50=100,V50/10,IF(F50=50,V50/20,V50/40)))))+X50) -> 436.01726 | Z50: =+Y50/L50 -> 436.01726 | AA50: =(F50*K50)+Q50+R50+S50+T50+U50+W50+X50 -> 463.68393 | AB50: =+((K50*F50)+$Q50+$R50+$U50+$S50+$T50)*($J50/100) -> 37.113236 | AC50: =(F50*K50)+Q50+R50+S50+T50+U50+AB50 -> 408.24559 | AD50: =AC50*1.5 -> 612.36839
A51: =+A50+1 -> 49 | B51: Kapok Buds | C51: मराठी मोग्गू | D51: =+VLOOKUP($B51,'Master Data'!$B$20:$W$197,2,FALSE) -> Amazon | E51: Recycle Box | F51: 1000 | G51: Wholesale | H51: Maruthi Plastics | I51: Shree Maruthi Couriers-Local | J51: 10 | K51: =IF(D51="In House Production",INDEX('Master Data'!$H$552:$J$580,MATCH('Production Cost'!B51,'Master Data'!$H$552:$H$580,0),3),VLOOKUP($B51,'Master Data'!$B:$W,IF(G51="Wholesale",21,22),FALSE)) -> 1.07 | L51: 1 | M51: =INDEX('Master Data'!$B$323:$K$376,MATCH('Production Cost'!$B51,'Master Data'!$B$323:$B$376,0),MATCH('Production Cost'!F$3,'Master Data'!$B$323:$K$323,0)) -> 2 | N51: =IF(H51="Maruthi Plastics",INDEX('Master Data'!$B$202:$L$255,MATCH('Production Cost'!B51,'Master Data'!$B$202:$B$255,0),MATCH('Production Cost'!F51,'Master Data'!$B$202:$L$202,0)),INDEX('Master Data'!$B$261:$L$314,MATCH('Production Cost'!B51,'Master Data'!$B$261:$B$314,0),MATCH('Production Cost'!F51,'Master Data'!$B$261:$L$261,0))) -> One side Transparent Flat Bottom with Zipper (1000Gm) | O51: =1000/L51 -> 1000 | P51: =+VLOOKUP($N51,'Master Data'!$B:$W,IF(G51="Wholesale",21,22),FALSE) -> 11.94 | Q51: =+P51*M51 -> 23.88 | R51: =IF(G51="Wholesale",'Master Data'!$V$127*$M51,'Master Data'!$W$127*$M51) -> 4.4 | S51: =IF(G51="Wholesale",'Master Data'!$V$111*$M51,'Master Data'!$W$111*$M51) -> 6.1538462 | T51: =IF(F51=1000,'Master Data'!$AF$40,IF(F51=500,'Master Data'!$AF$39,IF(F51=250,'Master Data'!$AF$39,'Master Data'!$AF$38))) -> 11.116667 | U51: =IF(F51=1000,VLOOKUP($E51,'Master Data'!$B:$W,IF(G51="Wholesale",21,22),FALSE),IF(F51=500,VLOOKUP($E51,'Master Data'!$B:$W,IF(G51="Wholesale",21,22),FALSE)/2,IF(F51=250,VLOOKUP($E51,'Master Data'!$B:$W,IF(G51="Wholesale",21,22),FALSE)/3,IF(F51=100,VLOOKUP($E51,'Master Data'!$B:$W,IF(G51="Wholesale",21,22),FALSE)/4,IF(F51=50,VLOOKUP($E51,'Master Data'!$B:$W,IF(G51="Wholesale",21,22),FALSE)/6,IF(F51=25,VLOOKUP($E51,'Master Data'!$B:$W,IF(G51="Wholesale",21,22),FALSE)/8,VLOOKUP($E51,'Master Data'!$B:$W,IF(G51="Wholesale",21,22),FALSE)/8)))))) -> 0 | V51: =+VLOOKUP($I51,'Master Data'!$B:$V,IF(G51="Wholesale",20,21),FALSE) -> 40 | W51: =IF(F51=1000,'Master Data'!$AB$32,IF(F51=500,'Master Data'!$AB$33,IF(F51=250,'Master Data'!$AB$34,IF(F51=100,'Master Data'!$AB$35,IF(F51=50,'Master Data'!$AB$36,IF(F51=25,'Master Data'!$AB$37,'Master Data'!$AB$38)))))) -> 56.55 | X51: =+((K51*F51)+$Q51+$R51+$U51+S51)*($J51/100) -> 110.44338 | Y51: =+(F51*K51)+Q51+R51+S51+U51+(IF(F51=1000,V51,IF(F51=500,V51/2,IF(F51=250,V51/4,IF(F51=100,V51/10,IF(F51=50,V51/20,V51/40)))))+X51) -> 1254.8772 | Z51: =+Y51/L51 -> 1254.8772 | AA51: =(F51*K51)+Q51+R51+S51+T51+U51+W51+X51 -> 1282.5439 | AB51: =+((K51*F51)+$Q51+$R51+$U51+$S51+$T51)*($J51/100) -> 111.55505 | AC51: =(F51*K51)+Q51+R51+S51+T51+U51+AB51 -> 1227.1056 | AD51: =AC51*1.5 -> 1840.6583
A52: =+A51+1 -> 50 | B52: Kabab Chini | C52: कबाब चीनी | D52: =+VLOOKUP($B52,'Master Data'!$B$20:$W$197,2,FALSE) -> Chandan Enterprise | E52: Recycle Box | F52: 1000 | G52: Wholesale | H52: Maruthi Plastics | I52: Shree Maruthi Couriers-Local | J52: 10 | K52: =IF(D52="In House Production",INDEX('Master Data'!$H$552:$J$580,MATCH('Production Cost'!B52,'Master Data'!$H$552:$H$580,0),3),VLOOKUP($B52,'Master Data'!$B:$W,IF(G52="Wholesale",21,22),FALSE)) -> 1.4135238 | L52: 1 | M52: =INDEX('Master Data'!$B$323:$K$376,MATCH('Production Cost'!$B52,'Master Data'!$B$323:$B$376,0),MATCH('Production Cost'!F$3,'Master Data'!$B$323:$K$323,0)) -> 1 | N52: =IF(H52="Maruthi Plastics",INDEX('Master Data'!$B$202:$L$255,MATCH('Production Cost'!B52,'Master Data'!$B$202:$B$255,0),MATCH('Production Cost'!F52,'Master Data'!$B$202:$L$202,0)),INDEX('Master Data'!$B$261:$L$314,MATCH('Production Cost'!B52,'Master Data'!$B$261:$B$314,0),MATCH('Production Cost'!F52,'Master Data'!$B$261:$L$261,0))) -> One side Transparent Flat Bottom with Zipper (1000Gm) | O52: =1000/L52 -> 1000 | P52: =+VLOOKUP($N52,'Master Data'!$B:$W,IF(G52="Wholesale",21,22),FALSE) -> 11.94 | Q52: =+P52*M52 -> 11.94 | R52: =IF(G52="Wholesale",'Master Data'!$V$127*$M52,'Master Data'!$W$127*$M52) -> 2.2 | S52: =IF(G52="Wholesale",'Master Data'!$V$111*$M52,'Master Data'!$W$111*$M52) -> 3.0769231 | T52: =IF(F52=1000,'Master Data'!$AF$40,IF(F52=500,'Master Data'!$AF$39,IF(F52=250,'Master Data'!$AF$39,'Master Data'!$AF$38))) -> 11.116667 | U52: =IF(F52=1000,VLOOKUP($E52,'Master Data'!$B:$W,IF(G52="Wholesale",21,22),FALSE),IF(F52=500,VLOOKUP($E52,'Master Data'!$B:$W,IF(G52="Wholesale",21,22),FALSE)/2,IF(F52=250,VLOOKUP($E52,'Master Data'!$B:$W,IF(G52="Wholesale",21,22),FALSE)/3,IF(F52=100,VLOOKUP($E52,'Master Data'!$B:$W,IF(G52="Wholesale",21,22),FALSE)/4,IF(F52=50,VLOOKUP($E52,'Master Data'!$B:$W,IF(G52="Wholesale",21,22),FALSE)/6,IF(F52=25,VLOOKUP($E52,'Master Data'!$B:$W,IF(G52="Wholesale",21,22),FALSE)/8,VLOOKUP($E52,'Master Data'!$B:$W,IF(G52="Wholesale",21,22),FALSE)/8)))))) -> 0 | V52: =+VLOOKUP($I52,'Master Data'!$B:$V,IF(G52="Wholesale",20,21),FALSE) -> 40 | W52: =IF(F52=1000,'Master Data'!$AB$32,IF(F52=500,'Master Data'!$AB$33,IF(F52=250,'Master Data'!$AB$34,IF(F52=100,'Master Data'!$AB$35,IF(F52=50,'Master Data'!$AB$36,IF(F52=25,'Master Data'!$AB$37,'Master Data'!$AB$38)))))) -> 56.55 | X52: =+((K52*F52)+$Q52+$R52+$U52+S52)*($J52/100) -> 143.07407 | Y52: =+(F52*K52)+Q52+R52+S52+U52+(IF(F52=1000,V52,IF(F52=500,V52/2,IF(F52=250,V52/4,IF(F52=100,V52/10,IF(F52=50,V52/20,V52/40)))))+X52) -> 1613.8148 | Z52: =+Y52/L52 -> 1613.8148 | AA52: =(F52*K52)+Q52+R52+S52+T52+U52+W52+X52 -> 1641.4815 | AB52: =+((K52*F52)+$Q52+$R52+$U52+$S52+$T52)*($J52/100) -> 144.18574 | AC52: =(F52*K52)+Q52+R52+S52+T52+U52+AB52 -> 1586.0431 | AD52: =AC52*1.5 -> 2379.0647
A53: =+A52+1 -> 51 | B53: Black Cumin | C53: काला जीरा | D53: =+VLOOKUP($B53,'Master Data'!$B$20:$W$197,2,FALSE) -> Chandan Enterprise | E53: Recycle Box | F53: 1000 | G53: Wholesale | H53: Maruthi Plastics | I53: Shree Maruthi Couriers-Local | J53: 10 | K53: =IF(D53="In House Production",INDEX('Master Data'!$H$552:$J$580,MATCH('Production Cost'!B53,'Master Data'!$H$552:$H$580,0),3),VLOOKUP($B53,'Master Data'!$B:$W,IF(G53="Wholesale",21,22),FALSE)) -> 1.1087619 | L53: 1 | M53: =INDEX('Master Data'!$B$323:$K$376,MATCH('Production Cost'!$B53,'Master Data'!$B$323:$B$376,0),MATCH('Production Cost'!F$3,'Master Data'!$B$323:$K$323,0)) -> 1 | N53: =IF(H53="Maruthi Plastics",INDEX('Master Data'!$B$202:$L$255,MATCH('Production Cost'!B53,'Master Data'!$B$202:$B$255,0),MATCH('Production Cost'!F53,'Master Data'!$B$202:$L$202,0)),INDEX('Master Data'!$B$261:$L$314,MATCH('Production Cost'!B53,'Master Data'!$B$261:$B$314,0),MATCH('Production Cost'!F53,'Master Data'!$B$261:$L$261,0))) -> One side Transparent Flat Bottom with Zipper (1000Gm) | O53: =1000/L53 -> 1000 | P53: =+VLOOKUP($N53,'Master Data'!$B:$W,IF(G53="Wholesale",21,22),FALSE) -> 11.94 | Q53: =+P53*M53 -> 11.94 | R53: =IF(G53="Wholesale",'Master Data'!$V$127*$M53,'Master Data'!$W$127*$M53) -> 2.2 | S53: =IF(G53="Wholesale",'Master Data'!$V$111*$M53,'Master Data'!$W$111*$M53) -> 3.0769231 | T53: =IF(F53=1000,'Master Data'!$AF$40,IF(F53=500,'Master Data'!$AF$39,IF(F53=250,'Master Data'!$AF$39,'Master Data'!$AF$38))) -> 11.116667 | U53: =IF(F53=1000,VLOOKUP($E53,'Master Data'!$B:$W,IF(G53="Wholesale",21,22),FALSE),IF(F53=500,VLOOKUP($E53,'Master Data'!$B:$W,IF(G53="Wholesale",21,22),FALSE)/2,IF(F53=250,VLOOKUP($E53,'Master Data'!$B:$W,IF(G53="Wholesale",21,22),FALSE)/3,IF(F53=100,VLOOKUP($E53,'Master Data'!$B:$W,IF(G53="Wholesale",21,22),FALSE)/4,IF(F53=50,VLOOKUP($E53,'Master Data'!$B:$W,IF(G53="Wholesale",21,22),FALSE)/6,IF(F53=25,VLOOKUP($E53,'Master Data'!$B:$W,IF(G53="Wholesale",21,22),FALSE)/8,VLOOKUP($E53,'Master Data'!$B:$W,IF(G53="Wholesale",21,22),FALSE)/8)))))) -> 0 | V53: =+VLOOKUP($I53,'Master Data'!$B:$V,IF(G53="Wholesale",20,21),FALSE) -> 40 | W53: =IF(F53=1000,'Master Data'!$AB$32,IF(F53=500,'Master Data'!$AB$33,IF(F53=250,'Master Data'!$AB$34,IF(F53=100,'Master Data'!$AB$35,IF(F53=50,'Master Data'!$AB$36,IF(F53=25,'Master Data'!$AB$37,'Master Data'!$AB$38)))))) -> 56.55 | X53: =+((K53*F53)+$Q53+$R53+$U53+S53)*($J53/100) -> 112.59788 | Y53: =+(F53*K53)+Q53+R53+S53+U53+(IF(F53=1000,V53,IF(F53=500,V53/2,IF(F53=250,V53/4,IF(F53=100,V53/10,IF(F53=50,V53/20,V53/40)))))+X53) -> 1278.5767 | Z53: =+Y53/L53 -> 1278.5767 | AA53: =(F53*K53)+Q53+R53+S53+T53+U53+W53+X53 -> 1306.2434 | AB53: =+((K53*F53)+$Q53+$R53+$U53+$S53+$T53)*($J53/100) -> 113.70955 | AC53: =(F53*K53)+Q53+R53+S53+T53+U53+AB53 -> 1250.805 | AD53: =AC53*1.5 -> 1876.2076
A54: =+A53+1 -> 52 | B54: Stone Flower | C54: दगड़ फूल | D54: =+VLOOKUP($B54,'Master Data'!$B$20:$W$197,2,FALSE) -> Ali Kikabai | E54: Recycle Box | F54: 1000 | G54: Wholesale | H54: Maruthi Plastics | I54: Shree Maruthi Couriers-Local | J54: 10 | K54: =IF(D54="In House Production",INDEX('Master Data'!$H$552:$J$580,MATCH('Production Cost'!B54,'Master Data'!$H$552:$H$580,0),3),VLOOKUP($B54,'Master Data'!$B:$W,IF(G54="Wholesale",21,22),FALSE)) -> 0.4836 | L54: 1 | M54: =INDEX('Master Data'!$B$323:$K$376,MATCH('Production Cost'!$B54,'Master Data'!$B$323:$B$376,0),MATCH('Production Cost'!F$3,'Master Data'!$B$323:$K$323,0)) -> 4 | N54: =IF(H54="Maruthi Plastics",INDEX('Master Data'!$B$202:$L$255,MATCH('Production Cost'!B54,'Master Data'!$B$202:$B$255,0),MATCH('Production Cost'!F54,'Master Data'!$B$202:$L$202,0)),INDEX('Master Data'!$B$261:$L$314,MATCH('Production Cost'!B54,'Master Data'!$B$261:$B$314,0),MATCH('Production Cost'!F54,'Master Data'!$B$261:$L$261,0))) -> One side Transparent Flat Bottom with Zipper (1000Gm) | O54: =1000/L54 -> 1000 | P54: =+VLOOKUP($N54,'Master Data'!$B:$W,IF(G54="Wholesale",21,22),FALSE) -> 11.94 | Q54: =+P54*M54 -> 47.76 | R54: =IF(G54="Wholesale",'Master Data'!$V$127*$M54,'Master Data'!$W$127*$M54) -> 8.8 | S54: =IF(G54="Wholesale",'Master Data'!$V$111*$M54,'Master Data'!$W$111*$M54) -> 12.307692 | T54: =IF(F54=1000,'Master Data'!$AF$40,IF(F54=500,'Master Data'!$AF$39,IF(F54=250,'Master Data'!$AF$39,'Master Data'!$AF$38))) -> 11.116667 | U54: =IF(F54=1000,VLOOKUP($E54,'Master Data'!$B:$W,IF(G54="Wholesale",21,22),FALSE),IF(F54=500,VLOOKUP($E54,'Master Data'!$B:$W,IF(G54="Wholesale",21,22),FALSE)/2,IF(F54=250,VLOOKUP($E54,'Master Data'!$B:$W,IF(G54="Wholesale",21,22),FALSE)/3,IF(F54=100,VLOOKUP($E54,'Master Data'!$B:$W,IF(G54="Wholesale",21,22),FALSE)/4,IF(F54=50,VLOOKUP($E54,'Master Data'!$B:$W,IF(G54="Wholesale",21,22),FALSE)/6,IF(F54=25,VLOOKUP($E54,'Master Data'!$B:$W,IF(G54="Wholesale",21,22),FALSE)/8,VLOOKUP($E54,'Master Data'!$B:$W,IF(G54="Wholesale",21,22),FALSE)/8)))))) -> 0 | V54: =+VLOOKUP($I54,'Master Data'!$B:$V,IF(G54="Wholesale",20,21),FALSE) -> 40 | W54: =IF(F54=1000,'Master Data'!$AB$32,IF(F54=500,'Master Data'!$AB$33,IF(F54=250,'Master Data'!$AB$34,IF(F54=100,'Master Data'!$AB$35,IF(F54=50,'Master Data'!$AB$36,IF(F54=25,'Master Data'!$AB$37,'Master Data'!$AB$38)))))) -> 56.55 | X54: =+((K54*F54)+$Q54+$R54+$U54+S54)*($J54/100) -> 55.246769 | Y54: =+(F54*K54)+Q54+R54+S54+U54+(IF(F54=1000,V54,IF(F54=500,V54/2,IF(F54=250,V54/4,IF(F54=100,V54/10,IF(F54=50,V54/20,V54/40)))))+X54) -> 647.71446 | Z54: =+Y54/L54 -> 647.71446 | AA54: =(F54*K54)+Q54+R54+S54+T54+U54+W54+X54 -> 675.38113 | AB54: =+((K54*F54)+$Q54+$R54+$U54+$S54+$T54)*($J54/100) -> 56.358436 | AC54: =(F54*K54)+Q54+R54+S54+T54+U54+AB54 -> 619.94279 | AD54: =AC54*1.5 -> 929.91419
A55: =+A54+1 -> 53 | B55: Fenugreek Seeds | D55: =+VLOOKUP($B55,'Master Data'!$B$20:$W$197,2,FALSE) -> Chandan Enterprise | E55: Recycle Box | F55: 1000 | G55: Wholesale | H55: Maruthi Plastics | I55: Shree Maruthi Couriers-Local | J55: 10 | K55: =IF(D55="In House Production",INDEX('Master Data'!$H$552:$J$580,MATCH('Production Cost'!B55,'Master Data'!$H$552:$H$580,0),3),VLOOKUP($B55,'Master Data'!$B:$W,IF(G55="Wholesale",21,22),FALSE)) -> 0.1 | L55: 1 | M55: =INDEX('Master Data'!$B$323:$K$376,MATCH('Production Cost'!$B55,'Master Data'!$B$323:$B$376,0),MATCH('Production Cost'!F$3,'Master Data'!$B$323:$K$323,0)) -> 1 | N55: =IF(H55="Maruthi Plastics",INDEX('Master Data'!$B$202:$L$255,MATCH('Production Cost'!B55,'Master Data'!$B$202:$B$255,0),MATCH('Production Cost'!F55,'Master Data'!$B$202:$L$202,0)),INDEX('Master Data'!$B$261:$L$314,MATCH('Production Cost'!B55,'Master Data'!$B$261:$B$314,0),MATCH('Production Cost'!F55,'Master Data'!$B$261:$L$261,0))) -> One side Transparent Flat Bottom with Zipper (1000Gm) | O55: =1000/L55 -> 1000 | P55: =+VLOOKUP($N55,'Master Data'!$B:$W,IF(G55="Wholesale",21,22),FALSE) -> 11.94 | Q55: =+P55*M55 -> 11.94 | R55: =IF(G55="Wholesale",'Master Data'!$V$127*$M55,'Master Data'!$W$127*$M55) -> 2.2 | S55: =IF(G55="Wholesale",'Master Data'!$V$111*$M55,'Master Data'!$W$111*$M55) -> 3.0769231 | T55: =IF(F55=1000,'Master Data'!$AF$40,IF(F55=500,'Master Data'!$AF$39,IF(F55=250,'Master Data'!$AF$39,'Master Data'!$AF$38))) -> 11.116667 | U55: =IF(F55=1000,VLOOKUP($E55,'Master Data'!$B:$W,IF(G55="Wholesale",21,22),FALSE),IF(F55=500,VLOOKUP($E55,'Master Data'!$B:$W,IF(G55="Wholesale",21,22),FALSE)/2,IF(F55=250,VLOOKUP($E55,'Master Data'!$B:$W,IF(G55="Wholesale",21,22),FALSE)/3,IF(F55=100,VLOOKUP($E55,'Master Data'!$B:$W,IF(G55="Wholesale",21,22),FALSE)/4,IF(F55=50,VLOOKUP($E55,'Master Data'!$B:$W,IF(G55="Wholesale",21,22),FALSE)/6,IF(F55=25,VLOOKUP($E55,'Master Data'!$B:$W,IF(G55="Wholesale",21,22),FALSE)/8,VLOOKUP($E55,'Master Data'!$B:$W,IF(G55="Wholesale",21,22),FALSE)/8)))))) -> 0 | V55: =+VLOOKUP($I55,'Master Data'!$B:$V,IF(G55="Wholesale",20,21),FALSE) -> 40 | W55: =IF(F55=1000,'Master Data'!$AB$32,IF(F55=500,'Master Data'!$AB$33,IF(F55=250,'Master Data'!$AB$34,IF(F55=100,'Master Data'!$AB$35,IF(F55=50,'Master Data'!$AB$36,IF(F55=25,'Master Data'!$AB$37,'Master Data'!$AB$38)))))) -> 56.55 | X55: =+((K55*F55)+$Q55+$R55+$U55+S55)*($J55/100) -> 11.721692 | Y55: =+(F55*K55)+Q55+R55+S55+U55+(IF(F55=1000,V55,IF(F55=500,V55/2,IF(F55=250,V55/4,IF(F55=100,V55/10,IF(F55=50,V55/20,V55/40)))))+X55) -> 168.93862 | Z55: =+Y55/L55 -> 168.93862 | AA55: =(F55*K55)+Q55+R55+S55+T55+U55+W55+X55 -> 196.60528 | AB55: =+((K55*F55)+$Q55+$R55+$U55+$S55+$T55)*($J55/100) -> 12.833359 | AC55: =(F55*K55)+Q55+R55+S55+T55+U55+AB55 -> 141.16695 | AD55: =AC55*1.5 -> 211.75042
